Workbook

Sheet Output＞＞

Sheet PL
A1: 単位：千円、％
D3: 24年 | E3: 25年 | F3: 26年 | G3: 27年 | H3: 28年 | I3: 29年 | J3: 30年 | K3: 31年 | L3: 32年 | M3: 33年 | N3: 34年
A4: 全体 | B4: 売上高計 | D4: =D38 -> 213867.54 | E4: =E38 -> 398510.32 | F4: =F38 -> 887604.91 | G4: =G38 -> 1570742.7 | H4: =H38 -> 2355042.8 | I4: =I38 -> 3085274.9 | J4: =J38 -> 3765793.8 | K4: =K38 -> 4400581.2 | ... N4: =N38 -> 6065468.6
B5: 粗利 | D5: =D56 -> 141818.44 | E5: =E56 -> 315192.44 | F5: =F56 -> 783612.99 | G5: =G56 -> 1437511.8 | H5: =H56 -> 2190457.9 | I5: =I56 -> 2893098.4 | J5: =J56 -> 3549336.8 | K5: =K56 -> 4162757.3 | ... N5: =N56 -> 5777734.4
B6: 限界利益 | D6: =D74 -> 78150.005 | E6: =E74 -> 169988.04 | F6: =F74 -> 416077.98 | G6: =G74 -> 759305.2 | H6: =H74 -> 1152130.7 | I6: =I74 -> 1515355.1 | J6: =J74 -> 1851398.7 | K6: =K74 -> 2162470.5 | ... N6: =N74 -> 2965180.4
C7: 限界利益率 | D7: =D119 -> 0.36541311 | E7: =E119 -> 0.42655871 | F7: =F119 -> 0.46876485 | G7: =G119 -> 0.48340522 | H7: =H119 -> 0.48921859 | I7: =I119 -> 0.49115724 | J7: =J119 -> 0.4916357 | K7: =K119 -> 0.49140566 | ... N7: =N119 -> 0.48886254
B8: 直接利益 | D8: =D92 -> 48526.676 | E8: =E92 -> 23355.44 | F8: =F92 -> 214425.3 | G8: =G92 -> 525508.25 | H8: =H92 -> 889759.94 | I8: =I92 -> 1225293.9 | J8: =J92 -> 1534468.7 | K8: =K92 -> 1819435.9 | ... N8: =N92 -> 2547899.8
C9: 直接利益率 | D9: =D128 -> 0.22690061 | E9: =E128 -> 0.058606863 | F9: =F128 -> 0.24157742 | G9: =G128 -> 0.33456038 | H9: =H128 -> 0.37781052 | I9: =I128 -> 0.39714255 | J9: =J128 -> 0.4074755 | K9: =K128 -> 0.41345354 | ... N9: =N128 -> 0.42006645
B10: 営業利益 | D10: =D110 -> 48315.807 | E10: =E110 -> -2618.1223 | F10: =F110 -> 148572.95 | G10: =G110 -> 441478.86 | H10: =H110 -> 786748.93 | I10: =I110 -> 1104979.1 | J10: =J110 -> 1398326.5 | K10: =K110 -> 1668765.6 | ... N10: =N110 -> 2359973.2
C11: 営業利益率 | D11: =D137 -> 0.22591463 | E11: =E137 -> -0.006569773 | F11: =F137 -> 0.16738636 | G11: =G137 -> 0.28106378 | H11: =H137 -> 0.33406991 | I11: =I137 -> 0.35814608 | J11: =J137 -> 0.37132318 | K11: =K137 -> 0.37921482 | ... N11: =N137 -> 0.3890834
D13: 24年 | E13: 25年 | F13: 26年 | G13: 27年 | H13: 28年 | I13: 29年 | J13: 30年 | K13: 31年 | L13: 32年 | M13: 33年 | N13: 34年
A14: アプリ | B14: 売上高計 | D14: =D39 -> 31621.632 | E14: =E39 -> 160180.98 | F14: =F39 -> 538435.04 | G14: =G39 -> 1064836.5 | H14: =H39 -> 1674358.4 | I14: =I39 -> 2241213.9 | J14: =J39 -> 2768389.5 | K14: =K39 -> 3258662.7 | ... N14: =N39 -> 4533009
B15: 粗利 | D15: =D57 -> 31621.632 | E15: =E57 -> 160180.98 | F15: =F57 -> 538435.04 | G15: =G57 -> 1064836.5 | H15: =H57 -> 1674358.4 | I15: =I57 -> 2241213.9 | J15: =J57 -> 2768389.5 | K15: =K57 -> 3258662.7 | ... N15: =N57 -> 4533009
B16: 限界利益 | D16: =D75 -> 16776.923 | E16: =E75 -> 84984.353 | F16: =F75 -> 285667.83 | G16: =G75 -> 564951.2 | H16: =H75 -> 888334.36 | I16: =I75 -> 1189080.7 | J16: =J75 -> 1468774.8 | K16: =K75 -> 1728890.3 | ... N16: =N75 -> 2404997.4
C17: 限界利益率 | D17: =D120 -> 0.53055208 | E17: =E120 -> 0.53055208 | F17: =F120 -> 0.53055208 | G17: =G120 -> 0.53055208 | H17: =H120 -> 0.53055208 | I17: =I120 -> 0.53055208 | J17: =J120 -> 0.53055208 | K17: =K120 -> 0.53055208 | ... N17: =N120 -> 0.53055208
B18: 直接利益 | D18: =D93 -> 9238.9227 | E18: =E93 -> 17230.104 | F18: =F93 -> 176250.16 | G18: =G93 -> 441422.15 | H18: =H93 -> 749375.57 | I18: =I93 -> 1037071 | J18: =J93 -> 1305108.4 | K18: =K93 -> 1554616.3 | ... N18: =N93 -> 2203755.6
C19: 直接利益率 | D19: =D129 -> 0.29217096 | E19: =E129 -> 0.10756648 | F19: =F129 -> 0.32733784 | G19: =G129 -> 0.41454455 | H19: =H129 -> 0.44755982 | I19: =I129 -> 0.46272736 | J19: =J129 -> 0.47143238 | K19: =K129 -> 0.47707186 | ... N19: =N129 -> 0.48615735
B20: 営業利益 | D20: =D111 -> 9238.9227 | E20: =E111 -> 6230.1043 | F20: =F111 -> 135250.16 | G20: =G111 -> 395422.15 | H20: =H111 -> 698375.57 | I20: =I111 -> 981071 | J20: =J111 -> 1244108.4 | K20: =K111 -> 1488616.3 | ... N20: =N111 -> 2122755.6
C21: 営業利益率 | D21: =D138 -> 0.29217096 | E21: =E138 -> 0.038894158 | F21: =F138 -> 0.25119123 | G21: =G138 -> 0.37134543 | H21: =H138 -> 0.41710039 | I21: =I138 -> 0.4377409 | J21: =J138 -> 0.44939791 | K21: =K138 -> 0.45681816 | ... N21: =N138 -> 0.46828842
D23: 24年 | E23: 25年 | F23: 26年 | G23: 27年 | H23: 28年 | I23: 29年 | J23: 30年 | K23: 31年 | L23: 32年 | M23: 33年 | N23: 34年
A24: スタンド計 | B24: 売上高計 | D24: =SUM(D40:D42) -> 52989.912 | E24: =SUM(E40:E42) -> 109073.34 | F24: =SUM(F40:F42) -> 219913.87 | G24: =SUM(G40:G42) -> 376650.2 | H24: =SUM(H40:H42) -> 551428.33 | I24: =SUM(I40:I42) -> 714804.99 | J24: =SUM(J40:J42) -> 868148.37 | K24: =SUM(K40:K42) -> 1012662.4 | ... N24: =SUM(N40:N42) -> 1403203.6
B25: 粗利 | D25: =SUM(D58:D60) -> 36161.31 | E25: =SUM(E58:E60) -> 80975.961 | F25: =SUM(F58:F60) -> 171142.45 | G25: =SUM(G58:G60) -> 298639.81 | H25: =SUM(H58:H60) -> 442063.91 | I25: =SUM(I58:I60) -> 577849.03 | J25: =SUM(J58:J60) -> 706911.84 | K25: =SUM(K58:K60) -> 830059.03 | ... N25: =SUM(N58:N60) -> 1170689.9
B26: 限界利益 | D26: =SUM(D76:D78) -> 27230.486 | E26: =SUM(E76:E78) -> 50861.095 | F26: =SUM(F76:F78) -> 96267.551 | G26: =SUM(G76:G78) -> 160211.39 | H26: =SUM(H76:H78) -> 229653.75 | I26: =SUM(I76:I78) -> 292131.8 | J26: =SUM(J76:J78) -> 348481.28 | K26: =SUM(K76:K78) -> 399437.59 | ... N26: =SUM(N76:N78) -> 526040.43
C27: 限界利益率 | D27: =D26/D24 -> 0.51388056 | E27: =E26/E24 -> 0.46630182 | F27: =F26/F24 -> 0.43775117 | G27: =G26/G24 -> 0.42535858 | H27: =H26/H24 -> 0.41647071 | I27: =I26/I24 -> 0.40868741 | J27: =J26/J24 -> 0.40140751 | K27: =K26/K24 -> 0.39444298 | ... N27: =N26/N24 -> 0.37488531
B28: 直接利益 | D28: =SUM(D94:D96) -> 18590.156 | E28: =SUM(E94:E96) -> 7473.3436 | F28: =SUM(F94:F96) -> 29855.53 | G28: =SUM(G94:G96) -> 70383.13 | H28: =SUM(H94:H96) -> 124351.98 | I28: =SUM(I94:I96) -> 171086.39 | J28: =SUM(J94:J96) -> 211580.21 | K28: =SUM(K94:K96) -> 246618.63 | ... N28: =SUM(N94:N96) -> 325257.97
C29: 直接利益率 | D29: =D28/D24 -> 0.35082444 | E29: =E28/E24 -> 0.068516686 | F29: =F28/F24 -> 0.13576011 | G29: =G28/G24 -> 0.18686604 | H29: =H28/H24 -> 0.22550887 | I29: =I28/I24 -> 0.23934694 | J29: =J28/J24 -> 0.24371434 | K29: =K28/K24 -> 0.24353488 | ... N29: =N28/N24 -> 0.2317967
B30: 営業利益 | D30: =SUM(D112:D114) -> 18379.288 | E30: =SUM(E112:E114) -> 2869.7817 | F30: =SUM(F112:F114) -> 15603.177 | G30: =SUM(G112:G114) -> 42953.739 | H30: =SUM(H112:H114) -> 82940.966 | I30: =SUM(I112:I114) -> 117371.55 | J30: =SUM(J112:J114) -> 147038 | K30: =SUM(K112:K114) -> 172548.34 | ... N30: =SUM(N112:N114) -> 228931.3
C31: 営業利益率 | D31: =D30/D24 -> 0.34684503 | E31: =E30/E24 -> 0.02631057 | F31: =F30/F24 -> 0.070951311 | G31: =G30/G24 -> 0.11404146 | H31: =H30/H24 -> 0.15041115 | I31: =I30/I24 -> 0.1642008 | J31: =J30/J24 -> 0.16936967 | K31: =K30/K24 -> 0.17039078 | ... N31: =N30/N24 -> 0.16314902
D37: 24年 | E37: 25年 | F37: 26年 | G37: 27年 | H37: 28年 | I37: 29年 | J37: 30年 | K37: 31年 | L37: 32年 | M37: 33年 | N37: 34年
B38: 売上高計 | C38: サービス計 | D38: =SUM(D39:D46) -> 213867.54 | E38: =SUM(E39:E46) -> 398510.32 | F38: =SUM(F39:F46) -> 887604.91 | G38: =SUM(G39:G46) -> 1570742.7 | H38: =SUM(H39:H46) -> 2355042.8 | I38: =SUM(I39:I46) -> 3085274.9 | J38: =SUM(J39:J46) -> 3765793.8 | K38: =SUM(K39:K46) -> 4400581.2 | ... N38: =SUM(N39:N46) -> 6065468.6
B39: 売上高計 | C39: アプリ | D39: =売上高!E5 -> 31621.632 | E39: =売上高!F5 -> 160180.98 | F39: =売上高!G5 -> 538435.04 | G39: =売上高!H5 -> 1064836.5 | H39: =売上高!I5 -> 1674358.4 | I39: =売上高!J5 -> 2241213.9 | J39: =売上高!K5 -> 2768389.5 | K39: =売上高!L5 -> 3258662.7 | ... N39: =売上高!O5 -> 4533009
B40: 売上高計 | C40: スタンド（宅急便） | D40: =売上高!E6 -> 49489.56 | E40: =売上高!F6 -> 52260.975 | F40: =売上高!G6 -> 45989.658 | G40: =売上高!H6 -> 40470.899 | H40: =売上高!I6 -> 35614.391 | I40: =売上高!J6 -> 31340.664 | J40: =売上高!K6 -> 27579.785 | K40: =売上高!L6 -> 24270.211 | ... N40: =売上高!O6 -> 16539.469
B41: 売上高計 | C41: スタンド（ＦＳ） | D41: =売上高!E7 -> 1506.204 | E41: =売上高!F7 -> 32882.585 | F41: =売上高!G7 -> 101802.52 | G41: =売上高!H7 -> 195924.22 | H41: =売上高!I7 -> 295792.94 | I41: =売上高!J7 -> 383677.41 | J41: =売上高!K7 -> 461015.75 | K41: =売上高!L7 -> 529073.48 | ... N41: =売上高!O7 -> 688047.64
B42: 売上高計 | C42: スタンド（社外） | D42: =売上高!E8 -> 1994.148 | E42: =売上高!F8 -> 23929.776 | F42: =売上高!G8 -> 72121.686 | G42: =売上高!H8 -> 140255.08 | H42: =売上高!I8 -> 220021 | I42: =売上高!J8 -> 299786.92 | J42: =売上高!K8 -> 379552.84 | K42: =売上高!L8 -> 459318.76 | ... N42: =売上高!O8 -> 698616.52
B43: 売上高計 | C43: フロー（セミナー等） | D43: =売上高!E9 -> 45120 | E43: =売上高!F9 -> 45120 | F43: =売上高!G9 -> 45120 | G43: =売上高!H9 -> 45120 | H43: =売上高!I9 -> 45120 | I43: =売上高!J9 -> 45120 | J43: =売上高!K9 -> 45120 | K43: =売上高!L9 -> 45120 | ... N43: =売上高!O9 -> 45120
B44: 売上高計 | C44: ECストア | D44: =売上高!E10 -> 937 | E44: =売上高!F10 -> 937 | F44: =売上高!G10 -> 937 | G44: =売上高!H10 -> 937 | H44: =売上高!I10 -> 937 | I44: =売上高!J10 -> 937 | J44: =売上高!K10 -> 937 | K44: =売上高!L10 -> 937 | ... N44: =売上高!O10 -> 937
B45: 売上高計 | C45: 卸売 | D45: =売上高!E11 -> 49598 | E45: =売上高!F11 -> 49598 | F45: =売上高!G11 -> 49598 | G45: =売上高!H11 -> 49598 | H45: =売上高!I11 -> 49598 | I45: =売上高!J11 -> 49598 | J45: =売上高!K11 -> 49598 | K45: =売上高!L11 -> 49598 | ... N45: =売上高!O11 -> 49598
B46: 売上高計 | C46: 企業内手売 | D46: =売上高!E12 -> 33601 | E46: =売上高!F12 -> 33601 | F46: =売上高!G12 -> 33601 | G46: =売上高!H12 -> 33601 | H46: =売上高!I12 -> 33601 | I46: =売上高!J12 -> 33601 | J46: =売上高!K12 -> 33601 | K46: =売上高!L12 -> 33601 | ... N46: =売上高!O12 -> 33601
B47: 原価 | C47: サービス計 | D47: =SUM(D48:D55) -> 72049.102 | E47: =SUM(E48:E55) -> 83317.875 | F47: =SUM(F48:F55) -> 103991.92 | G47: =SUM(G48:G55) -> 133230.89 | H47: =SUM(H48:H55) -> 164584.92 | I47: =SUM(I48:I55) -> 192176.46 | J47: =SUM(J48:J55) -> 216457.03 | K47: =SUM(K48:K55) -> 237823.92 | ... N47: =SUM(N48:N55) -> 287734.25
B48: 原価 | C48: アプリ | D48: =D39*原価・変動費!E6 -> 0 | E48: =E39*原価・変動費!F6 -> 0 | F48: =F39*原価・変動費!G6 -> 0 | G48: =G39*原価・変動費!H6 -> 0 | H48: =H39*原価・変動費!I6 -> 0 | I48: =I39*原価・変動費!J6 -> 0 | J48: =J39*原価・変動費!K6 -> 0 | K48: =K39*原価・変動費!L6 -> 0 | ... N48: =N39*原価・変動費!O6 -> 0
B49: 原価 | C49: スタンド（宅急便） | D49: =D40*原価・変動費!E7 -> 16331.555 | E49: =E40*原価・変動費!F7 -> 17246.122 | F49: =F40*原価・変動費!G7 -> 15176.587 | G49: =G40*原価・変動費!H7 -> 13355.397 | H49: =H40*原価・変動費!I7 -> 11752.749 | I49: =I40*原価・変動費!J7 -> 10342.419 | J49: =J40*原価・変動費!K7 -> 9101.329 | K49: =K40*原価・変動費!L7 -> 8009.1695 | ... N49: =N40*原価・変動費!O7 -> 5458.0247
B50: 原価 | C50: スタンド（ＦＳ） | D50: =D41*原価・変動費!E8 -> 497.04732 | E50: =E41*原価・変動費!F8 -> 10851.253 | F50: =F41*原価・変動費!G8 -> 33594.832 | G50: =G41*原価・変動費!H8 -> 64654.993 | H50: =H41*原価・変動費!I8 -> 97611.67 | I50: =I41*原価・変動費!J8 -> 126613.55 | J50: =J41*原価・変動費!K8 -> 152135.2 | K50: =K41*原価・変動費!L8 -> 174594.25 | ... N50: =N41*原価・変動費!O8 -> 227055.72
B51: 原価 | C51: スタンド（社外） | D51: =D42*原価・変動費!E9 -> 0 | E51: =E42*原価・変動費!F9 -> 0 | F51: =F42*原価・変動費!G9 -> 0 | G51: =G42*原価・変動費!H9 -> 0 | H51: =H42*原価・変動費!I9 -> 0 | I51: =I42*原価・変動費!J9 -> 0 | J51: =J42*原価・変動費!K9 -> 0 | K51: =K42*原価・変動費!L9 -> 0 | ... N51: =N42*原価・変動費!O9 -> 0
B52: 原価 | C52: フロー（セミナー等） | D52: =D43*原価・変動費!E10 -> 0 | E52: =E43*原価・変動費!F10 -> 0 | F52: =F43*原価・変動費!G10 -> 0 | G52: =G43*原価・変動費!H10 -> 0 | H52: =H43*原価・変動費!I10 -> 0 | I52: =I43*原価・変動費!J10 -> 0 | J52: =J43*原価・変動費!K10 -> 0 | K52: =K43*原価・変動費!L10 -> 0 | ... N52: =N43*原価・変動費!O10 -> 0
B53: 原価 | C53: ECストア | D53: =D44*原価・変動費!E11 -> 421.65 | E53: =E44*原価・変動費!F11 -> 421.65 | F53: =F44*原価・変動費!G11 -> 421.65 | G53: =G44*原価・変動費!H11 -> 421.65 | H53: =H44*原価・変動費!I11 -> 421.65 | I53: =I44*原価・変動費!J11 -> 421.65 | J53: =J44*原価・変動費!K11 -> 421.65 | K53: =K44*原価・変動費!L11 -> 421.65 | ... N53: =N44*原価・変動費!O11 -> 421.65
B54: 原価 | C54: 卸売 | D54: =D45*原価・変動費!E12 -> 39678.4 | E54: =E45*原価・変動費!F12 -> 39678.4 | F54: =F45*原価・変動費!G12 -> 39678.4 | G54: =G45*原価・変動費!H12 -> 39678.4 | H54: =H45*原価・変動費!I12 -> 39678.4 | I54: =I45*原価・変動費!J12 -> 39678.4 | J54: =J45*原価・変動費!K12 -> 39678.4 | K54: =K45*原価・変動費!L12 -> 39678.4 | ... N54: =N45*原価・変動費!O12 -> 39678.4
B55: 原価 | C55: 企業内手売 | D55: =D46*原価・変動費!E13 -> 15120.45 | E55: =E46*原価・変動費!F13 -> 15120.45 | F55: =F46*原価・変動費!G13 -> 15120.45 | G55: =G46*原価・変動費!H13 -> 15120.45 | H55: =H46*原価・変動費!I13 -> 15120.45 | I55: =I46*原価・変動費!J13 -> 15120.45 | J55: =J46*原価・変動費!K13 -> 15120.45 | K55: =K46*原価・変動費!L13 -> 15120.45 | ... N55: =N46*原価・変動費!O13 -> 15120.45
B56: 粗利 | C56: サービス計 | D56: =SUM(D57:D64) -> 141818.44 | E56: =SUM(E57:E64) -> 315192.44 | F56: =SUM(F57:F64) -> 783612.99 | G56: =SUM(G57:G64) -> 1437511.8 | H56: =SUM(H57:H64) -> 2190457.9 | I56: =SUM(I57:I64) -> 2893098.4 | J56: =SUM(J57:J64) -> 3549336.8 | K56: =SUM(K57:K64) -> 4162757.3 | ... N56: =SUM(N57:N64) -> 5777734.4
B57: 粗利 | C57: アプリ | D57: =D39-D48 -> 31621.632 | E57: =E39-E48 -> 160180.98 | F57: =F39-F48 -> 538435.04 | G57: =G39-G48 -> 1064836.5 | H57: =H39-H48 -> 1674358.4 | I57: =I39-I48 -> 2241213.9 | J57: =J39-J48 -> 2768389.5 | K57: =K39-K48 -> 3258662.7 | ... N57: =N39-N48 -> 4533009
B58: 粗利 | C58: スタンド（宅急便） | D58: =D40-D49 -> 33158.005 | E58: =E40-E49 -> 35014.853 | F58: =F40-F49 -> 30813.071 | G58: =G40-G49 -> 27115.503 | H58: =H40-H49 -> 23861.642 | I58: =I40-I49 -> 20998.245 | J58: =J40-J49 -> 18478.456 | K58: =K40-K49 -> 16261.041 | ... N58: =N40-N49 -> 11081.444
B59: 粗利 | C59: スタンド（ＦＳ） | D59: =D41-D50 -> 1009.1567 | E59: =E41-E50 -> 22031.332 | F59: =F41-F50 -> 68207.689 | G59: =G41-G50 -> 131269.23 | H59: =H41-H50 -> 198181.27 | I59: =I41-I50 -> 257063.87 | J59: =J41-J50 -> 308880.55 | K59: =K41-K50 -> 354479.23 | ... N59: =N41-N50 -> 460991.92
B60: 粗利 | C60: スタンド（社外） | D60: =D42-D51 -> 1994.148 | E60: =E42-E51 -> 23929.776 | F60: =F42-F51 -> 72121.686 | G60: =G42-G51 -> 140255.08 | H60: =H42-H51 -> 220021 | I60: =I42-I51 -> 299786.92 | J60: =J42-J51 -> 379552.84 | K60: =K42-K51 -> 459318.76 | ... N60: =N42-N51 -> 698616.52
B61: 粗利 | C61: フロー（セミナー等） | D61: =D43-D52 -> 45120 | E61: =E43-E52 -> 45120 | F61: =F43-F52 -> 45120 | G61: =G43-G52 -> 45120 | H61: =H43-H52 -> 45120 | I61: =I43-I52 -> 45120 | J61: =J43-J52 -> 45120 | K61: =K43-K52 -> 45120 | ... N61: =N43-N52 -> 45120
B62: 粗利 | C62: ECストア | D62: =D44-D53 -> 515.35 | E62: =E44-E53 -> 515.35 | F62: =F44-F53 -> 515.35 | G62: =G44-G53 -> 515.35 | H62: =H44-H53 -> 515.35 | I62: =I44-I53 -> 515.35 | J62: =J44-J53 -> 515.35 | K62: =K44-K53 -> 515.35 | ... N62: =N44-N53 -> 515.35
B63: 粗利 | C63: 卸売 | D63: =D45-D54 -> 9919.6 | E63: =E45-E54 -> 9919.6 | F63: =F45-F54 -> 9919.6 | G63: =G45-G54 -> 9919.6 | H63: =H45-H54 -> 9919.6 | I63: =I45-I54 -> 9919.6 | J63: =J45-J54 -> 9919.6 | K63: =K45-K54 -> 9919.6 | ... N63: =N45-N54 -> 9919.6
B64: 粗利 | C64: 企業内手売 | D64: =D46-D55 -> 18480.55 | E64: =E46-E55 -> 18480.55 | F64: =F46-F55 -> 18480.55 | G64: =G46-G55 -> 18480.55 | H64: =H46-H55 -> 18480.55 | I64: =I46-I55 -> 18480.55 | J64: =J46-J55 -> 18480.55 | K64: =K46-K55 -> 18480.55 | ... N64: =N46-N55 -> 18480.55
B65: 変動費計 | C65: サービス計 | D65: =SUM(D66:D73) -> 63668.437 | E65: =SUM(E66:E73) -> 145204.4 | F65: =SUM(F66:F73) -> 367535.01 | G65: =SUM(G66:G73) -> 678206.58 | H65: =SUM(H66:H73) -> 1038327.1 | I65: =SUM(I66:I73) -> 1377743.3 | J65: =SUM(J66:J73) -> 1697938.1 | K65: =SUM(K66:K73) -> 2000286.8 | ... N65: =SUM(N66:N73) -> 2812554
B66: 変動費計 | C66: アプリ | D66: =D39*原価・変動費!E15 -> 14844.709 | E66: =E39*原価・変動費!F15 -> 75196.627 | F66: =F39*原価・変動費!G15 -> 252767.21 | G66: =G39*原価・変動費!H15 -> 499885.26 | H66: =H39*原価・変動費!I15 -> 786024.09 | I66: =I39*原価・変動費!J15 -> 1052133.2 | J66: =J39*原価・変動費!K15 -> 1299614.7 | K66: =K39*原価・変動費!L15 -> 1529772.4 | ... N66: =N39*原価・変動費!O15 -> 2128011.6
B67: 変動費計 | C67: スタンド（宅急便） | D67: =D40*原価・変動費!E16 -> 7126.4966 | E67: =E40*原価・変動費!F16 -> 7525.5805 | F67: =F40*原価・変動費!G16 -> 6622.5108 | G67: =G40*原価・変動費!H16 -> 5827.8095 | H67: =H40*原価・変動費!I16 -> 5128.4724 | I67: =I40*原価・変動費!J16 -> 4513.0557 | J67: =J40*原価・変動費!K16 -> 3971.489 | K67: =K40*原価・変動費!L16 -> 3494.9103 | ... N67: =N40*原価・変動費!O16 -> 2381.6835
B68: 変動費計 | C68: スタンド（ＦＳ） | D68: =D41*原価・変動費!E17 -> 95.342713 | E68: =E41*原価・変動費!F17 -> 2081.4676 | F68: =F41*原価・変動費!G17 -> 6444.0996 | G68: =G41*原価・変動費!H17 -> 12402.003 | H68: =H41*原価・変動費!I17 -> 18723.693 | I68: =I41*原価・変動費!J17 -> 24286.78 | J68: =J41*原価・変動費!K17 -> 29182.297 | K68: =K41*原価・変動費!L17 -> 33490.351 | ... N68: =N41*原価・変動費!O17 -> 43553.416
B69: 変動費計 | C69: スタンド（社外） | D69: =D42*原価・変動費!E18 -> 1708.9848 | E69: =E42*原価・変動費!F18 -> 20507.818 | F69: =F42*原価・変動費!G18 -> 61808.285 | G69: =G42*原価・変動費!H18 -> 120198.6 | H69: =H42*原価・変動費!I18 -> 188557.99 | I69: =I42*原価・変動費!J18 -> 256917.39 | J69: =J42*原価・変動費!K18 -> 325276.78 | K69: =K42*原価・変動費!L18 -> 393636.17 | ... N69: =N42*原価・変動費!O18 -> 598714.35
B70: 変動費計 | C70: フロー（セミナー等） | D70: =D43*原価・変動費!E19 -> 23611.296 | E70: =E43*原価・変動費!F19 -> 23611.296 | F70: =F43*原価・変動費!G19 -> 23611.296 | G70: =G43*原価・変動費!H19 -> 23611.296 | H70: =H43*原価・変動費!I19 -> 23611.296 | I70: =I43*原価・変動費!J19 -> 23611.296 | J70: =J43*原価・変動費!K19 -> 23611.296 | K70: =K43*原価・変動費!L19 -> 23611.296 | ... N70: =N43*原価・変動費!O19 -> 23611.296
B71: 変動費計 | C71: ECストア | D71: =D44*原価・変動費!E20 -> 361.3072 | E71: =E44*原価・変動費!F20 -> 361.3072 | F71: =F44*原価・変動費!G20 -> 361.3072 | G71: =G44*原価・変動費!H20 -> 361.3072 | H71: =H44*原価・変動費!I20 -> 361.3072 | I71: =I44*原価・変動費!J20 -> 361.3072 | J71: =J44*原価・変動費!K20 -> 361.3072 | K71: =K44*原価・変動費!L20 -> 361.3072 | ... N71: =N44*原価・変動費!O20 -> 361.3072
B72: 変動費計 | C72: 卸売 | D72: =D45*原価・変動費!E21 -> 2479.9 | E72: =E45*原価・変動費!F21 -> 2479.9 | F72: =F45*原価・変動費!G21 -> 2479.9 | G72: =G45*原価・変動費!H21 -> 2479.9 | H72: =H45*原価・変動費!I21 -> 2479.9 | I72: =I45*原価・変動費!J21 -> 2479.9 | J72: =J45*原価・変動費!K21 -> 2479.9 | K72: =K45*原価・変動費!L21 -> 2479.9 | ... N72: =N45*原価・変動費!O21 -> 2479.9
B73: 変動費計 | C73: 企業内手売 | D73: =D46*原価・変動費!E22 -> 13440.4 | E73: =E46*原価・変動費!F22 -> 13440.4 | F73: =F46*原価・変動費!G22 -> 13440.4 | G73: =G46*原価・変動費!H22 -> 13440.4 | H73: =H46*原価・変動費!I22 -> 13440.4 | I73: =I46*原価・変動費!J22 -> 13440.4 | J73: =J46*原価・変動費!K22 -> 13440.4 | K73: =K46*原価・変動費!L22 -> 13440.4 | ... N73: =N46*原価・変動費!O22 -> 13440.4
B74: 限界利益 | C74: サービス計 | D74: =SUM(D75:D82) -> 78150.005 | E74: =SUM(E75:E82) -> 169988.04 | F74: =SUM(F75:F82) -> 416077.98 | G74: =SUM(G75:G82) -> 759305.2 | H74: =SUM(H75:H82) -> 1152130.7 | I74: =SUM(I75:I82) -> 1515355.1 | J74: =SUM(J75:J82) -> 1851398.7 | K74: =SUM(K75:K82) -> 2162470.5 | ... N74: =SUM(N75:N82) -> 2965180.4
B75: 限界利益 | C75: アプリ | D75: =D57-D66 -> 16776.923 | E75: =E57-E66 -> 84984.353 | F75: =F57-F66 -> 285667.83 | G75: =G57-G66 -> 564951.2 | H75: =H57-H66 -> 888334.36 | I75: =I57-I66 -> 1189080.7 | J75: =J57-J66 -> 1468774.8 | K75: =K57-K66 -> 1728890.3 | ... N75: =N57-N66 -> 2404997.4
B76: 限界利益 | C76: スタンド（宅急便） | D76: =D58-D67 -> 26031.509 | E76: =E58-E67 -> 27489.273 | F76: =F58-F67 -> 24190.56 | G76: =G58-G67 -> 21287.693 | H76: =H58-H67 -> 18733.17 | I76: =I58-I67 -> 16485.189 | J76: =J58-J67 -> 14506.967 | K76: =K58-K67 -> 12766.131 | ... N76: =N58-N67 -> 8699.7606
B77: 限界利益 | C77: スタンド（ＦＳ） | D77: =D59-D68 -> 913.81397 | E77: =E59-E68 -> 19949.864 | F77: =F59-F68 -> 61763.589 | G77: =G59-G68 -> 118867.22 | H77: =H59-H68 -> 179457.58 | I77: =I59-I68 -> 232777.09 | J77: =J59-J68 -> 279698.25 | K77: =K59-K68 -> 320988.88 | ... N77: =N59-N68 -> 417438.5
B78: 限界利益 | C78: スタンド（社外） | D78: =D60-D69 -> 285.16316 | E78: =E60-E69 -> 3421.958 | F78: =F60-F69 -> 10313.401 | G78: =G60-G69 -> 20056.476 | H78: =H60-H69 -> 31463.002 | I78: =I60-I69 -> 42869.529 | J78: =J60-J69 -> 54276.056 | K78: =K60-K69 -> 65682.582 | ... N78: =N60-N69 -> 99902.162
B79: 限界利益 | C79: フロー（セミナー等） | D79: =D61-D70 -> 21508.704 | E79: =E61-E70 -> 21508.704 | F79: =F61-F70 -> 21508.704 | G79: =G61-G70 -> 21508.704 | H79: =H61-H70 -> 21508.704 | I79: =I61-I70 -> 21508.704 | J79: =J61-J70 -> 21508.704 | K79: =K61-K70 -> 21508.704 | ... N79: =N61-N70 -> 21508.704
B80: 限界利益 | C80: ECストア | D80: =D62-D71 -> 154.0428 | E80: =E62-E71 -> 154.0428 | F80: =F62-F71 -> 154.0428 | G80: =G62-G71 -> 154.0428 | H80: =H62-H71 -> 154.0428 | I80: =I62-I71 -> 154.0428 | J80: =J62-J71 -> 154.0428 | K80: =K62-K71 -> 154.0428 | ... N80: =N62-N71 -> 154.0428
B81: 限界利益 | C81: 卸売 | D81: =D63-D72 -> 7439.7 | E81: =E63-E72 -> 7439.7 | F81: =F63-F72 -> 7439.7 | G81: =G63-G72 -> 7439.7 | H81: =H63-H72 -> 7439.7 | I81: =I63-I72 -> 7439.7 | J81: =J63-J72 -> 7439.7 | K81: =K63-K72 -> 7439.7 | ... N81: =N63-N72 -> 7439.7
B82: 限界利益 | C82: 企業内手売 | D82: =D64-D73 -> 5040.15 | E82: =E64-E73 -> 5040.15 | F82: =F64-F73 -> 5040.15 | G82: =G64-G73 -> 5040.15 | H82: =H64-H73 -> 5040.15 | I82: =I64-I73 -> 5040.15 | J82: =J64-J73 -> 5040.15 | K82: =K64-K73 -> 5040.15 | ... N82: =N64-N73 -> 5040.15
B83: 固定費計 | C83: サービス計 | D83: =固定費!E5 -> 29706.33 | E83: =固定費!F5 -> 146632.61 | F83: =固定費!G5 -> 201652.68 | G83: =固定費!H5 -> 233796.94 | H83: =固定費!I5 -> 262370.77 | I83: =固定費!J5 -> 290061.15 | J83: =固定費!K5 -> 316929.93 | K83: =固定費!L5 -> 343034.62 | ... N83: =固定費!O5 -> 417280.54
B84: 固定費計 | C84: アプリ | D84: =固定費!E6 -> 7538 | E84: =固定費!F6 -> 67754.248 | F84: =固定費!G6 -> 109417.67 | G84: =固定費!H6 -> 123529.05 | H84: =固定費!I6 -> 138958.79 | I84: =固定費!J6 -> 152009.71 | J84: =固定費!K6 -> 163666.35 | K84: =固定費!L6 -> 174274 | ... N84: =固定費!O6 -> 201241.72
B85: 固定費計 | C85: スタンド（宅急便） | D85: =固定費!E7 -> 7621 | E85: =固定費!F7 -> 11911.511 | F85: =固定費!G7 -> 7402.1227 | G85: =固定費!H7 -> 3800.0637 | H85: =固定費!I7 -> 2895.4218 | I85: =固定費!J7 -> 2473.4422 | J85: =固定費!K7 -> 2232.5199 | K85: =固定費!L7 -> 2078.7944 | ... N85: =固定費!O7 -> 1841.7801
B86: 固定費計 | C86: スタンド（ＦＳ） | D86: =固定費!E8 -> 703.5 | E86: =固定費!F8 -> 22608.878 | F86: =固定費!G8 -> 37678.948 | G86: =固定費!H8 -> 50387.347 | H86: =固定費!I8 -> 50460.984 | I86: =固定費!J8 -> 50355.397 | J86: =固定費!K8 -> 50190.864 | K86: =固定費!L8 -> 50004.388 | ... N86: =固定費!O8 -> 49427.132
B87: 固定費計 | C87: スタンド（社外） | D87: =固定費!E9 -> 398.8296 | E87: =固定費!F9 -> 8867.3626 | F87: =固定費!G9 -> 21330.95 | G87: =固定費!H9 -> 35640.853 | H87: =固定費!I9 -> 51945.365 | I87: =固定費!J9 -> 68216.579 | J87: =固定費!K9 -> 84477.683 | K87: =固定費!L9 -> 100735.78 | ... N87: =固定費!O9 -> 149513.54
B88: 固定費計 | C88: フロー（セミナー等） | D88: =固定費!E10 -> 12245 | E88: =固定費!F10 -> 19940.563 | F88: =固定費!G10 -> 16565.841 | G88: =固定費!H10 -> 14686.648 | H88: =固定費!I10 -> 13873.505 | I88: =固定費!J10 -> 13488.066 | J88: =固定費!K10 -> 13263.431 | K88: =固定費!L10 -> 13116.521 | ... N88: =固定費!O10 -> 12877.301
B89: 固定費計 | C89: ECストア | D89: =固定費!E11 -> 1200 | E89: =固定費!F11 -> 1359.8126 | F89: =固定費!G11 -> 1289.7302 | G89: =固定費!H11 -> 1250.7053 | H89: =固定費!I11 -> 1233.8189 | I89: =固定費!J11 -> 1225.8146 | J89: =固定費!K11 -> 1221.1496 | K89: =固定費!L11 -> 1218.0987 | ... N89: =固定費!O11 -> 1213.1309
B90: 固定費計 | C90: 卸売 | D90: =固定費!E12 -> 0 | E90: =固定費!F12 -> 8459.3204 | F90: =固定費!G12 -> 4749.6696 | G90: =固定費!H12 -> 2683.9724 | H90: =固定費!I12 -> 1790.1288 | I90: =固定費!J12 -> 1366.4358 | J90: =固定費!K12 -> 1119.5063 | K90: =固定費!L12 -> 958.01664 | ... N90: =固定費!O12 -> 695.05429
B91: 固定費計 | C91: 企業内手売 | D91: =固定費!E13 -> 0 | E91: =固定費!F13 -> 5730.909 | F91: =固定費!G13 -> 3217.7436 | G91: =固定費!H13 -> 1818.3023 | H91: =固定費!I13 -> 1212.7529 | I91: =固定費!J13 -> 925.71492 | J91: =固定費!K13 -> 758.4284 | K91: =固定費!L13 -> 649.0245 | ... N91: =固定費!O13 -> 470.87623
B92: 直接利益 | C92: サービス計 | D92: =SUM(D93:D100) -> 48526.676 | E92: =SUM(E93:E100) -> 23355.44 | F92: =SUM(F93:F100) -> 214425.3 | G92: =SUM(G93:G100) -> 525508.25 | H92: =SUM(H93:H100) -> 889759.94 | I92: =SUM(I93:I100) -> 1225293.9 | J92: =SUM(J93:J100) -> 1534468.7 | K92: =SUM(K93:K100) -> 1819435.9 | ... N92: =SUM(N93:N100) -> 2547899.8
B93: 直接利益 | C93: アプリ | D93: =D75-D84 -> 9238.9227 | E93: =E75-E84 -> 17230.104 | F93: =F75-F84 -> 176250.16 | G93: =G75-G84 -> 441422.15 | H93: =H75-H84 -> 749375.57 | I93: =I75-I84 -> 1037071 | J93: =J75-J84 -> 1305108.4 | K93: =K75-K84 -> 1554616.3 | ... N93: =N75-N84 -> 2203755.6
B94: 直接利益 | C94: スタンド（宅急便） | D94: =D76-D84 -> 18493.509 | E94: =E76-E85 -> 15577.762 | F94: =F76-F85 -> 16788.438 | G94: =G76-G85 -> 17487.629 | H94: =H76-H85 -> 15837.748 | I94: =I76-I85 -> 14011.747 | J94: =J76-J85 -> 12274.447 | K94: =K76-K85 -> 10687.336 | L94: =L76-L85 -> 9260.624 | ... N94: =N76-N85 -> 6857.9806
B95: 直接利益 | C95: スタンド（ＦＳ） | D95: =D77-D86 -> 210.31397 | E95: =E77-E86 -> -2659.0135 | F95: =F77-F86 -> 24084.641 | G95: =G77-G86 -> 68479.878 | H95: =H77-H86 -> 128996.59 | I95: =I77-I86 -> 182421.69 | J95: =J77-J86 -> 229507.39 | K95: =K77-K86 -> 270984.49 | ... N95: =N77-N86 -> 368011.37
B96: 直接利益 | C96: スタンド（社外） | D96: =D78-D87 -> -113.66644 | E96: =E78-E87 -> -5445.4046 | F96: =F78-F87 -> -11017.549 | G96: =G78-G87 -> -15584.377 | H96: =H78-H87 -> -20482.362 | I96: =I78-I87 -> -25347.05 | J96: =J78-J87 -> -30201.627 | K96: =K78-K87 -> -35053.2 | ... N96: =N78-N87 -> -49611.383
B97: 直接利益 | C97: フロー（セミナー等） | D97: =D79-D88 -> 9263.704 | E97: =E79-E88 -> 1568.1409 | F97: =F79-F88 -> 4942.8626 | G97: =G79-G88 -> 6822.0564 | H97: =H79-H88 -> 7635.1985 | I97: =I79-I88 -> 8020.6381 | J97: =J79-J88 -> 8245.2733 | K97: =K79-K88 -> 8392.1828 | ... N97: =N79-N88 -> 8631.4033
B98: 直接利益 | C98: ECストア | D98: =D80-D89 -> -1045.9572 | E98: =E80-E89 -> -1205.7698 | F98: =F80-F89 -> -1135.6874 | G98: =G80-G89 -> -1096.6625 | H98: =H80-H89 -> -1079.7761 | I98: =I80-I89 -> -1071.7718 | J98: =J80-J89 -> -1067.1068 | K98: =K80-K89 -> -1064.0559 | ... N98: =N80-N89 -> -1059.0881
B99: 直接利益 | C99: 卸売 | D99: =D81-D90 -> 7439.7 | E99: =E81-E90 -> -1019.6204 | F99: =F81-F90 -> 2690.0304 | G99: =G81-G90 -> 4755.7276 | H99: =H81-H90 -> 5649.5712 | I99: =I81-I90 -> 6073.2642 | J99: =J81-J90 -> 6320.1937 | K99: =K81-K90 -> 6481.6834 | ... N99: =N81-N90 -> 6744.6457
B100: 直接利益 | C100: 企業内手売 | D100: =D82-D91 -> 5040.15 | E100: =E82-E91 -> -690.75903 | F100: =F82-F91 -> 1822.4064 | G100: =G82-G91 -> 3221.8477 | H100: =H82-H91 -> 3827.3971 | I100: =I82-I91 -> 4114.4351 | J100: =J82-J91 -> 4281.7216 | K100: =K82-K91 -> 4391.1255 | ... N100: =N82-N91 -> 4569.2738
B101: 営業・一般管理費計 | C101: サービス計 | D101: =営業・一般管理費!E5 -> 71244.869 | E101: =営業・一般管理費!F5 -> 107703.56 | F101: =営業・一般管理費!G5 -> 170283.27 | G101: =営業・一般管理費!H5 -> 192422.19 | H101: =営業・一般管理費!I5 -> 215088.35 | I101: =営業・一般管理費!J5 -> 235818.8 | J101: =営業・一般管理費!K5 -> 254832.93 | K101: =営業・一般管理費!L5 -> 272324.7 | ... N101: =営業・一般管理費!O5 -> 317284.48
B102: 営業・一般管理費計 | C102: アプリ | D102: =営業・一般管理費!E6 -> 0 | E102: =営業・一般管理費!F6 -> 11000 | F102: =営業・一般管理費!G6 -> 41000 | G102: =営業・一般管理費!H6 -> 46000 | H102: =営業・一般管理費!I6 -> 51000 | I102: =営業・一般管理費!J6 -> 56000 | J102: =営業・一般管理費!K6 -> 61000 | K102: =営業・一般管理費!L6 -> 66000 | ... N102: =営業・一般管理費!O6 -> 81000
B103: 営業・一般管理費計 | C103: スタンド（宅急便） | D103: =営業・一般管理費!E7 -> 0 | E103: =営業・一般管理費!F7 -> 0 | F103: =営業・一般管理費!G7 -> 0 | G103: =営業・一般管理費!H7 -> 0 | H103: =営業・一般管理費!I7 -> 0 | I103: =営業・一般管理費!J7 -> 0 | J103: =営業・一般管理費!K7 -> 0 | K103: =営業・一般管理費!L7 -> 0 | ... N103: =営業・一般管理費!O7 -> 0
B104: 営業・一般管理費計 | C104: スタンド（ＦＳ） | D104: =営業・一般管理費!E8 -> 210.86856 | E104: =営業・一般管理費!F8 -> 4603.5619 | F104: =営業・一般管理費!G8 -> 14252.353 | G104: =営業・一般管理費!H8 -> 27429.391 | H104: =営業・一般管理費!I8 -> 41411.011 | I104: =営業・一般管理費!J8 -> 53714.838 | J104: =営業・一般管理費!K8 -> 64542.205 | K104: =営業・一般管理費!L8 -> 74070.287 | ... N104: =営業・一般管理費!O8 -> 96326.67
B105: 営業・一般管理費計 | C105: スタンド（社外） | D105: =営業・一般管理費!E9 -> 0 | E105: =営業・一般管理費!F9 -> 0 | F105: =営業・一般管理費!G9 -> 0 | G105: =営業・一般管理費!H9 -> 0 | H105: =営業・一般管理費!I9 -> 0 | I105: =営業・一般管理費!J9 -> 0 | J105: =営業・一般管理費!K9 -> 0 | K105: =営業・一般管理費!L9 -> 0 | ... N105: =営業・一般管理費!O9 -> 0
B106: 営業・一般管理費計 | C106: フロー（セミナー等） | D106: =営業・一般管理費!E10 -> 0 | E106: =営業・一般管理費!F10 -> 10370 | F106: =営業・一般管理費!G10 -> 10600 | G106: =営業・一般管理費!H10 -> 10600 | H106: =営業・一般管理費!I10 -> 10600 | I106: =営業・一般管理費!J10 -> 10600 | J106: =営業・一般管理費!K10 -> 10600 | K106: =営業・一般管理費!L10 -> 10600 | ... N106: =営業・一般管理費!O10 -> 10600
B107: 営業・一般管理費計 | C107: ECストア | D107: =営業・一般管理費!E11 -> 0 | E107: =営業・一般管理費!F11 -> 0 | F107: =営業・一般管理費!G11 -> 0 | G107: =営業・一般管理費!H11 -> 0 | H107: =営業・一般管理費!I11 -> 0 | I107: =営業・一般管理費!J11 -> 0 | J107: =営業・一般管理費!K11 -> 0 | K107: =営業・一般管理費!L11 -> 0 | ... N107: =営業・一般管理費!O11 -> 0
B108: 営業・一般管理費計 | C108: 卸売 | D108: =営業・一般管理費!E12 -> 0 | E108: =営業・一般管理費!F12 -> 0 | F108: =営業・一般管理費!G12 -> 0 | G108: =営業・一般管理費!H12 -> 0 | H108: =営業・一般管理費!I12 -> 0 | I108: =営業・一般管理費!J12 -> 0 | J108: =営業・一般管理費!K12 -> 0 | K108: =営業・一般管理費!L12 -> 0 | ... N108: =営業・一般管理費!O12 -> 0
...

Sheet 売上高
A1: 単位：千円
E2: ※ベンチマーク値
E3: 24年 | F3: 25年 | G3: 26年 | H3: 27年 | I3: 28年 | J3: 29年 | K3: 30年 | L3: 31年 | M3: 32年 | N3: 33年 | O3: 34年
B4: 売上高 | C4: 合計 | D4: サービス計 | E4: =SUM(E5:E12) -> 213867.54 | F4: =SUM(F5:F12) -> 398510.32 | G4: =SUM(G5:G12) -> 887604.91 | H4: =SUM(H5:H12) -> 1570742.7 | I4: =SUM(I5:I12) -> 2355042.8 | J4: =SUM(J5:J12) -> 3085274.9 | K4: =SUM(K5:K12) -> 3765793.8 | L4: =SUM(L5:L12) -> 4400581.2 | ... O4: =SUM(O5:O12) -> 6065468.6
D5: アプリ | E5: =E32+E59 -> 31621.632 | F5: =F32+F59 -> 160180.98 | G5: =G32+G59 -> 538435.04 | H5: =H32+H59 -> 1064836.5 | I5: =I32+I59 -> 1674358.4 | J5: =J32+J59 -> 2241213.9 | K5: =K32+K59 -> 2768389.5 | L5: =L32+L59 -> 3258662.7 | ... O5: =O32+O59 -> 4533009
D6: スタンド（宅急便） | E6: =E33+E60 -> 49489.56 | F6: =F33+F60 -> 52260.975 | G6: =G33+G60 -> 45989.658 | H6: =H33+H60 -> 40470.899 | I6: =I33+I60 -> 35614.391 | J6: =J33+J60 -> 31340.664 | K6: =K33+K60 -> 27579.785 | L6: =L33+L60 -> 24270.211 | ... O6: =O33+O60 -> 16539.469
D7: スタンド（ＦＳ） | E7: =E34+E61 -> 1506.204 | F7: =F34+F61 -> 32882.585 | G7: =G34+G61 -> 101802.52 | H7: =H34+H61 -> 195924.22 | I7: =I34+I61 -> 295792.94 | J7: =J34+J61 -> 383677.41 | K7: =K34+K61 -> 461015.75 | L7: =L34+L61 -> 529073.48 | ... O7: =O34+O61 -> 688047.64
D8: スタンド（社外） | E8: =E35+E62 -> 1994.148 | F8: =F35+F62 -> 23929.776 | G8: =G35+G62 -> 72121.686 | H8: =H35+H62 -> 140255.08 | I8: =I35+I62 -> 220021 | J8: =J35+J62 -> 299786.92 | K8: =K35+K62 -> 379552.84 | L8: =L35+L62 -> 459318.76 | ... O8: =O35+O62 -> 698616.52
D9: フロー（セミナー等） | E9: =E36+E63 -> 45120 | F9: =F36+F63 -> 45120 | G9: =G36+G63 -> 45120 | H9: =H36+H63 -> 45120 | I9: =I36+I63 -> 45120 | J9: =J36+J63 -> 45120 | K9: =K36+K63 -> 45120 | L9: =L36+L63 -> 45120 | ... O9: =O36+O63 -> 45120
D10: ECストア | E10: =E37 -> 937 | F10: =F37 -> 937 | G10: =G37 -> 937 | H10: =H37 -> 937 | I10: =I37 -> 937 | J10: =J37 -> 937 | K10: =K37 -> 937 | L10: =L37 -> 937 | ... O10: =O37 -> 937
D11: 卸売 | E11: =E38 -> 49598 | F11: =F38 -> 49598 | G11: =G38 -> 49598 | H11: =H38 -> 49598 | I11: =I38 -> 49598 | J11: =J38 -> 49598 | K11: =K38 -> 49598 | L11: =L38 -> 49598 | ... O11: =O38 -> 49598
D12: 企業内手売 | E12: =E39 -> 33601 | F12: =F39 -> 33601 | G12: =G39 -> 33601 | H12: =H39 -> 33601 | I12: =I39 -> 33601 | J12: =J39 -> 33601 | K12: =K39 -> 33601 | L12: =L39 -> 33601 | ... O12: =O39 -> 33601
C13: Web | E13: =E40+E64 -> 17118.456 | F13: =F40+F64 -> 278489.78 | G13: =G40+G64 -> 549162.91 | H13: =H40+H64 -> 862671.85 | I13: =I40+I64 -> 1187790.7 | J13: =J40+J64 -> 1491614.5 | K13: =K40+K64 -> 1775905.1 | L13: =L40+L64 -> 2042268.2 | ... O13: =O40+O64 -> 2747814.9
D14: アプリ | E14: =E41+E65 -> 3720.192 | F14: =F41+F65 -> 132520.98 | G14: =G41+G65 -> 323939.84 | H14: =H41+H65 -> 544367.93 | I14: =I41+I65 -> 771126.71 | J14: =J41+J65 -> 982012.38 | K14: =K41+K65 -> 1178136.1 | L14: =L41+L65 -> 1360531.1 | ... O14: =O41+O65 -> 1834622.6
D15: スタンド（宅急便） | E15: =E42+E66 -> 9897.912 | F15: =F42+F66 -> 52260.975 | G15: =G42+G66 -> 45989.658 | H15: =H42+H66 -> 40470.899 | I15: =I42+I66 -> 35614.391 | J15: =J42+J66 -> 31340.664 | K15: =K42+K66 -> 27579.785 | L15: =L42+L66 -> 24270.211 | ... O15: =O42+O66 -> 16539.469
D16: スタンド（ＦＳ） | E16: =E43+E67 -> 1506.204 | F16: =F43+F67 -> 26319.839 | G16: =G43+G67 -> 71962.468 | H16: =H43+H67 -> 122370.17 | I16: =I43+I67 -> 172409.49 | J16: =J43+J67 -> 216444.09 | K16: =K43+K67 -> 255194.53 | L16: =L43+L67 -> 289294.93 | ... O16: =O43+O67 -> 368949.08
D17: スタンド（社外） | E17: =E44+E68 -> 1994.148 | F17: =F44+F68 -> 22267.986 | G17: =G44+G68 -> 62150.946 | H17: =H44+H68 -> 110342.86 | I17: =I44+I68 -> 163520.14 | J17: =J44+J68 -> 216697.42 | K17: =K44+K68 -> 269874.7 | L17: =L44+L68 -> 323051.98 | ... O17: =O44+O68 -> 482583.82
D18: フロー（セミナー等） | E18: =E45+E69 -> 0 | F18: =F45+F69 -> 45120 | G18: =G45+G69 -> 45120 | H18: =H45+H69 -> 45120 | I18: =I45+I69 -> 45120 | J18: =J45+J69 -> 45120 | K18: =K45+K69 -> 45120 | L18: =L45+L69 -> 45120 | ... O18: =O45+O69 -> 45120
C19: 法人 | E19: =E46+E70 -> 0 | F19: =F46+F70 -> 29013.51 | G19: =G46+G70 -> 216908.65 | H19: =H46+H70 -> 541876.59 | I19: =I46+I70 -> 952292.87 | J19: =J46+J70 -> 1334437.3 | K19: =K46+K70 -> 1690457.3 | L19: =L46+L70 -> 2022330 | ... O19: =O46+O70 -> 2890567.7
D20: アプリ | E20: =E47+E71 -> 0 | F20: =F47+F71 -> 25200 | G20: =G47+G71 -> 194544 | H20: =H47+H71 -> 476269.92 | I20: =I47+I71 -> 832019.03 | J20: =J47+J71 -> 1162865.7 | K20: =K47+K71 -> 1470553.1 | L20: =L47+L71 -> 1756702.4 | ... O20: =O47+O71 -> 2500477.9
D21: スタンド（宅急便） | E21: =E48+E72 -> 0 | F21: =F48+F72 -> 0 | G21: =G48+G72 -> 0 | H21: =H48+H72 -> 0 | I21: =I48+I72 -> 0 | J21: =J48+J72 -> 0 | K21: =K48+K72 -> 0 | L21: =L48+L72 -> 0 | ... O21: =O48+O72 -> 0
D22: スタンド（ＦＳ） | E22: =E49+E73 -> 0 | F22: =F49+F73 -> 2151.72 | G22: =G49+G73 -> 12393.907 | H22: =H49+H73 -> 35694.453 | I22: =I49+I73 -> 63772.987 | J22: =J49+J73 -> 88482.098 | K22: =K49+K73 -> 110226.11 | L22: =L49+L73 -> 129360.85 | ... O22: =O49+O73 -> 174057.14
D23: スタンド（社外） | E23: =E50+E74 -> 0 | F23: =F50+F74 -> 1661.79 | G23: =G50+G74 -> 9970.74 | H23: =H50+H74 -> 29912.22 | I23: =I50+I74 -> 56500.86 | J23: =J50+J74 -> 83089.5 | K23: =K50+K74 -> 109678.14 | L23: =L50+L74 -> 136266.78 | ... O23: =O50+O74 -> 216032.7
D24: フロー（セミナー等） | E24: =E51+E75 -> 0 | F24: =F51+F75 -> 0 | G24: =G51+G75 -> 0 | H24: =H51+H75 -> 0 | I24: =I51+I75 -> 0 | J24: =J51+J75 -> 0 | K24: =K51+K75 -> 0 | L24: =L51+L75 -> 0 | ... O24: =O51+O75 -> 0
C25: 代理店 | E25: =E52+E76 -> 0 | F25: =F52+F76 -> 6871.026 | G25: =G52+G76 -> 37397.346 | H25: =H52+H76 -> 82058.215 | I25: =I52+I76 -> 130823.18 | J25: =J52+J76 -> 175087.05 | K25: =K52+K76 -> 215295.41 | L25: =L52+L76 -> 251847 | ... O25: =O52+O76 -> 342949.91
D26: アプリ | E26: =E53+E77 -> 0 | F26: =F53+F77 -> 2460 | G26: =G53+G77 -> 19951.2 | H26: =H53+H77 -> 44198.616 | I26: =I53+I77 -> 71212.713 | J26: =J53+J77 -> 96335.823 | K26: =K53+K77 -> 119700.32 | L26: =L53+L77 -> 141429.29 | ... O26: =O53+O77 -> 197908.49
D27: スタンド（宅急便） | E27: =E54+E78 -> 0 | F27: =F54+F78 -> 0 | G27: =G54+G78 -> 0 | H27: =H54+H78 -> 0 | I27: =I54+I78 -> 0 | J27: =J54+J78 -> 0 | K27: =K54+K78 -> 0 | L27: =L54+L78 -> 0 | ... O27: =O54+O78 -> 0
D28: スタンド（ＦＳ） | E28: =E55+E79 -> 0 | F28: =F55+F79 -> 4411.026 | G28: =G55+G79 -> 17446.146 | H28: =H55+H79 -> 37859.599 | I28: =I55+I79 -> 59610.466 | J28: =J55+J79 -> 78751.228 | K28: =K55+K79 -> 95595.099 | L28: =L55+L79 -> 110417.71 | ... O28: =O55+O79 -> 145041.42
D29: スタンド（社外） | E29: =E56+E80 -> 0 | F29: =F56+F80 -> 0 | G29: =G56+G80 -> 0 | H29: =H56+H80 -> 0 | I29: =I56+I80 -> 0 | J29: =J56+J80 -> 0 | K29: =K56+K80 -> 0 | L29: =L56+L80 -> 0 | ... O29: =O56+O80 -> 0
D30: フロー（セミナー等） | E30: =E57+E81 -> 0 | F30: =F57+F81 -> 0 | G30: =G57+G81 -> 0 | H30: =H57+H81 -> 0 | I30: =I57+I81 -> 0 | J30: =J57+J81 -> 0 | K30: =K57+K81 -> 0 | L30: =L57+L81 -> 0 | ... O30: =O57+O81 -> 0
C31: 既存 | D31: サービス計 | E31: =SUM(E32:E39) -> 196749.09 | F31: =SUM(F32:F39) -> 218371.89 | G31: =SUM(G32:G39) -> 580586.26 | H31: =SUM(H32:H39) -> 1099224.6 | I31: =SUM(I32:I39) -> 1883524.7 | J31: =SUM(J32:J39) -> 2613756.8 | K31: =SUM(K32:K39) -> 3294275.7 | L31: =SUM(L32:L39) -> 3929063.1 | ... O31: =SUM(O32:O39) -> 5593950.5
D32: アプリ | E32: =契約数!E8*客単価!E5 -> 27901.44 | F32: =F41+F47+F53 -> 30215.7 | G32: =G41+G47+G53 -> 305928.8 | H32: =H41+H47+H53 -> 698828.78 | I32: =I41+I47+I53 -> 1308350.8 | J32: =J41+J47+J53 -> 1875206.2 | K32: =K41+K47+K53 -> 2402381.8 | L32: =L41+L47+L53 -> 2892655.1 | M32: =M41+M47+M53 -> 3348609.2 | ... O32: =O41+O47+O53 -> 4167001.3
D33: スタンド（宅急便） | E33: =契約数!E9*客単価!E6 -> 39591.648 | F33: =F42+F48+F54 -> 52260.975 | G33: =G42+G48+G54 -> 45989.658 | H33: =H42+H48+H54 -> 40470.899 | I33: =I42+I48+I54 -> 35614.391 | J33: =J42+J48+J54 -> 31340.664 | K33: =K42+K48+K54 -> 27579.785 | L33: =L42+L48+L54 -> 24270.211 | M33: =M42+M48+M54 -> 21357.785 | ... O33: =O42+O48+O54 -> 16539.469
D34: スタンド（ＦＳ） | E34: =契約数!E10*客単価!E7 -> 0 | F34: =F43+F49+F55 -> 2650.919 | G34: =G43+G49+G55 -> 55540.541 | H34: =H43+H49+H55 -> 130296.76 | I34: =I43+I49+I55 -> 230165.48 | J34: =J43+J49+J55 -> 318049.95 | K34: =K43+K49+K55 -> 395388.29 | L34: =L43+L49+L55 -> 463446.02 | M34: =M43+M49+M55 -> 523336.83 | ... O34: =O43+O49+O55 -> 622420.18
D35: スタンド（社外） | E35: =契約数!E11*客単価!E8 -> 0 | F35: =F44+F50+F56 -> 3988.296 | G35: =G44+G50+G56 -> 43871.256 | H35: =H44+H50+H56 -> 100372.12 | I35: =I44+I50+I56 -> 180138.04 | J35: =J44+J50+J56 -> 259903.96 | K35: =K44+K50+K56 -> 339669.88 | L35: =L44+L50+L56 -> 419435.8 | M35: =M44+M50+M56 -> 499201.72 | ... O35: =O44+O50+O56 -> 658733.56
D36: フロー（セミナー等） | E36: =契約数!E12*客単価!E9 -> 45120 | F36: =F45+F51+F57 -> 45120 | G36: =G45+G51+G57 -> 45120 | H36: =H45+H51+H57 -> 45120 | I36: =I45+I51+I57 -> 45120 | J36: =J45+J51+J57 -> 45120 | K36: =K45+K51+K57 -> 45120 | L36: =L45+L51+L57 -> 45120 | M36: =M45+M51+M57 -> 45120 | ... O36: =O45+O51+O57 -> 45120
D37: ECストア | E37: 937 | F37: =E37 -> 937 | G37: =F37 -> 937 | H37: =G37 -> 937 | I37: =H37 -> 937 | J37: =I37 -> 937 | K37: =J37 -> 937 | L37: =K37 -> 937 | M37: =L37 -> 937 | ... O37: =N37 -> 937 | Q37: ＊ECストアは計画上はステイ
D38: 卸売 | E38: 49598 | F38: =E38 -> 49598 | G38: =F38 -> 49598 | H38: =G38 -> 49598 | I38: =H38 -> 49598 | J38: =I38 -> 49598 | K38: =J38 -> 49598 | L38: =K38 -> 49598 | M38: =L38 -> 49598 | ... O38: =N38 -> 49598 | Q38: ＊卸売は計画上はステイ
D39: 企業内手売 | E39: 33601 | F39: =E39 -> 33601 | G39: =F39 -> 33601 | H39: =G39 -> 33601 | I39: =H39 -> 33601 | J39: =I39 -> 33601 | K39: =J39 -> 33601 | L39: =K39 -> 33601 | M39: =L39 -> 33601 | ... O39: =N39 -> 33601 | Q39: ＊企業内手売は計画上はステイ
C40: Web | E40: =SUM(E41:E45) -> 0 | F40: =SUM(F41:F45) -> 134235.89 | G40: =SUM(G41:G45) -> 378681.04 | H40: =SUM(H41:H45) -> 652848.01 | I40: =SUM(I41:I45) -> 977966.88 | J40: =SUM(J41:J45) -> 1281790.7 | K40: =SUM(K41:K45) -> 1566081.2 | L40: =SUM(L41:L45) -> 1832444.3 | ... O40: =SUM(O41:O45) -> 2537991.1
D41: アプリ | F41: =契約数!F13*客単価!F11 -> 30215.7 | G41: =契約数!G13*客単価!G11 -> 203033.6 | H41: =契約数!H13*客単価!H11 -> 395560.25 | I41: =契約数!I13*客単価!I11 -> 622319.03 | J41: =契約数!J13*客単価!J11 -> 833204.7 | K41: =契約数!K13*客単価!K11 -> 1029328.4 | L41: =契約数!L13*客単価!L11 -> 1211723.4 | M41: =契約数!M13*客単価!M11 -> 1381350.7 | ... O41: =契約数!O13*客単価!O11 -> 1685814.9
D42: スタンド（宅急便） | F42: =契約数!F14*客単価!F12 -> 52260.975 | G42: =契約数!G14*客単価!G12 -> 45989.658 | H42: =契約数!H14*客単価!H12 -> 40470.899 | I42: =契約数!I14*客単価!I12 -> 35614.391 | J42: =契約数!J14*客単価!J12 -> 31340.664 | K42: =契約数!K14*客単価!K12 -> 27579.785 | L42: =契約数!L14*客単価!L12 -> 24270.211 | M42: =契約数!M14*客単価!M12 -> 21357.785 | ... O42: =契約数!O14*客単価!O12 -> 16539.469
D43: スタンド（ＦＳ） | F43: =契約数!F15*客単価!F13 -> 2650.919 | G43: =契約数!G15*客単価!G13 -> 43990.108 | H43: =契約数!H15*客単価!H13 -> 87942.649 | I43: =契約数!I15*客単価!I13 -> 137981.97 | J43: =契約数!J15*客単価!J13 -> 182016.57 | K43: =契約数!K15*客単価!K13 -> 220767.01 | L43: =契約数!L15*客単価!L13 -> 254867.41 | M43: =契約数!M15*客単価!M13 -> 284875.75 | ... O43: =契約数!O15*客単価!O13 -> 334521.56
D44: スタンド（社外） | F44: =契約数!F16*客単価!F14 -> 3988.296 | G44: =契約数!G16*客単価!G14 -> 40547.676 | H44: =契約数!H16*客単価!H14 -> 83754.216 | I44: =契約数!I16*客単価!I14 -> 136931.5 | J44: =契約数!J16*客単価!J14 -> 190108.78 | K44: =契約数!K16*客単価!K14 -> 243286.06 | L44: =契約数!L16*客単価!L14 -> 296463.34 | M44: =契約数!M16*客単価!M14 -> 349640.62 | ... O44: =契約数!O16*客単価!O14 -> 455995.18
D45: フロー（セミナー等） | F45: =契約数!F17*客単価!F15 -> 45120 | G45: =契約数!G17*客単価!G15 -> 45120 | H45: =契約数!H17*客単価!H15 -> 45120 | I45: =契約数!I17*客単価!I15 -> 45120 | J45: =契約数!J17*客単価!J15 -> 45120 | K45: =契約数!K17*客単価!K15 -> 45120 | L45: =契約数!L17*客単価!L15 -> 45120 | M45: =契約数!M17*客単価!M15 -> 45120 | ... O45: =契約数!O17*客単価!O15 -> 45120
C46: 法人 | E46: =SUM(E47:E51) -> 0 | F46: =SUM(F47:F51) -> 0 | G46: =SUM(G47:G51) -> 100854.61 | H46: =SUM(H47:H51) -> 309768.51 | I46: =SUM(I47:I51) -> 720184.79 | J46: =SUM(J47:J51) -> 1102329.2 | K46: =SUM(K47:K51) -> 1458349.3 | L46: =SUM(L47:L51) -> 1790221.9 | ... O46: =SUM(O47:O51) -> 2658459.7
D47: アプリ | F47: =契約数!F18*客単価!F16 -> 0 | G47: =契約数!G18*客単価!G16 -> 93744 | H47: =契約数!H18*客単価!H16 -> 274669.92 | I47: =契約数!I18*客単価!I16 -> 630419.03 | J47: =契約数!J18*客単価!J16 -> 961265.69 | K47: =契約数!K18*客単価!K16 -> 1268953.1 | L47: =契約数!L18*客単価!L16 -> 1555102.4 | M47: =契約数!M18*客単価!M16 -> 1821221.2 | ... O47: =契約数!O18*客単価!O16 -> 2298877.9
D48: スタンド（宅急便） | F48: =契約数!F19*客単価!F17 -> 0 | G48: =契約数!G19*客単価!G17 -> 0 | H48: =契約数!H19*客単価!H17 -> 0 | I48: =契約数!I19*客単価!I17 -> 0 | J48: =契約数!J19*客単価!J17 -> 0 | K48: =契約数!K19*客単価!K17 -> 0 | L48: =契約数!L19*客単価!L17 -> 0 | M48: =契約数!M19*客単価!M17 -> 0 | ... O48: =契約数!O19*客単価!O17 -> 0
D49: スタンド（ＦＳ） | F49: =契約数!F20*客単価!F18 -> 0 | G49: =契約数!G20*客単価!G18 -> 3787.0272 | H49: =契約数!H20*客単価!H18 -> 18480.693 | I49: =契約数!I20*客単価!I18 -> 46559.227 | J49: =契約数!J20*客単価!J18 -> 71268.338 | K49: =契約数!K20*客単価!K18 -> 93012.355 | L49: =契約数!L20*客単価!L18 -> 112147.09 | M49: =契約数!M20*客単価!M18 -> 128985.66 | ... O49: =契約数!O20*客単価!O18 -> 156843.38
D50: スタンド（社外） | F50: =契約数!F21*客単価!F19 -> 0 | G50: =契約数!G21*客単価!G19 -> 3323.58 | H50: =契約数!H21*客単価!H19 -> 16617.9 | I50: =契約数!I21*客単価!I19 -> 43206.54 | J50: =契約数!J21*客単価!J19 -> 69795.18 | K50: =契約数!K21*客単価!K19 -> 96383.82 | L50: =契約数!L21*客単価!L19 -> 122972.46 | M50: =契約数!M21*客単価!M19 -> 149561.1 | ... O50: =契約数!O21*客単価!O19 -> 202738.38
D51: フロー（セミナー等） | F51: =契約数!F22*客単価!F20 -> 0 | G51: =契約数!G22*客単価!G20 -> 0 | H51: =契約数!H22*客単価!H20 -> 0 | I51: =契約数!I22*客単価!I20 -> 0 | J51: =契約数!J22*客単価!J20 -> 0 | K51: =契約数!K22*客単価!K20 -> 0 | L51: =契約数!L22*客単価!L20 -> 0 | M51: =契約数!M22*客単価!M20 -> 0 | ... O51: =契約数!O22*客単価!O20 -> 0
C52: 代理店 | E52: =SUM(E53:E57) -> 0 | F52: =SUM(F53:F57) -> 0 | G52: =SUM(G53:G57) -> 16914.606 | H52: =SUM(H53:H57) -> 52472.035 | I52: =SUM(I53:I57) -> 101237 | J52: =SUM(J53:J57) -> 145500.87 | K52: =SUM(K53:K57) -> 185709.23 | L52: =SUM(L53:L57) -> 222260.82 | ... O52: =SUM(O53:O57) -> 313363.73
D53: アプリ | F53: =契約数!F23*客単価!F21 -> 0 | G53: =契約数!G23*客単価!G21 -> 9151.2 | H53: =契約数!H23*客単価!H21 -> 28598.616 | I53: =契約数!I23*客単価!I21 -> 55612.713 | J53: =契約数!J23*客単価!J21 -> 80735.823 | K53: =契約数!K23*客単価!K21 -> 104100.32 | L53: =契約数!L23*客単価!L21 -> 125829.29 | M53: =契約数!M23*客単価!M21 -> 146037.24 | ... O53: =契約数!O23*客単価!O21 -> 182308.49
D54: スタンド（宅急便） | F54: =契約数!F24*客単価!F22 -> 0 | G54: =契約数!G24*客単価!G22 -> 0 | H54: =契約数!H24*客単価!H22 -> 0 | I54: =契約数!I24*客単価!I22 -> 0 | J54: =契約数!J24*客単価!J22 -> 0 | K54: =契約数!K24*客単価!K22 -> 0 | L54: =契約数!L24*客単価!L22 -> 0 | M54: =契約数!M24*客単価!M22 -> 0 | ... O54: =契約数!O24*客単価!O22 -> 0
D55: スタンド（ＦＳ） | F55: =契約数!F25*客単価!F23 -> 0 | G55: =契約数!G25*客単価!G23 -> 7763.4058 | H55: =契約数!H25*客単価!H23 -> 23873.419 | I55: =契約数!I25*客単価!I23 -> 45624.286 | J55: =契約数!J25*客単価!J23 -> 64765.048 | K55: =契約数!K25*客単価!K23 -> 81608.919 | L55: =契約数!L25*客単価!L23 -> 96431.526 | M55: =契約数!M25*客単価!M23 -> 109475.42 | ... O55: =契約数!O25*客単価!O23 -> 131055.24
D56: スタンド（社外） | F56: =契約数!F26*客単価!F24 -> 0 | G56: =契約数!G26*客単価!G24 -> 0 | H56: =契約数!H26*客単価!H24 -> 0 | I56: =契約数!I26*客単価!I24 -> 0 | J56: =契約数!J26*客単価!J24 -> 0 | K56: =契約数!K26*客単価!K24 -> 0 | L56: =契約数!L26*客単価!L24 -> 0 | M56: =契約数!M26*客単価!M24 -> 0 | ... O56: =契約数!O26*客単価!O24 -> 0
D57: フロー（セミナー等） | F57: =契約数!F27*客単価!F25 -> 0 | G57: =契約数!G27*客単価!G25 -> 0 | H57: =契約数!H27*客単価!H25 -> 0 | I57: =契約数!I27*客単価!I25 -> 0 | J57: =契約数!J27*客単価!J25 -> 0 | K57: =契約数!K27*客単価!K25 -> 0 | L57: =契約数!L27*客単価!L25 -> 0 | M57: =契約数!M27*客単価!M25 -> 0 | ... O57: =契約数!O27*客単価!O25 -> 0
C58: 新規 | D58: サービス計 | E58: =SUM(E59:E63) -> 17118.456 | F58: =SUM(F59:F63) -> 180138.43 | G58: =SUM(G59:G63) -> 307018.65 | H58: =SUM(H59:H63) -> 471518.1 | I58: =SUM(I59:I63) -> 471518.1 | J58: =SUM(J59:J63) -> 471518.1 | K58: =SUM(K59:K63) -> 471518.1 | L58: =SUM(L59:L63) -> 471518.1 | ... O58: =SUM(O59:O63) -> 471518.1
D59: アプリ | E59: =E65+E71+E77 -> 3720.192 | F59: =F65+F71+F77 -> 129965.28 | G59: =G65+G71+G77 -> 232506.24 | H59: =H65+H71+H77 -> 366007.68 | I59: =I65+I71+I77 -> 366007.68 | J59: =J65+J71+J77 -> 366007.68 | K59: =K65+K71+K77 -> 366007.68 | L59: =L65+L71+L77 -> 366007.68 | ... O59: =O65+O71+O77 -> 366007.68
D60: スタンド（宅急便） | E60: =E66+E72+E78 -> 9897.912 | F60: =F66+F72+F78 -> 0 | G60: =G66+G72+G78 -> 0 | H60: =H66+H72+H78 -> 0 | I60: =I66+I72+I78 -> 0 | J60: =J66+J72+J78 -> 0 | K60: =K66+K72+K78 -> 0 | L60: =L66+L72+L78 -> 0 | ... O60: =O66+O72+O78 -> 0
D61: スタンド（ＦＳ） | E61: =E67+E73+E79 -> 1506.204 | F61: =F67+F73+F79 -> 30231.666 | G61: =G67+G73+G79 -> 46261.98 | H61: =H67+H73+H79 -> 65627.46 | I61: =I67+I73+I79 -> 65627.46 | J61: =J67+J73+J79 -> 65627.46 | K61: =K67+K73+K79 -> 65627.46 | L61: =L67+L73+L79 -> 65627.46 | ... O61: =O67+O73+O79 -> 65627.46
D62: スタンド（社外） | E62: =E68+E74+E80 -> 1994.148 | F62: =F68+F74+F80 -> 19941.48 | G62: =G68+G74+G80 -> 28250.43 | H62: =H68+H74+H80 -> 39882.96 | I62: =I68+I74+I80 -> 39882.96 | J62: =J68+J74+J80 -> 39882.96 | K62: =K68+K74+K80 -> 39882.96 | L62: =L68+L74+L80 -> 39882.96 | ... O62: =O68+O74+O80 -> 39882.96
D63: フロー（セミナー等） | E63: =E69+E75+E81 -> 0 | F63: =F69+F75+F81 -> 0 | G63: =G69+G75+G81 -> 0 | H63: =H69+H75+H81 -> 0 | I63: =I69+I75+I81 -> 0 | J63: =J69+J75+J81 -> 0 | K63: =K69+K75+K81 -> 0 | L63: =L69+L75+L81 -> 0 | ... O63: =O69+O75+O81 -> 0
C64: Web | E64: =SUM(E65:E69) -> 17118.456 | F64: =SUM(F65:F69) -> 144253.89 | G64: =SUM(G65:G69) -> 170481.87 | H64: =SUM(H65:H69) -> 209823.84 | I64: =SUM(I65:I69) -> 209823.84 | J64: =SUM(J65:J69) -> 209823.84 | K64: =SUM(K65:K69) -> 209823.84 | L64: =SUM(L65:L69) -> 209823.84 | ... O64: =SUM(O65:O69) -> 209823.84
D65: アプリ | E65: =契約数!E34*客単価!E5*1/2 -> 3720.192 | F65: =契約数!F34*客単価!F5*1/2 -> 102305.28 | G65: =契約数!G34*客単価!G5*1/2 -> 120906.24 | H65: =契約数!H34*客単価!H5*1/2 -> 148807.68 | I65: =契約数!I34*客単価!I5*1/2 -> 148807.68 | J65: =契約数!J34*客単価!J5*1/2 -> 148807.68 | K65: =契約数!K34*客単価!K5*1/2 -> 148807.68 | L65: =契約数!L34*客単価!L5*1/2 -> 148807.68 | ... O65: =契約数!O34*客単価!O5*1/2 -> 148807.68
D66: スタンド（宅急便） | E66: =契約数!E35*客単価!E6*1/2 -> 9897.912 | F66: =契約数!F35*客単価!F6*1/2 -> 0 | G66: =契約数!G35*客単価!G6*1/2 -> 0 | H66: =契約数!H35*客単価!H6*1/2 -> 0 | I66: =契約数!I35*客単価!I6*1/2 -> 0 | J66: =契約数!J35*客単価!J6*1/2 -> 0 | K66: =契約数!K35*客単価!K6*1/2 -> 0 | L66: =契約数!L35*客単価!L6*1/2 -> 0 | ... O66: =契約数!O35*客単価!O6*1/2 -> 0
D67: スタンド（ＦＳ） | E67: =契約数!E36*客単価!E7*1/2 -> 1506.204 | F67: =契約数!F36*客単価!F7*1/2 -> 23668.92 | G67: =契約数!G36*客単価!G7*1/2 -> 27972.36 | H67: =契約数!H36*客単価!H7*1/2 -> 34427.52 | I67: =契約数!I36*客単価!I7*1/2 -> 34427.52 | J67: =契約数!J36*客単価!J7*1/2 -> 34427.52 | K67: =契約数!K36*客単価!K7*1/2 -> 34427.52 | L67: =契約数!L36*客単価!L7*1/2 -> 34427.52 | ... O67: =契約数!O36*客単価!O7*1/2 -> 34427.52
D68: スタンド（社外） | E68: =契約数!E37*客単価!E8*1/2 -> 1994.148 | F68: =契約数!F37*客単価!F8*1/2 -> 18279.69 | G68: =契約数!G37*客単価!G8*1/2 -> 21603.27 | H68: =契約数!H37*客単価!H8*1/2 -> 26588.64 | I68: =契約数!I37*客単価!I8*1/2 -> 26588.64 | J68: =契約数!J37*客単価!J8*1/2 -> 26588.64 | K68: =契約数!K37*客単価!K8*1/2 -> 26588.64 | L68: =契約数!L37*客単価!L8*1/2 -> 26588.64 | ... O68: =契約数!O37*客単価!O8*1/2 -> 26588.64
D69: フロー（セミナー等） | E69: =契約数!E38*客単価!E9*1/2 -> 0 | F69: =契約数!F38*客単価!F9*1/2 -> 0 | G69: =契約数!G38*客単価!G9*1/2 -> 0 | H69: =契約数!H38*客単価!H9*1/2 -> 0 | I69: =契約数!I38*客単価!I9*1/2 -> 0 | J69: =契約数!J38*客単価!J9*1/2 -> 0 | K69: =契約数!K38*客単価!K9*1/2 -> 0 | L69: =契約数!L38*客単価!L9*1/2 -> 0 | ... O69: =契約数!O38*客単価!O9*1/2 -> 0
C70: 法人 | E70: =SUM(E71:E75) -> 0 | F70: =SUM(F71:F75) -> 29013.51 | G70: =SUM(G71:G75) -> 116054.04 | H70: =SUM(H71:H75) -> 232108.08 | I70: =SUM(I71:I75) -> 232108.08 | J70: =SUM(J71:J75) -> 232108.08 | K70: =SUM(K71:K75) -> 232108.08 | L70: =SUM(L71:L75) -> 232108.08 | ... O70: =SUM(O71:O75) -> 232108.08
D71: アプリ | E71: =契約数!E39*客単価!E16*1/2 -> 0 | F71: =契約数!F39*客単価!F16*1/2 -> 25200 | G71: =契約数!G39*客単価!G16*1/2 -> 100800 | H71: =契約数!H39*客単価!H16*1/2 -> 201600 | I71: =契約数!I39*客単価!I16*1/2 -> 201600 | J71: =契約数!J39*客単価!J16*1/2 -> 201600 | K71: =契約数!K39*客単価!K16*1/2 -> 201600 | L71: =契約数!L39*客単価!L16*1/2 -> 201600 | ... O71: =契約数!O39*客単価!O16*1/2 -> 201600
D72: スタンド（宅急便） | E72: =契約数!E40*客単価!E17*1/2 -> 0 | F72: =契約数!F40*客単価!F17*1/2 -> 0 | G72: =契約数!G40*客単価!G17*1/2 -> 0 | H72: =契約数!H40*客単価!H17*1/2 -> 0 | I72: =契約数!I40*客単価!I17*1/2 -> 0 | J72: =契約数!J40*客単価!J17*1/2 -> 0 | K72: =契約数!K40*客単価!K17*1/2 -> 0 | L72: =契約数!L40*客単価!L17*1/2 -> 0 | ... O72: =契約数!O40*客単価!O17*1/2 -> 0
D73: スタンド（ＦＳ） | E73: =契約数!E41*客単価!E18*1/2 -> 0 | F73: =契約数!F41*客単価!F18*1/2 -> 2151.72 | G73: =契約数!G41*客単価!G18*1/2 -> 8606.88 | H73: =契約数!H41*客単価!H18*1/2 -> 17213.76 | I73: =契約数!I41*客単価!I18*1/2 -> 17213.76 | J73: =契約数!J41*客単価!J18*1/2 -> 17213.76 | K73: =契約数!K41*客単価!K18*1/2 -> 17213.76 | L73: =契約数!L41*客単価!L18*1/2 -> 17213.76 | ... O73: =契約数!O41*客単価!O18*1/2 -> 17213.76
D74: スタンド（社外） | E74: =契約数!E42*客単価!E19*1/2 -> 0 | F74: =契約数!F42*客単価!F19*1/2 -> 1661.79 | G74: =契約数!G42*客単価!G19*1/2 -> 6647.16 | H74: =契約数!H42*客単価!H19*1/2 -> 13294.32 | I74: =契約数!I42*客単価!I19*1/2 -> 13294.32 | J74: =契約数!J42*客単価!J19*1/2 -> 13294.32 | K74: =契約数!K42*客単価!K19*1/2 -> 13294.32 | L74: =契約数!L42*客単価!L19*1/2 -> 13294.32 | ... O74: =契約数!O42*客単価!O19*1/2 -> 13294.32
D75: フロー（セミナー等） | E75: =契約数!E43*客単価!E20*1/2 -> 0 | F75: =契約数!F43*客単価!F20*1/2 -> 0 | G75: =契約数!G43*客単価!G20*1/2 -> 0 | H75: =契約数!H43*客単価!H20*1/2 -> 0 | I75: =契約数!I43*客単価!I20*1/2 -> 0 | J75: =契約数!J43*客単価!J20*1/2 -> 0 | K75: =契約数!K43*客単価!K20*1/2 -> 0 | L75: =契約数!L43*客単価!L20*1/2 -> 0 | ... O75: =契約数!O43*客単価!O20*1/2 -> 0
C76: 代理店 | E76: =SUM(E77:E81) -> 0 | F76: =SUM(F77:F81) -> 6871.026 | G76: =SUM(G77:G81) -> 20482.74 | H76: =SUM(H77:H81) -> 29586.18 | I76: =SUM(I77:I81) -> 29586.18 | J76: =SUM(J77:J81) -> 29586.18 | K76: =SUM(K77:K81) -> 29586.18 | L76: =SUM(L77:L81) -> 29586.18 | ... O76: =SUM(O77:O81) -> 29586.18
D77: アプリ | E77: =契約数!E44*客単価!E21*1/2 -> 0 | F77: =契約数!F44*客単価!F21*1/2 -> 2460 | G77: =契約数!G44*客単価!G21*1/2 -> 10800 | H77: =契約数!H44*客単価!H21*1/2 -> 15600 | I77: =契約数!I44*客単価!I21*1/2 -> 15600 | J77: =契約数!J44*客単価!J21*1/2 -> 15600 | K77: =契約数!K44*客単価!K21*1/2 -> 15600 | L77: =契約数!L44*客単価!L21*1/2 -> 15600 | ... O77: =契約数!O44*客単価!O21*1/2 -> 15600
D78: スタンド（宅急便） | E78: =契約数!E45*客単価!E22*1/2 -> 0 | F78: =契約数!F45*客単価!F22*1/2 -> 0 | G78: =契約数!G45*客単価!G22*1/2 -> 0 | H78: =契約数!H45*客単価!H22*1/2 -> 0 | I78: =契約数!I45*客単価!I22*1/2 -> 0 | J78: =契約数!J45*客単価!J22*1/2 -> 0 | K78: =契約数!K45*客単価!K22*1/2 -> 0 | L78: =契約数!L45*客単価!L22*1/2 -> 0 | ... O78: =契約数!O45*客単価!O22*1/2 -> 0
D79: スタンド（ＦＳ） | E79: =契約数!E46*客単価!E23*1/2 -> 0 | F79: =契約数!F46*客単価!F23*1/2 -> 4411.026 | G79: =契約数!G46*客単価!G23*1/2 -> 9682.74 | H79: =契約数!H46*客単価!H23*1/2 -> 13986.18 | I79: =契約数!I46*客単価!I23*1/2 -> 13986.18 | J79: =契約数!J46*客単価!J23*1/2 -> 13986.18 | K79: =契約数!K46*客単価!K23*1/2 -> 13986.18 | L79: =契約数!L46*客単価!L23*1/2 -> 13986.18 | ... O79: =契約数!O46*客単価!O23*1/2 -> 13986.18
D80: スタンド（社外） | E80: =契約数!E47*客単価!E24*1/2 -> 0 | F80: =契約数!F47*客単価!F24*1/2 -> 0 | G80: =契約数!G47*客単価!G24*1/2 -> 0 | H80: =契約数!H47*客単価!H24*1/2 -> 0 | I80: =契約数!I47*客単価!I24*1/2 -> 0 | J80: =契約数!J47*客単価!J24*1/2 -> 0 | K80: =契約数!K47*客単価!K24*1/2 -> 0 | L80: =契約数!L47*客単価!L24*1/2 -> 0 | ... O80: =契約数!O47*客単価!O24*1/2 -> 0
D81: フロー（セミナー等） | E81: =契約数!E48*客単価!E25*1/2 -> 0 | F81: =契約数!F48*客単価!F25*1/2 -> 0 | G81: =契約数!G48*客単価!G25*1/2 -> 0 | H81: =契約数!H48*客単価!H25*1/2 -> 0 | I81: =契約数!I48*客単価!I25*1/2 -> 0 | J81: =契約数!J48*客単価!J25*1/2 -> 0 | K81: =契約数!K48*客単価!K25*1/2 -> 0 | L81: =契約数!L48*客単価!L25*1/2 -> 0 | ... O81: =契約数!O48*客単価!O25*1/2 -> 0

Sheet Input＞＞

Sheet 契約数
E3: 24年 | F3: 25年 | G3: 26年 | H3: 27年 | I3: 28年 | J3: 29年 | K3: 30年 | L3: 31年 | M3: 32年 | N3: 33年 | O3: 34年
B4: 契約数 | E4: =E5+E6 -> 290 | F4: =F5+F6 -> 653.27 | G4: =G5+G6 -> 1191.1311 | H4: =H5+H6 -> 1921.0235 | I4: =I5+I6 -> 2592.8073 | J4: =J5+J6 -> 3212.3999 | K4: =K5+K6 -> 3785.0828 | L4: =L5+L6 -> 4315.5722 | ... O4: =O5+O6 -> 5693.8395
B5: 契約数 | C5: ストック | E5: =SUM(E8:E11)+SUM(E29:E32) -> 170 | F5: =SUM(F8:F11)+SUM(F29:F32) -> 533.27 | G5: =SUM(G8:G11)+SUM(G29:G32) -> 1071.1311 | H5: =SUM(H8:H11)+SUM(H29:H32) -> 1801.0235 | I5: =SUM(I8:I11)+SUM(I29:I32) -> 2472.8073 | J5: =SUM(J8:J11)+SUM(J29:J32) -> 3092.3999 | K5: =SUM(K8:K11)+SUM(K29:K32) -> 3665.0828 | L5: =SUM(L8:L11)+SUM(L29:L32) -> 4195.5722 | ... O5: =SUM(O8:O11)+SUM(O29:O32) -> 5573.8395
B6: 契約数 | C6: フロー | E6: =E12+E33 -> 120 | F6: =F12+F33 -> 120 | G6: =G12+G33 -> 120 | H6: =H12+H33 -> 120 | I6: =I12+I33 -> 120 | J6: =J12+J33 -> 120 | K6: =K12+K33 -> 120 | L6: =L12+L33 -> 120 | ... O6: =O12+O33 -> 120
B7: 契約数 | C7: 既存 | E7: =SUM(E8:E12) -> 227 | F7: =SUM(F8:F11) -> 151.27 | G7: =SUM(G8:G11) -> 486.1311 | H7: =SUM(H8:H11) -> 981.02352 | I7: =SUM(I8:I11) -> 1652.8073 | J7: =SUM(J8:J11) -> 2272.3999 | K7: =SUM(K8:K11) -> 2845.0828 | L7: =SUM(L8:L11) -> 3375.5722 | M7: =SUM(M8:M11) -> 3868.0822 | ... O7: =SUM(O8:O11) -> 4753.8395
B8: 契約数 | D8: アプリ | E8: =E13+E18+E23 -> 15 | F8: =F13+F18+F23 -> 17.67 | G8: =G13+G18+G23 -> 166.1631 | H8: =H13+H18+H23 -> 377.73168 | I8: =I13+I18+I23 -> 658.19047 | J8: =J13+J18+J23 -> 919.01713 | K8: =K13+K18+K23 -> 1161.5859 | L8: =L13+L18+L23 -> 1387.1749 | ... O8: =O13+O18+O23 -> 1973.5387
B9: 契約数 | D9: スタンド（宅急便） | E9: =E14+E19+E24 -> 92 | F9: =F14+F19+F24 -> 121.44 | G9: =G14+G19+G24 -> 106.8672 | H9: =H14+H19+H24 -> 94.043136 | I9: =I14+I19+I24 -> 82.75796 | J9: =J14+J19+J24 -> 72.827005 | K9: =K14+K19+K24 -> 64.087764 | L9: =L14+L19+L24 -> 56.397232 | ... O9: =O14+O19+O24 -> 38.433135
B10: 契約数 | D10: スタンド（ＦＳ） | E10: =E15+E20+E25 -> 0 | F10: =F15+F20+F25 -> 6.16 | G10: =G15+G20+G25 -> 147.1008 | H10: =H15+H20+H25 -> 358.2487 | I10: =I15+I20+I25 -> 640.85886 | J10: =J15+J20+J25 -> 889.5558 | K10: =K15+K20+K25 -> 1108.4091 | L10: =L15+L20+L25 -> 1301 | ... O10: =O15+O20+O25 -> 1750.8677
B11: 契約数 | D11: スタンド（社外） | E11: =E16+E21+E26 -> 0 | F11: =F16+F21+F26 -> 6 | G11: =G16+G21+G26 -> 66 | H11: =H16+H21+H26 -> 151 | I11: =I16+I21+I26 -> 271 | J11: =J16+J21+J26 -> 391 | K11: =K16+K21+K26 -> 511 | L11: =L16+L21+L26 -> 631 | ... O11: =O16+O21+O26 -> 991
B12: 契約数 | D12: フロー（セミナー等） | E12: =E17+E22+E27 -> 120 | F12: =F17+F22+F27 -> 120 | G12: =G17+G22+G27 -> 120 | H12: =H17+H22+H27 -> 120 | I12: =I17+I22+I27 -> 120 | J12: =J17+J22+J27 -> 120 | K12: =K17+K22+K27 -> 120 | L12: =L17+L22+L27 -> 120 | ... O12: =O17+O22+O27 -> 120
B13: 契約数 | C13: Web | D13: アプリ | E13: 15 | F13: =(E13+E34)*E50 -> 17.67 | G13: =(F13+F34)*F50 -> 118.7331 | H13: =(G13+G34)*G50 -> 231.32178 | I13: =(H13+H34)*H50 -> 363.92926 | J13: =(I13+I34)*I50 -> 487.25421 | K13: =(J13+J34)*J50 -> 601.94642 | L13: =(K13+K34)*K50 -> 708.61017 | M13: =(L13+L34)*L50 -> 807.80745 | ... O13: =(N13+N34)*N50 -> 985.85667
B14: 契約数 | D14: スタンド（宅急便） | E14: 92 | F14: =(E14+E35)*E51 -> 121.44 | G14: =(F14+F35)*F51 -> 106.8672 | H14: =(G14+G35)*G51 -> 94.043136 | I14: =(H14+H35)*H51 -> 82.75796 | J14: =(I14+I35)*I51 -> 72.827005 | K14: =(J14+J35)*J51 -> 64.087764 | L14: =(K14+K35)*K51 -> 56.397232 | M14: =(L14+L35)*L51 -> 49.629564 | ... O14: =(N14+N35)*N51 -> 38.433135
B15: 契約数 | D15: スタンド（ＦＳ） | E15: 0 | F15: =(E15+E36)*E52 -> 6.16 | G15: =(F15+F36)*F52 -> 102.2208 | H15: =(G15+G36)*G52 -> 204.3543 | I15: =(H15+H36)*H52 -> 320.63179 | J15: =(I15+I36)*I52 -> 422.95597 | K15: =(J15+J36)*J52 -> 513.00126 | L15: =(K15+K36)*K52 -> 592.24111 | M15: =(L15+L36)*L52 -> 661.97217 | ... O15: =(N15+N36)*N52 -> 777.33525
B16: 契約数 | D16: スタンド（社外） | E16: 0 | F16: =(E16+E37)*E53 -> 6 | G16: =(F16+F37)*F53 -> 61 | H16: =(G16+G37)*G53 -> 126 | I16: =(H16+H37)*H53 -> 206 | J16: =(I16+I37)*I53 -> 286 | K16: =(J16+J37)*J53 -> 366 | L16: =(K16+K37)*K53 -> 446 | M16: =(L16+L37)*L53 -> 526 | ... O16: =(N16+N37)*N53 -> 686
B17: 契約数 | D17: フロー（セミナー等） | E17: 120 | F17: =(E17+E38)*E54 -> 120 | G17: =(F17+F38)*F54 -> 120 | H17: =(G17+G38)*G54 -> 120 | I17: =(H17+H38)*H54 -> 120 | J17: =(I17+I38)*I54 -> 120 | K17: =(J17+J38)*J54 -> 120 | L17: =(K17+K38)*K54 -> 120 | M17: =(L17+L38)*L54 -> 120 | ... O17: =(N17+N38)*N54 -> 120
B18: 契約数 | C18: 法人 | D18: アプリ | F18: =(E18+E39)*E50 -> 0 | G18: =(F18+F39)*F50 -> 9.3 | H18: =(G18+G39)*G50 -> 27.249 | I18: =(H18+H39)*H50 -> 62.54157 | J18: =(I18+I39)*I50 -> 95.36366 | K18: =(J18+J39)*J50 -> 125.8882 | L18: =(K18+K39)*K50 -> 154.27603 | M18: =(L18+L39)*L50 -> 180.67671 | ... O18: =(N18+N39)*N50 -> 228.06328
B19: 契約数 | D19: スタンド（宅急便） | F19: =(E19+E40)*E51 -> 0 | G19: =(F19+F40)*F51 -> 0 | H19: =(G19+G40)*G51 -> 0 | I19: =(H19+H40)*H51 -> 0 | J19: =(I19+I40)*I51 -> 0 | K19: =(J19+J40)*J51 -> 0 | L19: =(K19+K40)*K51 -> 0 | M19: =(L19+L40)*L51 -> 0 | ... O19: =(N19+N40)*N51 -> 0
B20: 契約数 | D20: スタンド（ＦＳ） | F20: =(E20+E41)*E52 -> 0 | G20: =(F20+F41)*F52 -> 8.8 | H20: =(G20+G41)*G52 -> 42.944 | I20: =(H20+H41)*H52 -> 108.19072 | J20: =(I20+I41)*I52 -> 165.60783 | K20: =(J20+J41)*J52 -> 216.13489 | L20: =(K20+K41)*K52 -> 260.59871 | M20: =(L20+L41)*L52 -> 299.72686 | ... O20: =(N20+N41)*N52 -> 364.46048
B21: 契約数 | D21: スタンド（社外） | F21: =(E21+E42)*E53 -> 0 | G21: =(F21+F42)*F53 -> 5 | H21: =(G21+G42)*G53 -> 25 | I21: =(H21+H42)*H53 -> 65 | J21: =(I21+I42)*I53 -> 105 | K21: =(J21+J42)*J53 -> 145 | L21: =(K21+K42)*K53 -> 185 | M21: =(L21+L42)*L53 -> 225 | ... O21: =(N21+N42)*N53 -> 305
B22: 契約数 | D22: フロー（セミナー等） | F22: =(E22+E43)*E54 -> 0 | G22: =(F22+F43)*F54 -> 0 | H22: =(G22+G43)*G54 -> 0 | I22: =(H22+H43)*H54 -> 0 | J22: =(I22+I43)*I54 -> 0 | K22: =(J22+J43)*J54 -> 0 | L22: =(K22+K43)*K54 -> 0 | M22: =(L22+L43)*L54 -> 0 | ... O22: =(N22+N43)*N54 -> 0
B23: 契約数 | C23: 代理店 | D23: アプリ | F23: =(E23+E44)*E50 -> 0 | G23: =(F23+F44)*F50 -> 38.13 | H23: =(G23+G44)*G50 -> 119.1609 | I23: =(H23+H44)*H50 -> 231.71964 | J23: =(I23+I44)*I50 -> 336.39926 | K23: =(J23+J44)*J50 -> 433.75131 | L23: =(K23+K44)*K50 -> 524.28872 | M23: =(L23+L44)*L50 -> 608.48851 | ... O23: =(N23+N44)*N50 -> 759.61871
B24: 契約数 | D24: スタンド（宅急便） | F24: =(E24+E45)*E51 -> 0 | G24: =(F24+F45)*F51 -> 0 | H24: =(G24+G45)*G51 -> 0 | I24: =(H24+H45)*H51 -> 0 | J24: =(I24+I45)*I51 -> 0 | K24: =(J24+J45)*J51 -> 0 | L24: =(K24+K45)*K51 -> 0 | M24: =(L24+L45)*L51 -> 0 | ... O24: =(N24+N45)*N51 -> 0
B25: 契約数 | D25: スタンド（ＦＳ） | F25: =(E25+E46)*E52 -> 0 | G25: =(F25+F46)*F52 -> 36.08 | H25: =(G25+G46)*G52 -> 110.9504 | I25: =(H25+H46)*H52 -> 212.03635 | J25: =(I25+I46)*I52 -> 300.99199 | K25: =(J25+J46)*J52 -> 379.27295 | L25: =(K25+K46)*K52 -> 448.1602 | M25: =(L25+L46)*L52 -> 508.78097 | ... O25: =(N25+N46)*N52 -> 609.07199
B26: 契約数 | D26: スタンド（社外） | F26: =(E26+E47)*E53 -> 0 | G26: =(F26+F47)*F53 -> 0 | H26: =(G26+G47)*G53 -> 0 | I26: =(H26+H47)*H53 -> 0 | J26: =(I26+I47)*I53 -> 0 | K26: =(J26+J47)*J53 -> 0 | L26: =(K26+K47)*K53 -> 0 | M26: =(L26+L47)*L53 -> 0 | ... O26: =(N26+N47)*N53 -> 0
B27: 契約数 | D27: フロー（セミナー等） | F27: =(E27+E48)*E54 -> 0 | G27: =(F27+F48)*F54 -> 0 | H27: =(G27+G48)*G54 -> 0 | I27: =(H27+H48)*H54 -> 0 | J27: =(I27+I48)*I54 -> 0 | K27: =(J27+J48)*J54 -> 0 | L27: =(K27+K48)*K54 -> 0 | M27: =(L27+L48)*L54 -> 0 | ... O27: =(N27+N48)*N54 -> 0
B28: 契約数 | C28: 新規 | E28: =SUM(E29:E33) -> 63 | F28: =SUM(F29:F33) -> 382 | G28: =SUM(G29:G33) -> 585 | H28: =SUM(H29:H33) -> 820 | I28: =SUM(I29:I33) -> 820 | J28: =SUM(J29:J33) -> 820 | K28: =SUM(K29:K33) -> 820 | L28: =SUM(L29:L33) -> 820 | ... O28: =SUM(O29:O33) -> 820
B29: 契約数 | D29: アプリ | E29: =E34+E39+E44 -> 4 | F29: =F34+F39+F44 -> 161 | G29: =G34+G39+G44 -> 240 | H29: =H34+H39+H44 -> 330 | I29: =I34+I39+I44 -> 330 | J29: =J34+J39+J44 -> 330 | K29: =K34+K39+K44 -> 330 | L29: =L34+L39+L44 -> 330 | ... O29: =O34+O39+O44 -> 330
B30: 契約数 | D30: スタンド（宅急便） | E30: =E35+E40+E45 -> 46 | F30: =F35+F40+F45 -> 0 | G30: =G35+G40+G45 -> 0 | H30: =H35+H40+H45 -> 0 | I30: =I35+I40+I45 -> 0 | J30: =J35+J40+J45 -> 0 | K30: =K35+K40+K45 -> 0 | L30: =L35+L40+L45 -> 0 | ... O30: =O35+O40+O45 -> 0
B31: 契約数 | D31: スタンド（ＦＳ） | E31: =E36+E41+E46 -> 7 | F31: =F36+F41+F46 -> 161 | G31: =G36+G41+G46 -> 260 | H31: =H36+H41+H46 -> 370 | I31: =I36+I41+I46 -> 370 | J31: =J36+J41+J46 -> 370 | K31: =K36+K41+K46 -> 370 | L31: =L36+L41+L46 -> 370 | ... O31: =O36+O41+O46 -> 370
B32: 契約数 | D32: スタンド（社外） | E32: =E37+E42+E47 -> 6 | F32: =F37+F42+F47 -> 60 | G32: =G37+G42+G47 -> 85 | H32: =H37+H42+H47 -> 120 | I32: =I37+I42+I47 -> 120 | J32: =J37+J42+J47 -> 120 | K32: =K37+K42+K47 -> 120 | L32: =L37+L42+L47 -> 120 | ... O32: =O37+O42+O47 -> 120
B33: 契約数 | D33: フロー（セミナー等） | E33: =E38+E43+E48 -> 0 | F33: =F38+F43+F48 -> 0 | G33: =G38+G43+G48 -> 0 | H33: =H38+H43+H48 -> 0 | I33: =I38+I43+I48 -> 0 | J33: =J38+J43+J48 -> 0 | K33: =K38+K43+K48 -> 0 | L33: =L38+L43+L48 -> 0 | ... O33: =O38+O43+O48 -> 0
B34: 契約数 | C34: Web | D34: アプリ | E34: 4 | F34: 110 | G34: 130 | H34: 160 | I34: 160 | J34: 160 | K34: 160 | L34: 160 | M34: 160 | N34: 160 | O34: 160
B35: 契約数 | D35: スタンド（宅急便） | E35: 46
B36: 契約数 | D36: スタンド（ＦＳ） | E36: 7 | F36: =F34 -> 110 | G36: =G34 -> 130 | H36: =H34 -> 160 | I36: =I34 -> 160 | J36: =J34 -> 160 | K36: =K34 -> 160 | L36: =L34 -> 160 | M36: =M34 -> 160 | ... O36: =O34 -> 160 | Q36: スタンド単独獲得は反映していない
B37: 契約数 | D37: スタンド（社外） | E37: 6 | F37: =F34*1/2 -> 55 | G37: =G34*1/2 -> 65 | H37: =H34*1/2 -> 80 | I37: =I34*1/2 -> 80 | J37: =J34*1/2 -> 80 | K37: =K34*1/2 -> 80 | L37: =L34*1/2 -> 80 | M37: =M34*1/2 -> 80 | ... O37: =O34*1/2 -> 80
B38: 契約数 | D38: フロー（セミナー等） | E38: 0
B39: 契約数 | C39: 法人 | D39: アプリ | F39: 10 | G39: 20 | H39: 40 | I39: 40 | J39: 40 | K39: 40 | L39: 40 | M39: 40 | N39: 40 | O39: 40
B40: 契約数 | D40: スタンド（宅急便）
B41: 契約数 | D41: スタンド（ＦＳ） | F41: 10 | G41: =G39*2 -> 40 | H41: =H39*2 -> 80 | I41: =I39*2 -> 80 | J41: =J39*2 -> 80 | K41: =K39*2 -> 80 | L41: =L39*2 -> 80 | M41: =M39*2 -> 80 | N41: =N39*2 -> 80 | O41: =O39*2 -> 80 | Q41: スタンド単独獲得は反映していない
B42: 契約数 | D42: スタンド（社外） | F42: =F41/2 -> 5 | G42: =G41/2 -> 20 | H42: =H41/2 -> 40 | I42: =I41/2 -> 40 | J42: =J41/2 -> 40 | K42: =K41/2 -> 40 | L42: =L41/2 -> 40 | M42: =M41/2 -> 40 | ... O42: =O41/2 -> 40
B43: 契約数 | D43: フロー（セミナー等）
B44: 契約数 | C44: 代理店 | D44: アプリ | E44: 0 | F44: 41 | G44: 90 | H44: 130 | I44: 130 | J44: 130 | K44: 130 | L44: 130 | M44: 130 | N44: 130 | O44: 130
B45: 契約数 | D45: スタンド（宅急便） | E45: 0
B46: 契約数 | D46: スタンド（ＦＳ） | E46: 0 | F46: =F44 -> 41 | G46: =G44 -> 90 | H46: =H44 -> 130 | I46: =I44 -> 130 | J46: =J44 -> 130 | K46: =K44 -> 130 | L46: =L44 -> 130 | M46: =M44 -> 130 | ... O46: =O44 -> 130 | Q46: スタンド単独獲得は反映していない
B47: 契約数 | D47: スタンド（社外） | E47: 0
B48: 契約数 | D48: フロー（セミナー等） | E48: 0
B49: 契約数 | C49: 継続率 | F49: =F7/E7 -> 0.66638767 | G49: =G7/F7 -> 3.213665 | H49: =H7/G7 -> 2.0180226 | I49: =I7/H7 -> 1.6847784 | J49: =J7/I7 -> 1.3748729 | K49: =K7/J7 -> 1.2520168 | L49: =L7/K7 -> 1.1864583 | M49: =M7/L7 -> 1.1459042 | ... O49: =O7/N7 -> 1.0988028
B50: 契約数 | D50: アプリ | E50: 0.93 | F50: 0.93 | G50: 0.93 | H50: 0.93 | I50: 0.93 | J50: 0.93 | K50: 0.93 | L50: 0.93 | M50: 0.93 | N50: 0.93 | O50: 0.93
B51: 契約数 | D51: スタンド（宅急便） | E51: 0.88 | F51: 0.88 | G51: 0.88 | H51: 0.88 | I51: 0.88 | J51: 0.88 | K51: 0.88 | L51: 0.88 | M51: 0.88 | N51: 0.88 | O51: 0.88
B52: 契約数 | D52: スタンド（ＦＳ） | E52: 0.88 | F52: 0.88 | G52: 0.88 | H52: 0.88 | I52: 0.88 | J52: 0.88 | K52: 0.88 | L52: 0.88 | M52: 0.88 | N52: 0.88 | O52: 0.88
B53: 契約数 | D53: スタンド（社外） | E53: 1 | F53: 1 | G53: 1 | H53: 1 | I53: 1 | J53: 1 | K53: 1 | L53: 1 | M53: 1 | N53: 1 | O53: 1
B54: 契約数 | D54: フロー（セミナー等） | E54: 1 | F54: 1 | G54: 1 | H54: 1 | I54: 1 | J54: 1 | K54: 1 | L54: 1 | M54: 1 | N54: 1 | O54: 1

Sheet 客単価
A1: 単位：千円
E3: 24年 | F3: 25年 | G3: 26年 | H3: 27年 | I3: 28年 | J3: 29年 | K3: 30年 | L3: 31年 | M3: 32年 | N3: 33年 | O3: 34年
B4: 客単価
B5: 客単価 | C5: 既存 | D5: アプリ | E5: =155008*12/1000 -> 1860.096 | F5: =E5 -> 1860.096 | G5: =F5 -> 1860.096 | H5: =G5 -> 1860.096 | I5: =H5 -> 1860.096 | J5: =I5 -> 1860.096 | K5: =J5 -> 1860.096 | L5: =K5 -> 1860.096 | M5: =L5 -> 1860.096 | ... O5: =N5 -> 1860.096
B6: 客単価 | D6: スタンド（宅急便） | E6: =35862*12/1000 -> 430.344 | F6: =E6 -> 430.344 | G6: =F6 -> 430.344 | H6: =G6 -> 430.344 | I6: =H6 -> 430.344 | J6: =I6 -> 430.344 | K6: =J6 -> 430.344 | L6: =K6 -> 430.344 | M6: =L6 -> 430.344 | ... O6: =N6 -> 430.344
B7: 客単価 | D7: スタンド（ＦＳ） | E7: =35862*12/1000 -> 430.344 | F7: =E7 -> 430.344 | G7: =F7 -> 430.344 | H7: =G7 -> 430.344 | I7: =H7 -> 430.344 | J7: =I7 -> 430.344 | K7: =J7 -> 430.344 | L7: =K7 -> 430.344 | M7: =L7 -> 430.344 | ... O7: =N7 -> 430.344
B8: 客単価 | D8: スタンド（社外） | E8: =55393*12/1000 -> 664.716 | F8: =E8 -> 664.716 | G8: =F8 -> 664.716 | H8: =G8 -> 664.716 | I8: =H8 -> 664.716 | J8: =I8 -> 664.716 | K8: =J8 -> 664.716 | L8: =K8 -> 664.716 | M8: =L8 -> 664.716 | ... O8: =N8 -> 664.716
B9: 客単価 | D9: フロー（セミナー等） | E9: 376 | F9: =E9 -> 376 | G9: =F9 -> 376 | H9: =G9 -> 376 | I9: =H9 -> 376 | J9: =I9 -> 376 | K9: =J9 -> 376 | L9: =K9 -> 376 | M9: =L9 -> 376 | ... O9: =N9 -> 376
B10: 客単価 | C10: 新規
B11: 客単価 | C11: Web | D11: アプリ | F11: 1710 | G11: 1710 | H11: 1710 | I11: 1710 | J11: 1710 | K11: 1710 | L11: 1710 | M11: 1710 | N11: 1710 | O11: 1710 | Q11: 従業員数 | R11: 356 | S11: 人
B12: 客単価 | D12: スタンド（宅急便） | F12: =F6 -> 430.344 | G12: =G6 -> 430.344 | H12: =H6 -> 430.344 | I12: =I6 -> 430.344 | J12: =J6 -> 430.344 | K12: =K6 -> 430.344 | L12: =L6 -> 430.344 | M12: =M6 -> 430.344 | ... O12: =O6 -> 430.344 | Q12: 単価 | R12: 400 | S12: 円/月・人
B13: 客単価 | D13: スタンド（ＦＳ） | F13: =F7 -> 430.344 | G13: =G7 -> 430.344 | H13: =H7 -> 430.344 | I13: =I7 -> 430.344 | J13: =J7 -> 430.344 | K13: =K7 -> 430.344 | L13: =L7 -> 430.344 | M13: =M7 -> 430.344 | ... O13: =O7 -> 430.344
B14: 客単価 | D14: スタンド（社外） | F14: =F8 -> 664.716 | G14: =G8 -> 664.716 | H14: =H8 -> 664.716 | I14: =I8 -> 664.716 | J14: =J8 -> 664.716 | K14: =K8 -> 664.716 | L14: =L8 -> 664.716 | M14: =M8 -> 664.716 | ... O14: =O8 -> 664.716
B15: 客単価 | D15: フロー（セミナー等） | F15: =F9 -> 376 | G15: =G9 -> 376 | H15: =H9 -> 376 | I15: =I9 -> 376 | J15: =J9 -> 376 | K15: =K9 -> 376 | L15: =L9 -> 376 | M15: =M9 -> 376 | ... O15: =O9 -> 376
B16: 客単価 | C16: 法人 | D16: アプリ | F16: =$R$16*$R$17*12*1/2/1000 -> 5040 | G16: =$R$16*$R$17*12/1000 -> 10080 | H16: =$R$16*$R$17*12/1000 -> 10080 | I16: =$R$16*$R$17*12/1000 -> 10080 | J16: =$R$16*$R$17*12/1000 -> 10080 | K16: =$R$16*$R$17*12/1000 -> 10080 | L16: =$R$16*$R$17*12/1000 -> 10080 | M16: =$R$16*$R$17*12/1000 -> 10080 | N16: =$R$16*$R$17*12/1000 -> 10080 | O16: =$R$16*$R$17*12/1000 -> 10080 | Q16: 従業員数 | R16: 2100 | S16: 人
B17: 客単価 | D17: スタンド（宅急便） | F17: =F12 -> 430.344 | G17: =G12 -> 430.344 | H17: =H12 -> 430.344 | I17: =I12 -> 430.344 | J17: =J12 -> 430.344 | K17: =K12 -> 430.344 | L17: =L12 -> 430.344 | M17: =M12 -> 430.344 | ... O17: =O12 -> 430.344 | Q17: 単価 | R17: 400 | S17: 円/月・人
B18: 客単価 | D18: スタンド（ＦＳ） | F18: =F13 -> 430.344 | G18: =G13 -> 430.344 | H18: =H13 -> 430.344 | I18: =I13 -> 430.344 | J18: =J13 -> 430.344 | K18: =K13 -> 430.344 | L18: =L13 -> 430.344 | M18: =M13 -> 430.344 | ... O18: =O13 -> 430.344 | Q18: *25年は５0％OFFで計上
B19: 客単価 | D19: スタンド（社外） | F19: =F14 -> 664.716 | G19: =G14 -> 664.716 | H19: =H14 -> 664.716 | I19: =I14 -> 664.716 | J19: =J14 -> 664.716 | K19: =K14 -> 664.716 | L19: =L14 -> 664.716 | M19: =M14 -> 664.716 | ... O19: =O14 -> 664.716
B20: 客単価 | D20: フロー（セミナー等） | F20: =F15 -> 376 | G20: =G15 -> 376 | H20: =H15 -> 376 | I20: =I15 -> 376 | J20: =J15 -> 376 | K20: =K15 -> 376 | L20: =L15 -> 376 | M20: =M15 -> 376 | ... O20: =O15 -> 376
B21: 客単価 | C21: 代理店 | D21: アプリ | F21: =$R$21*$R$22*12*0.5/1000 -> 120 | G21: =$R$21*$R$22*12/1000 -> 240 | H21: =$R$21*$R$22*12/1000 -> 240 | I21: =$R$21*$R$22*12/1000 -> 240 | J21: =$R$21*$R$22*12/1000 -> 240 | K21: =$R$21*$R$22*12/1000 -> 240 | L21: =$R$21*$R$22*12/1000 -> 240 | M21: =$R$21*$R$22*12/1000 -> 240 | N21: =$R$21*$R$22*12/1000 -> 240 | O21: =$R$21*$R$22*12/1000 -> 240 | Q21: 従業員数 | R21: 80 | S21: 人
B22: 客単価 | D22: スタンド（宅急便） | F22: =F17/2 -> 215.172 | G22: =G17/2 -> 215.172 | H22: =H17/2 -> 215.172 | I22: =I17/2 -> 215.172 | J22: =J17/2 -> 215.172 | K22: =K17/2 -> 215.172 | L22: =L17/2 -> 215.172 | M22: =M17/2 -> 215.172 | ... O22: =O17/2 -> 215.172 | Q22: 単価 | R22: 250 | S22: 円/月・人
B23: 客単価 | D23: スタンド（ＦＳ） | F23: =F18/2 -> 215.172 | G23: =G18/2 -> 215.172 | H23: =H18/2 -> 215.172 | I23: =I18/2 -> 215.172 | J23: =J18/2 -> 215.172 | K23: =K18/2 -> 215.172 | L23: =L18/2 -> 215.172 | M23: =M18/2 -> 215.172 | ... O23: =O18/2 -> 215.172 | Q23: ※25年は半額CPを実施する
B24: 客単価 | D24: スタンド（社外） | F24: =F19/2 -> 332.358 | G24: =G19/2 -> 332.358 | H24: =H19/2 -> 332.358 | I24: =I19/2 -> 332.358 | J24: =J19/2 -> 332.358 | K24: =K19/2 -> 332.358 | L24: =L19/2 -> 332.358 | M24: =M19/2 -> 332.358 | ... O24: =O19/2 -> 332.358
B25: 客単価 | D25: フロー（セミナー等） | F25: =F20/2 -> 188 | G25: =G20/2 -> 188 | H25: =H20/2 -> 188 | I25: =I20/2 -> 188 | J25: =J20/2 -> 188 | K25: =K20/2 -> 188 | L25: =L20/2 -> 188 | M25: =M20/2 -> 188 | ... O25: =O20/2 -> 188

Sheet 原価・変動費
A1: 単位：％
E3: 24年 | F3: 25年 | G3: 26年 | H3: 27年 | I3: 28年 | J3: 29年 | K3: 30年 | L3: 31年 | M3: 32年 | N3: 33年 | O3: 34年
B4: 変動高比
C5: 原価
C6: 原価 | D6: アプリ | E6: 0 | F6: =E6 -> 0 | G6: =F6 -> 0 | H6: =G6 -> 0 | I6: =H6 -> 0 | J6: =I6 -> 0 | K6: =J6 -> 0 | L6: =K6 -> 0 | M6: =L6 -> 0 | ... O6: =N6 -> 0
C7: 原価 | D7: スタンド（宅急便） | E7: 0.33 | F7: =E7 -> 0.33 | G7: =F7 -> 0.33 | H7: =G7 -> 0.33 | I7: =H7 -> 0.33 | J7: =I7 -> 0.33 | K7: =J7 -> 0.33 | L7: =K7 -> 0.33 | M7: =L7 -> 0.33 | ... O7: =N7 -> 0.33
C8: 原価 | D8: スタンド（ＦＳ） | E8: 0.33 | F8: =E8 -> 0.33 | G8: =F8 -> 0.33 | H8: =G8 -> 0.33 | I8: =H8 -> 0.33 | J8: =I8 -> 0.33 | K8: =J8 -> 0.33 | L8: =K8 -> 0.33 | M8: =L8 -> 0.33 | ... O8: =N8 -> 0.33
C9: 原価 | D9: スタンド（社外） | E9: 0 | F9: =E9 -> 0 | G9: =F9 -> 0 | H9: =G9 -> 0 | I9: =H9 -> 0 | J9: =I9 -> 0 | K9: =J9 -> 0 | L9: =K9 -> 0 | M9: =L9 -> 0 | ... O9: =N9 -> 0
C10: 原価 | D10: フロー（セミナー等） | E10: 0 | F10: =E10 -> 0 | G10: =F10 -> 0 | H10: =G10 -> 0 | I10: =H10 -> 0 | J10: =I10 -> 0 | K10: =J10 -> 0 | L10: =K10 -> 0 | M10: =L10 -> 0 | ... O10: =N10 -> 0
C11: 原価 | D11: ＥＣストア | E11: 0.45 | F11: =E11 -> 0.45 | G11: =F11 -> 0.45 | H11: =G11 -> 0.45 | I11: =H11 -> 0.45 | J11: =I11 -> 0.45 | K11: =J11 -> 0.45 | L11: =K11 -> 0.45 | M11: =L11 -> 0.45 | ... O11: =N11 -> 0.45
C12: 原価 | D12: 卸売 | E12: 0.8 | F12: =E12 -> 0.8 | G12: =F12 -> 0.8 | H12: =G12 -> 0.8 | I12: =H12 -> 0.8 | J12: =I12 -> 0.8 | K12: =J12 -> 0.8 | L12: =K12 -> 0.8 | M12: =L12 -> 0.8 | ... O12: =N12 -> 0.8
C13: 原価 | D13: 企業内手売 | E13: 0.45 | F13: =E13 -> 0.45 | G13: =F13 -> 0.45 | H13: =G13 -> 0.45 | I13: =H13 -> 0.45 | J13: =I13 -> 0.45 | K13: =J13 -> 0.45 | L13: =K13 -> 0.45 | M13: =L13 -> 0.45 | ... O13: =N13 -> 0.45
C14: 変動費計
C15: 変動費計 | D15: アプリ | E15: =E24+E33+E42+E51+E60+E69+E78+E87+E96+E105 -> 0.46944792 | F15: =F24+F33+F42+F51+F60+F69+F78+F87+F96+F105 -> 0.46944792 | G15: =G24+G33+G42+G51+G60+G69+G78+G87+G96+G105 -> 0.46944792 | H15: =H24+H33+H42+H51+H60+H69+H78+H87+H96+H105 -> 0.46944792 | I15: =I24+I33+I42+I51+I60+I69+I78+I87+I96+I105 -> 0.46944792 | J15: =J24+J33+J42+J51+J60+J69+J78+J87+J96+J105 -> 0.46944792 | K15: =K24+K33+K42+K51+K60+K69+K78+K87+K96+K105 -> 0.46944792 | L15: =L24+L33+L42+L51+L60+L69+L78+L87+L96+L105 -> 0.46944792 | ... O15: =O24+O33+O42+O51+O60+O69+O78+O87+O96+O105 -> 0.46944792
C16: 変動費計 | D16: スタンド（宅急便） | E16: =E25+E34+E43+E52+E61+E70+E79+E88+E97+E106 -> 0.144 | F16: =F25+F34+F43+F52+F61+F70+F79+F88+F97+F106 -> 0.144 | G16: =G25+G34+G43+G52+G61+G70+G79+G88+G97+G106 -> 0.144 | H16: =H25+H34+H43+H52+H61+H70+H79+H88+H97+H106 -> 0.144 | I16: =I25+I34+I43+I52+I61+I70+I79+I88+I97+I106 -> 0.144 | J16: =J25+J34+J43+J52+J61+J70+J79+J88+J97+J106 -> 0.144 | K16: =K25+K34+K43+K52+K61+K70+K79+K88+K97+K106 -> 0.144 | L16: =L25+L34+L43+L52+L61+L70+L79+L88+L97+L106 -> 0.144 | ... O16: =O25+O34+O43+O52+O61+O70+O79+O88+O97+O106 -> 0.144
C17: 変動費計 | D17: スタンド（ＦＳ） | E17: =E26+E35+E44+E53+E62+E71+E80+E89+E98+E107 -> 0.0633 | F17: =F26+F35+F44+F53+F62+F71+F80+F89+F98+F107 -> 0.0633 | G17: =G26+G35+G44+G53+G62+G71+G80+G89+G98+G107 -> 0.0633 | H17: =H26+H35+H44+H53+H62+H71+H80+H89+H98+H107 -> 0.0633 | I17: =I26+I35+I44+I53+I62+I71+I80+I89+I98+I107 -> 0.0633 | J17: =J26+J35+J44+J53+J62+J71+J80+J89+J98+J107 -> 0.0633 | K17: =K26+K35+K44+K53+K62+K71+K80+K89+K98+K107 -> 0.0633 | L17: =L26+L35+L44+L53+L62+L71+L80+L89+L98+L107 -> 0.0633 | ... O17: =O26+O35+O44+O53+O62+O71+O80+O89+O98+O107 -> 0.0633
C18: 変動費計 | D18: スタンド（社外） | E18: =E27+E36+E45+E54+E63+E72+E81+E90+E99+E108 -> 0.857 | F18: =F27+F36+F45+F54+F63+F72+F81+F90+F99+F108 -> 0.857 | G18: =G27+G36+G45+G54+G63+G72+G81+G90+G99+G108 -> 0.857 | H18: =H27+H36+H45+H54+H63+H72+H81+H90+H99+H108 -> 0.857 | I18: =I27+I36+I45+I54+I63+I72+I81+I90+I99+I108 -> 0.857 | J18: =J27+J36+J45+J54+J63+J72+J81+J90+J99+J108 -> 0.857 | K18: =K27+K36+K45+K54+K63+K72+K81+K90+K99+K108 -> 0.857 | L18: =L27+L36+L45+L54+L63+L72+L81+L90+L99+L108 -> 0.857 | ... O18: =O27+O36+O45+O54+O63+O72+O81+O90+O99+O108 -> 0.857
C19: 変動費計 | D19: フロー（セミナー等） | E19: =E28+E37+E46+E55+E64+E73+E82+E91+E100+E109 -> 0.5233 | F19: =F28+F37+F46+F55+F64+F73+F82+F91+F100+F109 -> 0.5233 | G19: =G28+G37+G46+G55+G64+G73+G82+G91+G100+G109 -> 0.5233 | H19: =H28+H37+H46+H55+H64+H73+H82+H91+H100+H109 -> 0.5233 | I19: =I28+I37+I46+I55+I64+I73+I82+I91+I100+I109 -> 0.5233 | J19: =J28+J37+J46+J55+J64+J73+J82+J91+J100+J109 -> 0.5233 | K19: =K28+K37+K46+K55+K64+K73+K82+K91+K100+K109 -> 0.5233 | L19: =L28+L37+L46+L55+L64+L73+L82+L91+L100+L109 -> 0.5233 | ... O19: =O28+O37+O46+O55+O64+O73+O82+O91+O100+O109 -> 0.5233
C20: 変動費計 | D20: ＥＣストア | E20: =E29+E38+E47+E56+E65+E74+E83+E92+E101+E110 -> 0.3856 | F20: =F29+F38+F47+F56+F65+F74+F83+F92+F101+F110 -> 0.3856 | G20: =G29+G38+G47+G56+G65+G74+G83+G92+G101+G110 -> 0.3856 | H20: =H29+H38+H47+H56+H65+H74+H83+H92+H101+H110 -> 0.3856 | I20: =I29+I38+I47+I56+I65+I74+I83+I92+I101+I110 -> 0.3856 | J20: =J29+J38+J47+J56+J65+J74+J83+J92+J101+J110 -> 0.3856 | K20: =K29+K38+K47+K56+K65+K74+K83+K92+K101+K110 -> 0.3856 | L20: =L29+L38+L47+L56+L65+L74+L83+L92+L101+L110 -> 0.3856 | ... O20: =O29+O38+O47+O56+O65+O74+O83+O92+O101+O110 -> 0.3856
C21: 変動費計 | D21: 卸売 | E21: =E30+E39+E48+E57+E66+E75+E84+E93+E102+E111 -> 0.05 | F21: =F30+F39+F48+F57+F66+F75+F84+F93+F102+F111 -> 0.05 | G21: =G30+G39+G48+G57+G66+G75+G84+G93+G102+G111 -> 0.05 | H21: =H30+H39+H48+H57+H66+H75+H84+H93+H102+H111 -> 0.05 | I21: =I30+I39+I48+I57+I66+I75+I84+I93+I102+I111 -> 0.05 | J21: =J30+J39+J48+J57+J66+J75+J84+J93+J102+J111 -> 0.05 | K21: =K30+K39+K48+K57+K66+K75+K84+K93+K102+K111 -> 0.05 | L21: =L30+L39+L48+L57+L66+L75+L84+L93+L102+L111 -> 0.05 | ... O21: =O30+O39+O48+O57+O66+O75+O84+O93+O102+O111 -> 0.05
C22: 変動費計 | D22: 企業内手売 | E22: =E31+E40+E49+E58+E67+E76+E85+E94+E103+E112 -> 0.4 | F22: =F31+F40+F49+F58+F67+F76+F85+F94+F103+F112 -> 0.4 | G22: =G31+G40+G49+G58+G67+G76+G85+G94+G103+G112 -> 0.4 | H22: =H31+H40+H49+H58+H67+H76+H85+H94+H103+H112 -> 0.4 | I22: =I31+I40+I49+I58+I67+I76+I85+I94+I103+I112 -> 0.4 | J22: =J31+J40+J49+J58+J67+J76+J85+J94+J103+J112 -> 0.4 | K22: =K31+K40+K49+K58+K67+K76+K85+K94+K103+K112 -> 0.4 | L22: =L31+L40+L49+L58+L67+L76+L85+L94+L103+L112 -> 0.4 | ... O22: =O31+O40+O49+O58+O67+O76+O85+O94+O103+O112 -> 0.4
C23: 運搬費（KGL）
C24: 運搬費（KGL） | D24: アプリ | E24: 0 | F24: =E24 -> 0 | G24: =F24 -> 0 | H24: =G24 -> 0 | I24: =H24 -> 0 | J24: =I24 -> 0 | K24: =J24 -> 0 | L24: =K24 -> 0 | M24: =L24 -> 0 | ... O24: =N24 -> 0
C25: 運搬費（KGL） | D25: スタンド（宅急便） | E25: 0.012 | F25: =E25 -> 0.012 | G25: =F25 -> 0.012 | H25: =G25 -> 0.012 | I25: =H25 -> 0.012 | J25: =I25 -> 0.012 | K25: =J25 -> 0.012 | L25: =K25 -> 0.012 | M25: =L25 -> 0.012 | ... O25: =N25 -> 0.012
C26: 運搬費（KGL） | D26: スタンド（ＦＳ） | E26: 0.012 | F26: =E26 -> 0.012 | G26: =F26 -> 0.012 | H26: =G26 -> 0.012 | I26: =H26 -> 0.012 | J26: =I26 -> 0.012 | K26: =J26 -> 0.012 | L26: =K26 -> 0.012 | M26: =L26 -> 0.012 | ... O26: =N26 -> 0.012
C27: 運搬費（KGL） | D27: スタンド（社外） | E27: 0 | F27: =E27 -> 0 | G27: =F27 -> 0 | H27: =G27 -> 0 | I27: =H27 -> 0 | J27: =I27 -> 0 | K27: =J27 -> 0 | L27: =K27 -> 0 | M27: =L27 -> 0 | ... O27: =N27 -> 0
C28: 運搬費（KGL） | D28: フロー（セミナー等） | E28: 0 | F28: =E28 -> 0 | G28: =F28 -> 0 | H28: =G28 -> 0 | I28: =H28 -> 0 | J28: =I28 -> 0 | K28: =J28 -> 0 | L28: =K28 -> 0 | M28: =L28 -> 0 | ... O28: =N28 -> 0
C29: 運搬費（KGL） | D29: ＥＣストア | E29: 0.05 | F29: =E29 -> 0.05 | G29: =F29 -> 0.05 | H29: =G29 -> 0.05 | I29: =H29 -> 0.05 | J29: =I29 -> 0.05 | K29: =J29 -> 0.05 | L29: =K29 -> 0.05 | M29: =L29 -> 0.05 | ... O29: =N29 -> 0.05
C30: 運搬費（KGL） | D30: 卸売 | E30: 0.05 | F30: =E30 -> 0.05 | G30: =F30 -> 0.05 | H30: =G30 -> 0.05 | I30: =H30 -> 0.05 | J30: =I30 -> 0.05 | K30: =J30 -> 0.05 | L30: =K30 -> 0.05 | M30: =L30 -> 0.05 | ... O30: =N30 -> 0.05
C31: 運搬費（KGL） | D31: 企業内手売 | E31: 0.05 | F31: =E31 -> 0.05 | G31: =F31 -> 0.05 | H31: =G31 -> 0.05 | I31: =H31 -> 0.05 | J31: =I31 -> 0.05 | K31: =J31 -> 0.05 | L31: =K31 -> 0.05 | M31: =L31 -> 0.05 | ... O31: =N31 -> 0.05
C32: ヤマト委託費（商品）
C33: ヤマト委託費（商品） | D33: アプリ | E33: 0 | F33: =E33 -> 0 | G33: =F33 -> 0 | H33: =G33 -> 0 | I33: =H33 -> 0 | J33: =I33 -> 0 | K33: =J33 -> 0 | L33: =K33 -> 0 | M33: =L33 -> 0 | ... O33: =N33 -> 0
C34: ヤマト委託費（商品） | D34: スタンド（宅急便） | E34: 0.115 | F34: =E34 -> 0.115 | G34: =F34 -> 0.115 | H34: =G34 -> 0.115 | I34: =H34 -> 0.115 | J34: =I34 -> 0.115 | K34: =J34 -> 0.115 | L34: =K34 -> 0.115 | M34: =L34 -> 0.115 | ... O34: =N34 -> 0.115
C35: ヤマト委託費（商品） | D35: スタンド（ＦＳ） | E35: 0 | F35: =E35 -> 0 | G35: =F35 -> 0 | H35: =G35 -> 0 | I35: =H35 -> 0 | J35: =I35 -> 0 | K35: =J35 -> 0 | L35: =K35 -> 0 | M35: =L35 -> 0 | ... O35: =N35 -> 0
C36: ヤマト委託費（商品） | D36: スタンド（社外） | E36: 0 | F36: =E36 -> 0 | G36: =F36 -> 0 | H36: =G36 -> 0 | I36: =H36 -> 0 | J36: =I36 -> 0 | K36: =J36 -> 0 | L36: =K36 -> 0 | M36: =L36 -> 0 | ... O36: =N36 -> 0
C37: ヤマト委託費（商品） | D37: フロー（セミナー等） | E37: 0 | F37: =E37 -> 0 | G37: =F37 -> 0 | H37: =G37 -> 0 | I37: =H37 -> 0 | J37: =I37 -> 0 | K37: =J37 -> 0 | L37: =K37 -> 0 | M37: =L37 -> 0 | ... O37: =N37 -> 0
C38: ヤマト委託費（商品） | D38: ＥＣストア | E38: 0.333 | F38: =E38 -> 0.333 | G38: =F38 -> 0.333 | H38: =G38 -> 0.333 | I38: =H38 -> 0.333 | J38: =I38 -> 0.333 | K38: =J38 -> 0.333 | L38: =K38 -> 0.333 | M38: =L38 -> 0.333 | ... O38: =N38 -> 0.333
C39: ヤマト委託費（商品） | D39: 卸売 | E39: 0 | F39: =E39 -> 0 | G39: =F39 -> 0 | H39: =G39 -> 0 | I39: =H39 -> 0 | J39: =I39 -> 0 | K39: =J39 -> 0 | L39: =K39 -> 0 | M39: =L39 -> 0 | ... O39: =N39 -> 0
C40: ヤマト委託費（商品） | D40: 企業内手売 | E40: 0.333 | F40: =E40 -> 0.333 | G40: =F40 -> 0.333 | H40: =G40 -> 0.333 | I40: =H40 -> 0.333 | J40: =I40 -> 0.333 | K40: =J40 -> 0.333 | L40: =K40 -> 0.333 | M40: =L40 -> 0.333 | ... O40: =N40 -> 0.333
C41: NP手数料
C42: NP手数料 | D42: アプリ | E42: 0.017 | F42: =E42 -> 0.017 | G42: =F42 -> 0.017 | H42: =G42 -> 0.017 | I42: =H42 -> 0.017 | J42: =I42 -> 0.017 | K42: =J42 -> 0.017 | L42: =K42 -> 0.017 | M42: =L42 -> 0.017 | ... O42: =N42 -> 0.017
C43: NP手数料 | D43: スタンド（宅急便） | E43: 0.017 | F43: =E43 -> 0.017 | G43: =F43 -> 0.017 | H43: =G43 -> 0.017 | I43: =H43 -> 0.017 | J43: =I43 -> 0.017 | K43: =J43 -> 0.017 | L43: =K43 -> 0.017 | M43: =L43 -> 0.017 | ... O43: =N43 -> 0.017
C44: NP手数料 | D44: スタンド（ＦＳ） | E44: 0.0113 | F44: =E44 -> 0.0113 | G44: =F44 -> 0.0113 | H44: =G44 -> 0.0113 | I44: =H44 -> 0.0113 | J44: =I44 -> 0.0113 | K44: =J44 -> 0.0113 | L44: =K44 -> 0.0113 | M44: =L44 -> 0.0113 | ... O44: =N44 -> 0.0113 | P44: ※売上の2/3（企業請求分）に発生するため1.13%
C45: NP手数料 | D45: スタンド（社外） | E45: 0.017 | F45: =E45 -> 0.017 | G45: =F45 -> 0.017 | H45: =G45 -> 0.017 | I45: =H45 -> 0.017 | J45: =I45 -> 0.017 | K45: =J45 -> 0.017 | L45: =K45 -> 0.017 | M45: =L45 -> 0.017 | ... O45: =N45 -> 0.017
C46: NP手数料 | D46: フロー（セミナー等） | E46: 0.017 | F46: =E46 -> 0.017 | G46: =F46 -> 0.017 | H46: =G46 -> 0.017 | I46: =H46 -> 0.017 | J46: =I46 -> 0.017 | K46: =J46 -> 0.017 | L46: =K46 -> 0.017 | M46: =L46 -> 0.017 | ... O46: =N46 -> 0.017
C47: NP手数料 | D47: ＥＣストア | E47: 0 | F47: =E47 -> 0 | G47: =F47 -> 0 | H47: =G47 -> 0 | I47: =H47 -> 0 | J47: =I47 -> 0 | K47: =J47 -> 0 | L47: =K47 -> 0 | M47: =L47 -> 0 | ... O47: =N47 -> 0
C48: NP手数料 | D48: 卸売 | E48: 0 | F48: =E48 -> 0 | G48: =F48 -> 0 | H48: =G48 -> 0 | I48: =H48 -> 0 | J48: =I48 -> 0 | K48: =J48 -> 0 | L48: =K48 -> 0 | M48: =L48 -> 0 | ... O48: =N48 -> 0
C49: NP手数料 | D49: 企業内手売 | E49: 0.017 | F49: =E49 -> 0.017 | G49: =F49 -> 0.017 | H49: =G49 -> 0.017 | I49: =H49 -> 0.017 | J49: =I49 -> 0.017 | K49: =J49 -> 0.017 | L49: =K49 -> 0.017 | M49: =L49 -> 0.017 | ... O49: =N49 -> 0.017
C50: EC手数料（GMO/●●）
C51: EC手数料（GMO/●●） | D51: アプリ | E51: 0 | F51: =E51 -> 0 | G51: =F51 -> 0 | H51: =G51 -> 0 | I51: =H51 -> 0 | J51: =I51 -> 0 | K51: =J51 -> 0 | L51: =K51 -> 0 | M51: =L51 -> 0 | ... O51: =N51 -> 0
C52: EC手数料（GMO/●●） | D52: スタンド（宅急便） | E52: 0 | F52: =E52 -> 0 | G52: =F52 -> 0 | H52: =G52 -> 0 | I52: =H52 -> 0 | J52: =I52 -> 0 | K52: =J52 -> 0 | L52: =K52 -> 0 | M52: =L52 -> 0 | ... O52: =N52 -> 0
C53: EC手数料（GMO/●●） | D53: スタンド（ＦＳ） | E53: 0 | F53: =E53 -> 0 | G53: =F53 -> 0 | H53: =G53 -> 0 | I53: =H53 -> 0 | J53: =I53 -> 0 | K53: =J53 -> 0 | L53: =K53 -> 0 | M53: =L53 -> 0 | ... O53: =N53 -> 0
C54: EC手数料（GMO/●●） | D54: スタンド（社外） | E54: 0 | F54: =E54 -> 0 | G54: =F54 -> 0 | H54: =G54 -> 0 | I54: =H54 -> 0 | J54: =I54 -> 0 | K54: =J54 -> 0 | L54: =K54 -> 0 | M54: =L54 -> 0 | ... O54: =N54 -> 0
C55: EC手数料（GMO/●●） | D55: フロー（セミナー等） | E55: 0 | F55: =E55 -> 0 | G55: =F55 -> 0 | H55: =G55 -> 0 | I55: =H55 -> 0 | J55: =I55 -> 0 | K55: =J55 -> 0 | L55: =K55 -> 0 | M55: =L55 -> 0 | ... O55: =N55 -> 0
C56: EC手数料（GMO/●●） | D56: ＥＣストア | E56: 0.0025 | F56: =E56 -> 0.0025 | G56: =F56 -> 0.0025 | H56: =G56 -> 0.0025 | I56: =H56 -> 0.0025 | J56: =I56 -> 0.0025 | K56: =J56 -> 0.0025 | L56: =K56 -> 0.0025 | M56: =L56 -> 0.0025 | ... O56: =N56 -> 0.0025
C57: EC手数料（GMO/●●） | D57: 卸売 | E57: 0 | F57: =E57 -> 0 | G57: =F57 -> 0 | H57: =G57 -> 0 | I57: =H57 -> 0 | J57: =I57 -> 0 | K57: =J57 -> 0 | L57: =K57 -> 0 | M57: =L57 -> 0 | ... O57: =N57 -> 0
C58: EC手数料（GMO/●●） | D58: 企業内手売 | E58: 0 | F58: =E58 -> 0 | G58: =F58 -> 0 | H58: =G58 -> 0 | I58: =H58 -> 0 | J58: =I58 -> 0 | K58: =J58 -> 0 | L58: =K58 -> 0 | M58: =L58 -> 0 | ... O58: =N58 -> 0
C59: P/F手数料（テモナ）
C60: P/F手数料（テモナ） | D60: アプリ | E60: 0 | F60: =E60 -> 0 | G60: =F60 -> 0 | H60: =G60 -> 0 | I60: =H60 -> 0 | J60: =I60 -> 0 | K60: =J60 -> 0 | L60: =K60 -> 0 | M60: =L60 -> 0 | ... O60: =N60 -> 0
C61: P/F手数料（テモナ） | D61: スタンド（宅急便） | E61: 0 | F61: =E61 -> 0 | G61: =F61 -> 0 | H61: =G61 -> 0 | I61: =H61 -> 0 | J61: =I61 -> 0 | K61: =J61 -> 0 | L61: =K61 -> 0 | M61: =L61 -> 0 | ... O61: =N61 -> 0
C62: P/F手数料（テモナ） | D62: スタンド（ＦＳ） | E62: 0 | F62: =E62 -> 0 | G62: =F62 -> 0 | H62: =G62 -> 0 | I62: =H62 -> 0 | J62: =I62 -> 0 | K62: =J62 -> 0 | L62: =K62 -> 0 | M62: =L62 -> 0 | ... O62: =N62 -> 0
C63: P/F手数料（テモナ） | D63: スタンド（社外） | E63: 0 | F63: =E63 -> 0 | G63: =F63 -> 0 | H63: =G63 -> 0 | I63: =H63 -> 0 | J63: =I63 -> 0 | K63: =J63 -> 0 | L63: =K63 -> 0 | M63: =L63 -> 0 | ... O63: =N63 -> 0
C64: P/F手数料（テモナ） | D64: フロー（セミナー等） | E64: 0 | F64: =E64 -> 0 | G64: =F64 -> 0 | H64: =G64 -> 0 | I64: =H64 -> 0 | J64: =I64 -> 0 | K64: =J64 -> 0 | L64: =K64 -> 0 | M64: =L64 -> 0 | ... O64: =N64 -> 0
C65: P/F手数料（テモナ） | D65: ＥＣストア | E65: 0.0001 | F65: =E65 -> 0.0001 | G65: =F65 -> 0.0001 | H65: =G65 -> 0.0001 | I65: =H65 -> 0.0001 | J65: =I65 -> 0.0001 | K65: =J65 -> 0.0001 | L65: =K65 -> 0.0001 | M65: =L65 -> 0.0001 | ... O65: =N65 -> 0.0001
C66: P/F手数料（テモナ） | D66: 卸売 | E66: 0 | F66: =E66 -> 0 | G66: =F66 -> 0 | H66: =G66 -> 0 | I66: =H66 -> 0 | J66: =I66 -> 0 | K66: =J66 -> 0 | L66: =K66 -> 0 | M66: =L66 -> 0 | ... O66: =N66 -> 0
C67: P/F手数料（テモナ） | D67: 企業内手売 | E67: 0 | F67: =E67 -> 0 | G67: =F67 -> 0 | H67: =G67 -> 0 | I67: =H67 -> 0 | J67: =I67 -> 0 | K67: =J67 -> 0 | L67: =K67 -> 0 | M67: =L67 -> 0 | ... O67: =N67 -> 0
C68: ELEPAY手数料
C69: ELEPAY手数料 | D69: アプリ | E69: 0 | F69: =E69 -> 0 | G69: =F69 -> 0 | H69: =G69 -> 0 | I69: =H69 -> 0 | J69: =I69 -> 0 | K69: =J69 -> 0 | L69: =K69 -> 0 | M69: =L69 -> 0 | ... O69: =N69 -> 0
C70: ELEPAY手数料 | D70: スタンド（宅急便） | E70: 0 | F70: =E70 -> 0 | G70: =F70 -> 0 | H70: =G70 -> 0 | I70: =H70 -> 0 | J70: =I70 -> 0 | K70: =J70 -> 0 | L70: =K70 -> 0 | M70: =L70 -> 0 | ... O70: =N70 -> 0
C71: ELEPAY手数料 | D71: スタンド（ＦＳ） | E71: 0.04 | F71: =E71 -> 0.04 | G71: =F71 -> 0.04 | H71: =G71 -> 0.04 | I71: =H71 -> 0.04 | J71: =I71 -> 0.04 | K71: =J71 -> 0.04 | L71: =K71 -> 0.04 | M71: =L71 -> 0.04 | ... O71: =N71 -> 0.04
C72: ELEPAY手数料 | D72: スタンド（社外） | E72: 0.04 | F72: =E72 -> 0.04 | G72: =F72 -> 0.04 | H72: =G72 -> 0.04 | I72: =H72 -> 0.04 | J72: =I72 -> 0.04 | K72: =J72 -> 0.04 | L72: =K72 -> 0.04 | M72: =L72 -> 0.04 | ... O72: =N72 -> 0.04
C73: ELEPAY手数料 | D73: フロー（セミナー等） | E73: 0 | F73: =E73 -> 0 | G73: =F73 -> 0 | H73: =G73 -> 0 | I73: =H73 -> 0 | J73: =I73 -> 0 | K73: =J73 -> 0 | L73: =K73 -> 0 | M73: =L73 -> 0 | ... O73: =N73 -> 0 | Q73: 148425
C74: ELEPAY手数料 | D74: ＥＣストア | E74: 0 | F74: =E74 -> 0 | G74: =F74 -> 0 | H74: =G74 -> 0 | I74: =H74 -> 0 | J74: =I74 -> 0 | K74: =J74 -> 0 | L74: =K74 -> 0 | M74: =L74 -> 0 | ... O74: =N74 -> 0 | Q74: =Q73*400*12 -> 712440000
C75: ELEPAY手数料 | D75: 卸売 | E75: 0 | F75: =E75 -> 0 | G75: =F75 -> 0 | H75: =G75 -> 0 | I75: =H75 -> 0 | J75: =I75 -> 0 | K75: =J75 -> 0 | L75: =K75 -> 0 | M75: =L75 -> 0 | ... O75: =N75 -> 0
C76: ELEPAY手数料 | D76: 企業内手売 | E76: 0 | F76: =E76 -> 0 | G76: =F76 -> 0 | H76: =G76 -> 0 | I76: =H76 -> 0 | J76: =I76 -> 0 | K76: =J76 -> 0 | L76: =K76 -> 0 | M76: =L76 -> 0 | ... O76: =N76 -> 0
C77: フロー（セミナー等）委託費
C78: フロー（セミナー等）委託費 | D78: アプリ | E78: 0 | F78: =E78 -> 0 | G78: =F78 -> 0 | H78: =G78 -> 0 | I78: =H78 -> 0 | J78: =I78 -> 0 | K78: =J78 -> 0 | L78: =K78 -> 0 | M78: =L78 -> 0 | ... O78: =N78 -> 0
C79: フロー（セミナー等）委託費 | D79: スタンド（宅急便） | E79: 0 | F79: =E79 -> 0 | G79: =F79 -> 0 | H79: =G79 -> 0 | I79: =H79 -> 0 | J79: =I79 -> 0 | K79: =J79 -> 0 | L79: =K79 -> 0 | M79: =L79 -> 0 | ... O79: =N79 -> 0
C80: フロー（セミナー等）委託費 | D80: スタンド（ＦＳ） | E80: 0 | F80: =E80 -> 0 | G80: =F80 -> 0 | H80: =G80 -> 0 | I80: =H80 -> 0 | J80: =I80 -> 0 | K80: =J80 -> 0 | L80: =K80 -> 0 | M80: =L80 -> 0 | ... O80: =N80 -> 0
C81: フロー（セミナー等）委託費 | D81: スタンド（社外） | E81: 0 | F81: =E81 -> 0 | G81: =F81 -> 0 | H81: =G81 -> 0 | I81: =H81 -> 0 | J81: =I81 -> 0 | K81: =J81 -> 0 | L81: =K81 -> 0 | M81: =L81 -> 0 | ... O81: =N81 -> 0
C82: フロー（セミナー等）委託費 | D82: フロー（セミナー等） | E82: 0.5063 | F82: =E82 -> 0.5063 | G82: =F82 -> 0.5063 | H82: =G82 -> 0.5063 | I82: =H82 -> 0.5063 | J82: =I82 -> 0.5063 | K82: =J82 -> 0.5063 | L82: =K82 -> 0.5063 | M82: =L82 -> 0.5063 | ... O82: =N82 -> 0.5063
C83: フロー（セミナー等）委託費 | D83: ＥＣストア | E83: 0 | F83: =E83 -> 0 | G83: =F83 -> 0 | H83: =G83 -> 0 | I83: =H83 -> 0 | J83: =I83 -> 0 | K83: =J83 -> 0 | L83: =K83 -> 0 | M83: =L83 -> 0 | ... O83: =N83 -> 0
C84: フロー（セミナー等）委託費 | D84: 卸売 | E84: 0 | F84: =E84 -> 0 | G84: =F84 -> 0 | H84: =G84 -> 0 | I84: =H84 -> 0 | J84: =I84 -> 0 | K84: =J84 -> 0 | L84: =K84 -> 0 | M84: =L84 -> 0 | ... O84: =N84 -> 0
C85: フロー（セミナー等）委託費 | D85: 企業内手売 | E85: 0 | F85: =E85 -> 0 | G85: =F85 -> 0 | H85: =G85 -> 0 | I85: =H85 -> 0 | J85: =I85 -> 0 | K85: =J85 -> 0 | L85: =K85 -> 0 | M85: =L85 -> 0 | ... O85: =N85 -> 0
C86: スタンド委託費（社外）
C87: スタンド委託費（社外） | D87: アプリ | E87: 0 | F87: =E87 -> 0 | G87: =F87 -> 0 | H87: =G87 -> 0 | I87: =H87 -> 0 | J87: =I87 -> 0 | K87: =J87 -> 0 | L87: =K87 -> 0 | M87: =L87 -> 0 | ... O87: =N87 -> 0
C88: スタンド委託費（社外） | D88: スタンド（宅急便） | E88: 0 | F88: =E88 -> 0 | G88: =F88 -> 0 | H88: =G88 -> 0 | I88: =H88 -> 0 | J88: =I88 -> 0 | K88: =J88 -> 0 | L88: =K88 -> 0 | M88: =L88 -> 0 | ... O88: =N88 -> 0
C89: スタンド委託費（社外） | D89: スタンド（ＦＳ） | E89: 0 | F89: =E89 -> 0 | G89: =F89 -> 0 | H89: =G89 -> 0 | I89: =H89 -> 0 | J89: =I89 -> 0 | K89: =J89 -> 0 | L89: =K89 -> 0 | M89: =L89 -> 0 | ... O89: =N89 -> 0
C90: スタンド委託費（社外） | D90: スタンド（社外） | E90: 0.8 | F90: =E90 -> 0.8 | G90: =F90 -> 0.8 | H90: =G90 -> 0.8 | I90: =H90 -> 0.8 | J90: =I90 -> 0.8 | K90: =J90 -> 0.8 | L90: =K90 -> 0.8 | M90: =L90 -> 0.8 | ... O90: =N90 -> 0.8
C91: スタンド委託費（社外） | D91: フロー（セミナー等） | E91: 0 | F91: =E91 -> 0 | G91: =F91 -> 0 | H91: =G91 -> 0 | I91: =H91 -> 0 | J91: =I91 -> 0 | K91: =J91 -> 0 | L91: =K91 -> 0 | M91: =L91 -> 0 | ... O91: =N91 -> 0
C92: スタンド委託費（社外） | D92: ＥＣストア | E92: 0 | F92: =E92 -> 0 | G92: =F92 -> 0 | H92: =G92 -> 0 | I92: =H92 -> 0 | J92: =I92 -> 0 | K92: =J92 -> 0 | L92: =K92 -> 0 | M92: =L92 -> 0 | ... O92: =N92 -> 0
C93: スタンド委託費（社外） | D93: 卸売 | E93: 0 | F93: =E93 -> 0 | G93: =F93 -> 0 | H93: =G93 -> 0 | I93: =H93 -> 0 | J93: =I93 -> 0 | K93: =J93 -> 0 | L93: =K93 -> 0 | M93: =L93 -> 0 | ... O93: =N93 -> 0
C94: スタンド委託費（社外） | D94: 企業内手売 | E94: 0 | F94: =E94 -> 0 | G94: =F94 -> 0 | H94: =G94 -> 0 | I94: =H94 -> 0 | J94: =I94 -> 0 | K94: =J94 -> 0 | L94: =K94 -> 0 | M94: =L94 -> 0 | ... O94: =N94 -> 0
C95: ポイント交換原価
C96: スタンド委託費（社外） | D96: アプリ | E96: =R101 -> 0.319375 | F96: =E96 -> 0.319375 | G96: =F96 -> 0.319375 | H96: =G96 -> 0.319375 | I96: =H96 -> 0.319375 | J96: =I96 -> 0.319375 | K96: =J96 -> 0.319375 | L96: =K96 -> 0.319375 | M96: =L96 -> 0.319375 | ... O96: =N96 -> 0.319375 | Q96: ポイント付与数（年） | R96: =15*365 -> 5475
C97: スタンド委託費（社外） | D97: スタンド（宅急便） | E97: 0 | F97: =E97 -> 0 | G97: =F97 -> 0 | H97: =G97 -> 0 | I97: =H97 -> 0 | J97: =I97 -> 0 | K97: =J97 -> 0 | L97: =K97 -> 0 | M97: =L97 -> 0 | ... O97: =N97 -> 0 | Q97: ポイント獲得率 | R97: 0.4
C98: スタンド委託費（社外） | D98: スタンド（ＦＳ） | E98: 0 | F98: =E98 -> 0 | G98: =F98 -> 0 | H98: =G98 -> 0 | I98: =H98 -> 0 | J98: =I98 -> 0 | K98: =J98 -> 0 | L98: =K98 -> 0 | M98: =L98 -> 0 | ... O98: =N98 -> 0 | Q98: ポイント利用率 | R98: 0.7
C99: スタンド委託費（社外） | D99: スタンド（社外） | E99: 0 | F99: =E99 -> 0 | G99: =F99 -> 0 | H99: =G99 -> 0 | I99: =H99 -> 0 | J99: =I99 -> 0 | K99: =J99 -> 0 | L99: =K99 -> 0 | M99: =L99 -> 0 | ... O99: =N99 -> 0 | Q99: コスト（原価率100%前提） | R99: =R96*R97*R98 -> 1533
C100: スタンド委託費（社外） | D100: フロー（セミナー等） | E100: 0 | F100: =E100 -> 0 | G100: =F100 -> 0 | H100: =G100 -> 0 | I100: =H100 -> 0 | J100: =I100 -> 0 | K100: =J100 -> 0 | L100: =K100 -> 0 | M100: =L100 -> 0 | ... O100: =N100 -> 0 | Q100: 売上高（400円/月・人前提） | R100: =400*12 -> 4800
C101: スタンド委託費（社外） | D101: ＥＣストア | E101: 0 | F101: =E101 -> 0 | G101: =F101 -> 0 | H101: =G101 -> 0 | I101: =H101 -> 0 | J101: =I101 -> 0 | K101: =J101 -> 0 | L101: =K101 -> 0 | M101: =L101 -> 0 | ... O101: =N101 -> 0 | Q101: コスト高比 | R101: =R99/R100 -> 0.319375
...

Sheet 固定費
A1: 単位：千円
E3: 24年 | F3: 25年 | G3: 26年 | H3: 27年 | I3: 28年 | J3: 29年 | K3: 30年 | L3: 31年 | M3: 32年 | N3: 33年 | O3: 34年 | Q3: 単価
B4: 固定費
C5: 合計 | E5: =E15+E24+E33+E42+E51+E60+E69+E78+E87+E96+E105+E114+E123+E132+E141+E150+E159+E168+E177+E186+E195+E204+E213+E222 -> 29706.33 | F5: =F15+F24+F33+F42+F51+F60+F69+F78+F87+F96+F105+F114+F123+F132+F141+F150+F159+F168+F177+F186+F195+F204+F213+F222 -> 146632.61 | G5: =G15+G24+G33+G42+G51+G60+G69+G78+G87+G96+G105+G114+G123+G132+G141+G150+G159+G168+G177+G186+G195+G204+G213+G222 -> 201652.68 | H5: =H15+H24+H33+H42+H51+H60+H69+H78+H87+H96+H105+H114+H123+H132+H141+H150+H159+H168+H177+H186+H195+H204+H213+H222 -> 233796.94 | I5: =I15+I24+I33+I42+I51+I60+I69+I78+I87+I96+I105+I114+I123+I132+I141+I150+I159+I168+I177+I186+I195+I204+I213+I222 -> 262370.77 | J5: =J15+J24+J33+J42+J51+J60+J69+J78+J87+J96+J105+J114+J123+J132+J141+J150+J159+J168+J177+J186+J195+J204+J213+J222 -> 290061.15 | K5: =K15+K24+K33+K42+K51+K60+K69+K78+K87+K96+K105+K114+K123+K132+K141+K150+K159+K168+K177+K186+K195+K204+K213+K222 -> 316929.93 | L5: =L15+L24+L33+L42+L51+L60+L69+L78+L87+L96+L105+L114+L123+L132+L141+L150+L159+L168+L177+L186+L195+L204+L213+L222 -> 343034.62 | ... O5: =O15+O24+O33+O42+O51+O60+O69+O78+O87+O96+O105+O114+O123+O132+O141+O150+O159+O168+O177+O186+O195+O204+O213+O222 -> 417280.54
C6: 販売機器費 | D6: アプリ | E6: =E16+E25+E34+E43+E52+E61+E70+E79+E88+E97+E106+E115+E124+E133+E142+E151+E160+E169+E178+E187+E196+E205+E214+E223 -> 7538 | F6: =F16+F25+F34+F43+F52+F61+F70+F79+F88+F97+F106+F115+F124+F133+F142+F151+F160+F169+F178+F187+F196+F205+F214+F223 -> 67754.248 | G6: =G16+G25+G34+G43+G52+G61+G70+G79+G88+G97+G106+G115+G124+G133+G142+G151+G160+G169+G178+G187+G196+G205+G214+G223 -> 109417.67 | H6: =H16+H25+H34+H43+H52+H61+H70+H79+H88+H97+H106+H115+H124+H133+H142+H151+H160+H169+H178+H187+H196+H205+H214+H223 -> 123529.05 | I6: =I16+I25+I34+I43+I52+I61+I70+I79+I88+I97+I106+I115+I124+I133+I142+I151+I160+I169+I178+I187+I196+I205+I214+I223 -> 138958.79 | J6: =J16+J25+J34+J43+J52+J61+J70+J79+J88+J97+J106+J115+J124+J133+J142+J151+J160+J169+J178+J187+J196+J205+J214+J223 -> 152009.71 | K6: =K16+K25+K34+K43+K52+K61+K70+K79+K88+K97+K106+K115+K124+K133+K142+K151+K160+K169+K178+K187+K196+K205+K214+K223 -> 163666.35 | L6: =L16+L25+L34+L43+L52+L61+L70+L79+L88+L97+L106+L115+L124+L133+L142+L151+L160+L169+L178+L187+L196+L205+L214+L223 -> 174274 | ... O6: =O16+O25+O34+O43+O52+O61+O70+O79+O88+O97+O106+O115+O124+O133+O142+O151+O160+O169+O178+O187+O196+O205+O214+O223 -> 201241.72
C7: 販売機器費 | D7: スタンド（宅急便） | E7: =E17+E26+E35+E44+E53+E62+E71+E80+E89+E98+E107+E116+E125+E134+E143+E152+E161+E170+E179+E188+E197+E206+E215+E224 -> 7621 | F7: =F17+F26+F35+F44+F53+F62+F71+F80+F89+F98+F107+F116+F125+F134+F143+F152+F161+F170+F179+F188+F197+F206+F215+F224 -> 11911.511 | G7: =G17+G26+G35+G44+G53+G62+G71+G80+G89+G98+G107+G116+G125+G134+G143+G152+G161+G170+G179+G188+G197+G206+G215+G224 -> 7402.1227 | H7: =H17+H26+H35+H44+H53+H62+H71+H80+H89+H98+H107+H116+H125+H134+H143+H152+H161+H170+H179+H188+H197+H206+H215+H224 -> 3800.0637 | I7: =I17+I26+I35+I44+I53+I62+I71+I80+I89+I98+I107+I116+I125+I134+I143+I152+I161+I170+I179+I188+I197+I206+I215+I224 -> 2895.4218 | J7: =J17+J26+J35+J44+J53+J62+J71+J80+J89+J98+J107+J116+J125+J134+J143+J152+J161+J170+J179+J188+J197+J206+J215+J224 -> 2473.4422 | K7: =K17+K26+K35+K44+K53+K62+K71+K80+K89+K98+K107+K116+K125+K134+K143+K152+K161+K170+K179+K188+K197+K206+K215+K224 -> 2232.5199 | L7: =L17+L26+L35+L44+L53+L62+L71+L80+L89+L98+L107+L116+L125+L134+L143+L152+L161+L170+L179+L188+L197+L206+L215+L224 -> 2078.7944 | ... O7: =O17+O26+O35+O44+O53+O62+O71+O80+O89+O98+O107+O116+O125+O134+O143+O152+O161+O170+O179+O188+O197+O206+O215+O224 -> 1841.7801
C8: 販売機器費 | D8: スタンド（ＦＳ） | E8: =E18+E27+E36+E45+E54+E63+E72+E81+E90+E99+E108+E117+E126+E135+E144+E153+E162+E171+E180+E189+E198+E207+E216+E225 -> 703.5 | F8: =F18+F27+F36+F45+F54+F63+F72+F81+F90+F99+F108+F117+F126+F135+F144+F153+F162+F171+F180+F189+F198+F207+F216+F225 -> 22608.878 | G8: =G18+G27+G36+G45+G54+G63+G72+G81+G90+G99+G108+G117+G126+G135+G144+G153+G162+G171+G180+G189+G198+G207+G216+G225 -> 37678.948 | H8: =H18+H27+H36+H45+H54+H63+H72+H81+H90+H99+H108+H117+H126+H135+H144+H153+H162+H171+H180+H189+H198+H207+H216+H225 -> 50387.347 | I8: =I18+I27+I36+I45+I54+I63+I72+I81+I90+I99+I108+I117+I126+I135+I144+I153+I162+I171+I180+I189+I198+I207+I216+I225 -> 50460.984 | J8: =J18+J27+J36+J45+J54+J63+J72+J81+J90+J99+J108+J117+J126+J135+J144+J153+J162+J171+J180+J189+J198+J207+J216+J225 -> 50355.397 | K8: =K18+K27+K36+K45+K54+K63+K72+K81+K90+K99+K108+K117+K126+K135+K144+K153+K162+K171+K180+K189+K198+K207+K216+K225 -> 50190.864 | L8: =L18+L27+L36+L45+L54+L63+L72+L81+L90+L99+L108+L117+L126+L135+L144+L153+L162+L171+L180+L189+L198+L207+L216+L225 -> 50004.388 | ... O8: =O18+O27+O36+O45+O54+O63+O72+O81+O90+O99+O108+O117+O126+O135+O144+O153+O162+O171+O180+O189+O198+O207+O216+O225 -> 49427.132
C9: 販売機器費 | D9: スタンド（社外） | E9: =E19+E28+E37+E46+E55+E64+E73+E82+E91+E100+E109+E118+E127+E136+E145+E154+E163+E172+E181+E190+E199+E208+E217+E226 -> 398.8296 | F9: =F19+F28+F37+F46+F55+F64+F73+F82+F91+F100+F109+F118+F127+F136+F145+F154+F163+F172+F181+F190+F199+F208+F217+F226 -> 8867.3626 | G9: =G19+G28+G37+G46+G55+G64+G73+G82+G91+G100+G109+G118+G127+G136+G145+G154+G163+G172+G181+G190+G199+G208+G217+G226 -> 21330.95 | H9: =H19+H28+H37+H46+H55+H64+H73+H82+H91+H100+H109+H118+H127+H136+H145+H154+H163+H172+H181+H190+H199+H208+H217+H226 -> 35640.853 | I9: =I19+I28+I37+I46+I55+I64+I73+I82+I91+I100+I109+I118+I127+I136+I145+I154+I163+I172+I181+I190+I199+I208+I217+I226 -> 51945.365 | J9: =J19+J28+J37+J46+J55+J64+J73+J82+J91+J100+J109+J118+J127+J136+J145+J154+J163+J172+J181+J190+J199+J208+J217+J226 -> 68216.579 | K9: =K19+K28+K37+K46+K55+K64+K73+K82+K91+K100+K109+K118+K127+K136+K145+K154+K163+K172+K181+K190+K199+K208+K217+K226 -> 84477.683 | L9: =L19+L28+L37+L46+L55+L64+L73+L82+L91+L100+L109+L118+L127+L136+L145+L154+L163+L172+L181+L190+L199+L208+L217+L226 -> 100735.78 | ... O9: =O19+O28+O37+O46+O55+O64+O73+O82+O91+O100+O109+O118+O127+O136+O145+O154+O163+O172+O181+O190+O199+O208+O217+O226 -> 149513.54
C10: 販売機器費 | D10: フロー（セミナー等） | E10: =E20+E29+E38+E47+E56+E65+E74+E83+E92+E101+E110+E119+E128+E137+E146+E155+E164+E173+E182+E191+E200+E209+E218+E227 -> 12245 | F10: =F20+F29+F38+F47+F56+F65+F74+F83+F92+F101+F110+F119+F128+F137+F146+F155+F164+F173+F182+F191+F200+F209+F218+F227 -> 19940.563 | G10: =G20+G29+G38+G47+G56+G65+G74+G83+G92+G101+G110+G119+G128+G137+G146+G155+G164+G173+G182+G191+G200+G209+G218+G227 -> 16565.841 | H10: =H20+H29+H38+H47+H56+H65+H74+H83+H92+H101+H110+H119+H128+H137+H146+H155+H164+H173+H182+H191+H200+H209+H218+H227 -> 14686.648 | I10: =I20+I29+I38+I47+I56+I65+I74+I83+I92+I101+I110+I119+I128+I137+I146+I155+I164+I173+I182+I191+I200+I209+I218+I227 -> 13873.505 | J10: =J20+J29+J38+J47+J56+J65+J74+J83+J92+J101+J110+J119+J128+J137+J146+J155+J164+J173+J182+J191+J200+J209+J218+J227 -> 13488.066 | K10: =K20+K29+K38+K47+K56+K65+K74+K83+K92+K101+K110+K119+K128+K137+K146+K155+K164+K173+K182+K191+K200+K209+K218+K227 -> 13263.431 | L10: =L20+L29+L38+L47+L56+L65+L74+L83+L92+L101+L110+L119+L128+L137+L146+L155+L164+L173+L182+L191+L200+L209+L218+L227 -> 13116.521 | ... O10: =O20+O29+O38+O47+O56+O65+O74+O83+O92+O101+O110+O119+O128+O137+O146+O155+O164+O173+O182+O191+O200+O209+O218+O227 -> 12877.301
C11: 販売機器費 | D11: ＥＣストア | E11: =E21+E30+E39+E48+E57+E66+E75+E84+E93+E102+E111+E120+E129+E138+E147+E156+E165+E174+E183+E192+E201+E210+E219+E228 -> 1200 | F11: =F21+F30+F39+F48+F57+F66+F75+F84+F93+F102+F111+F120+F129+F138+F147+F156+F165+F174+F183+F192+F201+F210+F219+F228 -> 1359.8126 | G11: =G21+G30+G39+G48+G57+G66+G75+G84+G93+G102+G111+G120+G129+G138+G147+G156+G165+G174+G183+G192+G201+G210+G219+G228 -> 1289.7302 | H11: =H21+H30+H39+H48+H57+H66+H75+H84+H93+H102+H111+H120+H129+H138+H147+H156+H165+H174+H183+H192+H201+H210+H219+H228 -> 1250.7053 | I11: =I21+I30+I39+I48+I57+I66+I75+I84+I93+I102+I111+I120+I129+I138+I147+I156+I165+I174+I183+I192+I201+I210+I219+I228 -> 1233.8189 | J11: =J21+J30+J39+J48+J57+J66+J75+J84+J93+J102+J111+J120+J129+J138+J147+J156+J165+J174+J183+J192+J201+J210+J219+J228 -> 1225.8146 | K11: =K21+K30+K39+K48+K57+K66+K75+K84+K93+K102+K111+K120+K129+K138+K147+K156+K165+K174+K183+K192+K201+K210+K219+K228 -> 1221.1496 | L11: =L21+L30+L39+L48+L57+L66+L75+L84+L93+L102+L111+L120+L129+L138+L147+L156+L165+L174+L183+L192+L201+L210+L219+L228 -> 1218.0987 | ... O11: =O21+O30+O39+O48+O57+O66+O75+O84+O93+O102+O111+O120+O129+O138+O147+O156+O165+O174+O183+O192+O201+O210+O219+O228 -> 1213.1309
C12: 販売機器費 | D12: 卸売 | E12: =E22+E31+E40+E49+E58+E67+E76+E85+E94+E103+E112+E121+E130+E139+E148+E157+E166+E175+E184+E193+E202+E211+E220+E229 -> 0 | F12: =F22+F31+F40+F49+F58+F67+F76+F85+F94+F103+F112+F121+F130+F139+F148+F157+F166+F175+F184+F193+F202+F211+F220+F229 -> 8459.3204 | G12: =G22+G31+G40+G49+G58+G67+G76+G85+G94+G103+G112+G121+G130+G139+G148+G157+G166+G175+G184+G193+G202+G211+G220+G229 -> 4749.6696 | H12: =H22+H31+H40+H49+H58+H67+H76+H85+H94+H103+H112+H121+H130+H139+H148+H157+H166+H175+H184+H193+H202+H211+H220+H229 -> 2683.9724 | I12: =I22+I31+I40+I49+I58+I67+I76+I85+I94+I103+I112+I121+I130+I139+I148+I157+I166+I175+I184+I193+I202+I211+I220+I229 -> 1790.1288 | J12: =J22+J31+J40+J49+J58+J67+J76+J85+J94+J103+J112+J121+J130+J139+J148+J157+J166+J175+J184+J193+J202+J211+J220+J229 -> 1366.4358 | K12: =K22+K31+K40+K49+K58+K67+K76+K85+K94+K103+K112+K121+K130+K139+K148+K157+K166+K175+K184+K193+K202+K211+K220+K229 -> 1119.5063 | L12: =L22+L31+L40+L49+L58+L67+L76+L85+L94+L103+L112+L121+L130+L139+L148+L157+L166+L175+L184+L193+L202+L211+L220+L229 -> 958.01664 | ... O12: =O22+O31+O40+O49+O58+O67+O76+O85+O94+O103+O112+O121+O130+O139+O148+O157+O166+O175+O184+O193+O202+O211+O220+O229 -> 695.05429
C13: 販売機器費 | D13: 企業内手売 | E13: =E23+E32+E41+E50+E59+E68+E77+E86+E95+E104+E113+E122+E131+E140+E149+E158+E167+E176+E185+E194+E203+E212+E221+E230 -> 0 | F13: =F23+F32+F41+F50+F59+F68+F77+F86+F95+F104+F113+F122+F131+F140+F149+F158+F167+F176+F185+F194+F203+F212+F221+F230 -> 5730.909 | G13: =G23+G32+G41+G50+G59+G68+G77+G86+G95+G104+G113+G122+G131+G140+G149+G158+G167+G176+G185+G194+G203+G212+G221+G230 -> 3217.7436 | H13: =H23+H32+H41+H50+H59+H68+H77+H86+H95+H104+H113+H122+H131+H140+H149+H158+H167+H176+H185+H194+H203+H212+H221+H230 -> 1818.3023 | I13: =I23+I32+I41+I50+I59+I68+I77+I86+I95+I104+I113+I122+I131+I140+I149+I158+I167+I176+I185+I194+I203+I212+I221+I230 -> 1212.7529 | J13: =J23+J32+J41+J50+J59+J68+J77+J86+J95+J104+J113+J122+J131+J140+J149+J158+J167+J176+J185+J194+J203+J212+J221+J230 -> 925.71492 | K13: =K23+K32+K41+K50+K59+K68+K77+K86+K95+K104+K113+K122+K131+K140+K149+K158+K167+K176+K185+K194+K203+K212+K221+K230 -> 758.4284 | L13: =L23+L32+L41+L50+L59+L68+L77+L86+L95+L104+L113+L122+L131+L140+L149+L158+L167+L176+L185+L194+L203+L212+L221+L230 -> 649.0245 | ... O13: =O23+O32+O41+O50+O59+O68+O77+O86+O95+O104+O113+O122+O131+O140+O149+O158+O167+O176+O185+O194+O203+O212+O221+O230 -> 470.87623
B14: 固定費
C15: 販売機器費 | E15: =SUM(E16:E23) -> 4929 | F15: =SUM(F16:F23) -> 14973 | G15: =SUM(G16:G23) -> 24180 | H15: =SUM(H16:H23) -> 34410 | I15: =SUM(I16:I23) -> 34410 | J15: =SUM(J16:J23) -> 34410 | K15: =SUM(K16:K23) -> 34410 | L15: =SUM(L16:L23) -> 34410 | ... O15: =SUM(O16:O23) -> 34410
C16: 販売機器費 | D16: アプリ
C17: 販売機器費 | D17: スタンド（宅急便） | E17: =$Q$17*契約数!E35 -> 4278 | F17: =$Q$17*契約数!F35 -> 0 | G17: =$Q$17*契約数!G35 -> 0 | H17: =$Q$17*契約数!H35 -> 0 | I17: =$Q$17*契約数!I35 -> 0 | J17: =$Q$17*契約数!J35 -> 0 | K17: =$Q$17*契約数!K35 -> 0 | L17: =$Q$17*契約数!L35 -> 0 | ... O17: =$Q$17*契約数!O35 -> 0 | Q17: 93 | R17: 千円
C18: 販売機器費 | D18: スタンド（ＦＳ） | E18: =$Q$18*契約数!E36 -> 651 | F18: =$Q$18*契約数!F31 -> 14973 | G18: =$Q$18*契約数!G31 -> 24180 | H18: =$Q$18*契約数!H31 -> 34410 | I18: =$Q$18*契約数!I31 -> 34410 | J18: =$Q$18*契約数!J31 -> 34410 | K18: =$Q$18*契約数!K31 -> 34410 | L18: =$Q$18*契約数!L31 -> 34410 | M18: =$Q$18*契約数!M31 -> 34410 | ... O18: =$Q$18*契約数!O31 -> 34410 | Q18: 93 | R18: 千円
C19: 販売機器費 | D19: スタンド（社外）
C20: 販売機器費 | D20: フロー（セミナー等）
C21: 販売機器費 | D21: ＥＣストア
C22: 販売機器費 | D22: 卸売
C23: 販売機器費 | D23: 企業内手売
C24: ヤマト委託費（機器） | E24: =SUM(E25:E32) -> 212 | F24: =SUM(F25:F32) -> 644 | G24: =SUM(G25:G32) -> 1040 | H24: =SUM(H25:H32) -> 1480 | I24: =SUM(I25:I32) -> 1480 | J24: =SUM(J25:J32) -> 1480 | K24: =SUM(K25:K32) -> 1480 | L24: =SUM(L25:L32) -> 1480 | ... O24: =SUM(O25:O32) -> 1480
C25: ヤマト委託費（機器） | D25: アプリ
C26: ヤマト委託費（機器） | D26: スタンド（宅急便） | E26: =$Q$26*契約数!E35 -> 184 | F26: =$Q$26*契約数!F35 -> 0 | G26: =$Q$26*契約数!G35 -> 0 | H26: =$Q$26*契約数!H35 -> 0 | I26: =$Q$26*契約数!I35 -> 0 | J26: =$Q$26*契約数!J35 -> 0 | K26: =$Q$26*契約数!K35 -> 0 | L26: =$Q$26*契約数!L35 -> 0 | ... O26: =$Q$26*契約数!O35 -> 0 | Q26: 4 | R26: 千円
C27: ヤマト委託費（機器） | D27: スタンド（ＦＳ） | E27: =$Q$26*契約数!E36 -> 28 | F27: =$Q$26*契約数!F31 -> 644 | G27: =$Q$26*契約数!G31 -> 1040 | H27: =$Q$26*契約数!H31 -> 1480 | I27: =$Q$26*契約数!I31 -> 1480 | J27: =$Q$26*契約数!J31 -> 1480 | K27: =$Q$26*契約数!K31 -> 1480 | L27: =$Q$26*契約数!L31 -> 1480 | M27: =$Q$26*契約数!M31 -> 1480 | ... O27: =$Q$26*契約数!O31 -> 1480 | Q27: 4 | R27: 千円
C28: ヤマト委託費（機器） | D28: スタンド（社外）
C29: ヤマト委託費（機器） | D29: フロー（セミナー等）
C30: ヤマト委託費（機器） | D30: ＥＣストア
C31: ヤマト委託費（機器） | D31: 卸売
C32: ヤマト委託費（機器） | D32: 企業内手売
C33: POPスタンド・貯金箱購入費 | E33: =SUM(E34:E41) -> 79.5 | F33: =SUM(F34:F41) -> 241.5 | G33: =SUM(G34:G41) -> 390 | H33: =SUM(H34:H41) -> 555 | I33: =SUM(I34:I41) -> 555 | J33: =SUM(J34:J41) -> 555 | K33: =SUM(K34:K41) -> 555 | L33: =SUM(L34:L41) -> 555 | ... O33: =SUM(O34:O41) -> 555
C34: POPスタンド・貯金箱購入費 | D34: アプリ
C35: POPスタンド・貯金箱購入費 | D35: スタンド（宅急便） | E35: =$Q$35*契約数!E35 -> 69 | F35: =$Q$35*契約数!F35 -> 0 | G35: =$Q$35*契約数!G35 -> 0 | H35: =$Q$35*契約数!H35 -> 0 | I35: =$Q$35*契約数!I35 -> 0 | J35: =$Q$35*契約数!J35 -> 0 | K35: =$Q$35*契約数!K35 -> 0 | L35: =$Q$35*契約数!L35 -> 0 | ... O35: =$Q$35*契約数!O35 -> 0 | Q35: 1.5 | R35: 千円
C36: POPスタンド・貯金箱購入費 | D36: スタンド（ＦＳ） | E36: =$Q$36*契約数!E36 -> 10.5 | F36: =$Q$36*契約数!F31 -> 241.5 | G36: =$Q$36*契約数!G31 -> 390 | H36: =$Q$36*契約数!H31 -> 555 | I36: =$Q$36*契約数!I31 -> 555 | J36: =$Q$36*契約数!J31 -> 555 | K36: =$Q$36*契約数!K31 -> 555 | L36: =$Q$36*契約数!L31 -> 555 | M36: =$Q$36*契約数!M31 -> 555 | ... O36: =$Q$36*契約数!O31 -> 555 | Q36: 1.5 | R36: 千円
C37: POPスタンド・貯金箱購入費 | D37: スタンド（社外）
C38: POPスタンド・貯金箱購入費 | D38: フロー（セミナー等）
C39: POPスタンド・貯金箱購入費 | D39: ＥＣストア
C40: POPスタンド・貯金箱購入費 | D40: 卸売
C41: POPスタンド・貯金箱購入費 | D41: 企業内手売
C42: 冷蔵庫廃棄費 | E42: =SUM(E43:E50) -> 106 | F42: =SUM(F43:F50) -> 322 | G42: =SUM(G43:G50) -> 520 | H42: =SUM(H43:H50) -> 740 | I42: =SUM(I43:I50) -> 740 | J42: =SUM(J43:J50) -> 740 | K42: =SUM(K43:K50) -> 740 | L42: =SUM(L43:L50) -> 740 | ... O42: =SUM(O43:O50) -> 740
C43: 冷蔵庫廃棄費 | D43: アプリ
C44: 冷蔵庫廃棄費 | D44: スタンド（宅急便） | E44: =$Q$44*契約数!E35 -> 92 | F44: =$Q$44*契約数!F35 -> 0 | G44: =$Q$44*契約数!G35 -> 0 | H44: =$Q$44*契約数!H35 -> 0 | I44: =$Q$44*契約数!I35 -> 0 | J44: =$Q$44*契約数!J35 -> 0 | K44: =$Q$44*契約数!K35 -> 0 | L44: =$Q$44*契約数!L35 -> 0 | ... O44: =$Q$44*契約数!O35 -> 0 | Q44: 2 | R44: 千円
C45: 冷蔵庫廃棄費 | D45: スタンド（ＦＳ） | E45: =$Q$45*契約数!E36 -> 14 | F45: =$Q$45*契約数!F31 -> 322 | G45: =$Q$45*契約数!G31 -> 520 | H45: =$Q$45*契約数!H31 -> 740 | I45: =$Q$45*契約数!I31 -> 740 | J45: =$Q$45*契約数!J31 -> 740 | K45: =$Q$45*契約数!K31 -> 740 | L45: =$Q$45*契約数!L31 -> 740 | M45: =$Q$45*契約数!M31 -> 740 | ... O45: =$Q$45*契約数!O31 -> 740 | Q45: 2 | R45: 千円
C46: 冷蔵庫廃棄費 | D46: スタンド（社外）
C47: 冷蔵庫廃棄費 | D47: フロー（セミナー等）
C48: 冷蔵庫廃棄費 | D48: ＥＣストア
C49: 冷蔵庫廃棄費 | D49: 卸売
C50: 冷蔵庫廃棄費 | D50: 企業内手売
C51: 電子マネー手数料 | E51: =SUM(E52:E59) -> 1388 | F51: =SUM(F52:F59) -> 1388 | G51: =SUM(G52:G59) -> 1388 | H51: =SUM(H52:H59) -> 0 | I51: =SUM(I52:I59) -> 0 | J51: =SUM(J52:J59) -> 0 | K51: =SUM(K52:K59) -> 0 | L51: =SUM(L52:L59) -> 0 | ... O51: =SUM(O52:O59) -> 0
C52: 電子マネー手数料 | D52: アプリ
C53: 電子マネー手数料 | D53: スタンド（宅急便） | E53: 1388 | F53: 1388 | G53: 1388 | H53: 0 | I53: 0 | J53: 0 | K53: 0 | L53: 0 | M53: 0 | N53: 0 | O53: 0 | Q53: 27年にはすべてＦＳ移管完了
C54: 電子マネー手数料 | D54: スタンド（ＦＳ）
C55: 電子マネー手数料 | D55: スタンド（社外）
C56: 電子マネー手数料 | D56: フロー（セミナー等）
C57: 電子マネー手数料 | D57: ＥＣストア
C58: 電子マネー手数料 | D58: 卸売
C59: 電子マネー手数料 | D59: 企業内手売
C60: GMOシステム費 | E60: =SUM(E61:E68) -> 1610 | F60: =SUM(F61:F68) -> 1610 | G60: =SUM(G61:G68) -> 1610 | H60: =SUM(H61:H68) -> 1610 | I60: =SUM(I61:I68) -> 1610 | J60: =SUM(J61:J68) -> 1610 | K60: =SUM(K61:K68) -> 1610 | L60: =SUM(L61:L68) -> 1610 | ... O60: =SUM(O61:O68) -> 1610
C61: GMOシステム費 | D61: アプリ
C62: GMOシステム費 | D62: スタンド（宅急便） | E62: 1610 | F62: =E62 -> 1610 | G62: =F62 -> 1610 | H62: =G62 -> 1610 | I62: =H62 -> 1610 | J62: =I62 -> 1610 | K62: =J62 -> 1610 | L62: =K62 -> 1610 | M62: =L62 -> 1610 | ... O62: =N62 -> 1610
C63: GMOシステム費 | D63: スタンド（ＦＳ）
C64: GMOシステム費 | D64: スタンド（社外）
C65: GMOシステム費 | D65: フロー（セミナー等）
C66: GMOシステム費 | D66: ＥＣストア
C67: GMOシステム費 | D67: 卸売
C68: GMOシステム費 | D68: 企業内手売
C69: テモナシステム費 | E69: =SUM(E70:E77) -> 1200 | F69: =SUM(F70:F77) -> 1200 | G69: =SUM(G70:G77) -> 1200 | H69: =SUM(H70:H77) -> 1200 | I69: =SUM(I70:I77) -> 1200 | J69: =SUM(J70:J77) -> 1200 | K69: =SUM(K70:K77) -> 1200 | L69: =SUM(L70:L77) -> 1200 | ... O69: =SUM(O70:O77) -> 1200
C70: テモナシステム費 | D70: アプリ
C71: テモナシステム費 | D71: スタンド（宅急便）
C72: テモナシステム費 | D72: スタンド（ＦＳ）
C73: テモナシステム費 | D73: スタンド（社外）
C74: テモナシステム費 | D74: フロー（セミナー等）
C75: テモナシステム費 | D75: ＥＣストア | E75: 1200 | F75: =E75 -> 1200 | G75: =F75 -> 1200 | H75: =G75 -> 1200 | I75: =H75 -> 1200 | J75: =I75 -> 1200 | K75: =J75 -> 1200 | L75: =K75 -> 1200 | M75: =L75 -> 1200 | ... O75: =N75 -> 1200
C76: テモナシステム費 | D76: 卸売
C77: テモナシステム費 | D77: 企業内手売
C78: LearnOシステム費 | E78: =SUM(E79:E86) -> 6938 | F78: =SUM(F79:F86) -> 6938 | G78: =SUM(G79:G86) -> 6938 | H78: =SUM(H79:H86) -> 6938 | I78: =SUM(I79:I86) -> 6938 | J78: =SUM(J79:J86) -> 6938 | K78: =SUM(K79:K86) -> 6938 | L78: =SUM(L79:L86) -> 6938 | ... O78: =SUM(O79:O86) -> 6938
C79: LearnOシステム費 | D79: アプリ | E79: 6938 | F79: =E79 -> 6938 | G79: =F79 -> 6938 | H79: =G79 -> 6938 | I79: =H79 -> 6938 | J79: =I79 -> 6938 | K79: =J79 -> 6938 | L79: =K79 -> 6938 | M79: =L79 -> 6938 | ... O79: =N79 -> 6938
C80: LearnOシステム費 | D80: スタンド（宅急便）
C81: LearnOシステム費 | D81: スタンド（ＦＳ）
C82: LearnOシステム費 | D82: スタンド（社外）
C83: LearnOシステム費 | D83: フロー（セミナー等）
C84: LearnOシステム費 | D84: ＥＣストア
C85: LearnOシステム費 | D85: 卸売
C86: LearnOシステム費 | D86: 企業内手売
C87: ULIZAシステム費 | E87: =SUM(E88:E95) -> 600 | F87: =SUM(F88:F95) -> 600 | G87: =SUM(G88:G95) -> 600 | H87: =SUM(H88:H95) -> 600 | I87: =SUM(I88:I95) -> 600 | J87: =SUM(J88:J95) -> 600 | K87: =SUM(K88:K95) -> 600 | L87: =SUM(L88:L95) -> 600 | ... O87: =SUM(O88:O95) -> 600
C88: ULIZAシステム費 | D88: アプリ | E88: 600 | F88: =E88 -> 600 | G88: =F88 -> 600 | H88: =G88 -> 600 | I88: =H88 -> 600 | J88: =I88 -> 600 | K88: =J88 -> 600 | L88: =K88 -> 600 | M88: =L88 -> 600 | ... O88: =N88 -> 600
C89: ULIZAシステム費 | D89: スタンド（宅急便）
C90: ULIZAシステム費 | D90: スタンド（ＦＳ）
C91: ULIZAシステム費 | D91: スタンド（社外）
C92: ULIZAシステム費 | D92: フロー（セミナー等）
C93: ULIZAシステム費 | D93: ＥＣストア
C94: ULIZAシステム費 | D94: 卸売
C95: ULIZAシステム費 | D95: 企業内手売
C96: エデ委託費 | E96: =SUM(E97:E104) -> 3600 | F96: =SUM(F97:F104) -> 3600 | G96: =SUM(G97:G104) -> 3600 | H96: =SUM(H97:H104) -> 3600 | I96: =SUM(I97:I104) -> 3600 | J96: =SUM(J97:J104) -> 3600 | K96: =SUM(K97:K104) -> 3600 | L96: =SUM(L97:L104) -> 3600 | ... O96: =SUM(O97:O104) -> 3600
C97: エデ委託費 | D97: アプリ
C98: エデ委託費 | D98: スタンド（宅急便）
C99: エデ委託費 | D99: スタンド（ＦＳ）
C100: エデ委託費 | D100: スタンド（社外）
C101: エデ委託費 | D101: フロー（セミナー等） | E101: 3600 | F101: =E101 -> 3600 | G101: =F101 -> 3600 | H101: =G101 -> 3600 | I101: =H101 -> 3600 | J101: =I101 -> 3600 | K101: =J101 -> 3600 | L101: =K101 -> 3600 | M101: =L101 -> 3600 | ... O101: =N101 -> 3600
...

Sheet 営業・一般管理費
A1: 単位：千円
E3: 24年 | F3: 25年 | G3: 26年 | H3: 27年 | I3: 28年 | J3: 29年 | K3: 30年 | L3: 31年 | M3: 32年 | N3: 33年 | O3: 34年 | Q3: 単価
B4: 営業・一般管理費
C5: プログラム開発費（PoC含む） | E5: =E15+E24+E33+E42+E51+E60+E69+E78+E87 -> 71244.869 | F5: =F15+F24+F33+F42+F51+F60+F69+F78+F87 -> 107703.56 | G5: =G15+G24+G33+G42+G51+G60+G69+G78+G87 -> 170283.27 | H5: =H15+H24+H33+H42+H51+H60+H69+H78+H87 -> 192422.19 | I5: =I15+I24+I33+I42+I51+I60+I69+I78+I87 -> 215088.35 | J5: =J15+J24+J33+J42+J51+J60+J69+J78+J87 -> 235818.8 | K5: =K15+K24+K33+K42+K51+K60+K69+K78+K87 -> 254832.93 | L5: =L15+L24+L33+L42+L51+L60+L69+L78+L87 -> 272324.7 | ... O5: =O15+O24+O33+O42+O51+O60+O69+O78+O87 -> 317284.48
C6: プログラム開発費（PoC含む） | D6: アプリ | E6: =E16+E25+E34+E43+E52+E61+E70+E79+E88 -> 0 | F6: =F16+F25+F34+F43+F52+F61+F70+F79+F88 -> 11000 | G6: =G16+G25+G34+G43+G52+G61+G70+G79+G88 -> 41000 | H6: =H16+H25+H34+H43+H52+H61+H70+H79+H88 -> 46000 | I6: =I16+I25+I34+I43+I52+I61+I70+I79+I88 -> 51000 | J6: =J16+J25+J34+J43+J52+J61+J70+J79+J88 -> 56000 | K6: =K16+K25+K34+K43+K52+K61+K70+K79+K88 -> 61000 | L6: =L16+L25+L34+L43+L52+L61+L70+L79+L88 -> 66000 | ... O6: =O16+O25+O34+O43+O52+O61+O70+O79+O88 -> 81000
C7: プログラム開発費（PoC含む） | D7: スタンド（宅急便） | E7: =E17+E26+E35+E44+E53+E62+E71+E80+E89 -> 0 | F7: =F17+F26+F35+F44+F53+F62+F71+F80+F89 -> 0 | G7: =G17+G26+G35+G44+G53+G62+G71+G80+G89 -> 0 | H7: =H17+H26+H35+H44+H53+H62+H71+H80+H89 -> 0 | I7: =I17+I26+I35+I44+I53+I62+I71+I80+I89 -> 0 | J7: =J17+J26+J35+J44+J53+J62+J71+J80+J89 -> 0 | K7: =K17+K26+K35+K44+K53+K62+K71+K80+K89 -> 0 | L7: =L17+L26+L35+L44+L53+L62+L71+L80+L89 -> 0 | ... O7: =O17+O26+O35+O44+O53+O62+O71+O80+O89 -> 0
C8: プログラム開発費（PoC含む） | D8: スタンド（ＦＳ） | E8: =E18+E27+E36+E45+E54+E63+E72+E81+E90 -> 210.86856 | F8: =F18+F27+F36+F45+F54+F63+F72+F81+F90 -> 4603.5619 | G8: =G18+G27+G36+G45+G54+G63+G72+G81+G90 -> 14252.353 | H8: =H18+H27+H36+H45+H54+H63+H72+H81+H90 -> 27429.391 | I8: =I18+I27+I36+I45+I54+I63+I72+I81+I90 -> 41411.011 | J8: =J18+J27+J36+J45+J54+J63+J72+J81+J90 -> 53714.838 | K8: =K18+K27+K36+K45+K54+K63+K72+K81+K90 -> 64542.205 | L8: =L18+L27+L36+L45+L54+L63+L72+L81+L90 -> 74070.287 | ... O8: =O18+O27+O36+O45+O54+O63+O72+O81+O90 -> 96326.67
C9: プログラム開発費（PoC含む） | D9: スタンド（社外） | E9: =E19+E28+E37+E46+E55+E64+E73+E82+E91 -> 0 | F9: =F19+F28+F37+F46+F55+F64+F73+F82+F91 -> 0 | G9: =G19+G28+G37+G46+G55+G64+G73+G82+G91 -> 0 | H9: =H19+H28+H37+H46+H55+H64+H73+H82+H91 -> 0 | I9: =I19+I28+I37+I46+I55+I64+I73+I82+I91 -> 0 | J9: =J19+J28+J37+J46+J55+J64+J73+J82+J91 -> 0 | K9: =K19+K28+K37+K46+K55+K64+K73+K82+K91 -> 0 | L9: =L19+L28+L37+L46+L55+L64+L73+L82+L91 -> 0 | ... O9: =O19+O28+O37+O46+O55+O64+O73+O82+O91 -> 0
C10: プログラム開発費（PoC含む） | D10: フロー（セミナー等） | E10: =E20+E29+E38+E47+E56+E65+E74+E83+E92 -> 0 | F10: =F20+F29+F38+F47+F56+F65+F74+F83+F92 -> 10370 | G10: =G20+G29+G38+G47+G56+G65+G74+G83+G92 -> 10600 | H10: =H20+H29+H38+H47+H56+H65+H74+H83+H92 -> 10600 | I10: =I20+I29+I38+I47+I56+I65+I74+I83+I92 -> 10600 | J10: =J20+J29+J38+J47+J56+J65+J74+J83+J92 -> 10600 | K10: =K20+K29+K38+K47+K56+K65+K74+K83+K92 -> 10600 | L10: =L20+L29+L38+L47+L56+L65+L74+L83+L92 -> 10600 | ... O10: =O20+O29+O38+O47+O56+O65+O74+O83+O92 -> 10600 | Q10: 年間 | R10: 10000 | S10: 千円
C11: プログラム開発費（PoC含む） | D11: ＥＣストア | E11: =E21+E30+E39+E48+E57+E66+E75+E84+E93 -> 0 | F11: =F21+F30+F39+F48+F57+F66+F75+F84+F93 -> 0 | G11: =G21+G30+G39+G48+G57+G66+G75+G84+G93 -> 0 | H11: =H21+H30+H39+H48+H57+H66+H75+H84+H93 -> 0 | I11: =I21+I30+I39+I48+I57+I66+I75+I84+I93 -> 0 | J11: =J21+J30+J39+J48+J57+J66+J75+J84+J93 -> 0 | K11: =K21+K30+K39+K48+K57+K66+K75+K84+K93 -> 0 | L11: =L21+L30+L39+L48+L57+L66+L75+L84+L93 -> 0 | ... O11: =O21+O30+O39+O48+O57+O66+O75+O84+O93 -> 0
C12: プログラム開発費（PoC含む） | D12: 卸売 | E12: =E22+E31+E40+E49+E58+E67+E76+E85+E94 -> 0 | F12: =F22+F31+F40+F49+F58+F67+F76+F85+F94 -> 0 | G12: =G22+G31+G40+G49+G58+G67+G76+G85+G94 -> 0 | H12: =H22+H31+H40+H49+H58+H67+H76+H85+H94 -> 0 | I12: =I22+I31+I40+I49+I58+I67+I76+I85+I94 -> 0 | J12: =J22+J31+J40+J49+J58+J67+J76+J85+J94 -> 0 | K12: =K22+K31+K40+K49+K58+K67+K76+K85+K94 -> 0 | L12: =L22+L31+L40+L49+L58+L67+L76+L85+L94 -> 0 | ... O12: =O22+O31+O40+O49+O58+O67+O76+O85+O94 -> 0
C13: プログラム開発費（PoC含む） | D13: 企業内手売 | E13: =E23+E32+E41+E50+E59+E68+E77+E86+E95 -> 0 | F13: =F23+F32+F41+F50+F59+F68+F77+F86+F95 -> 0 | G13: =G23+G32+G41+G50+G59+G68+G77+G86+G95 -> 0 | H13: =H23+H32+H41+H50+H59+H68+H77+H86+H95 -> 0 | I13: =I23+I32+I41+I50+I59+I68+I77+I86+I95 -> 0 | J13: =J23+J32+J41+J50+J59+J68+J77+J86+J95 -> 0 | K13: =K23+K32+K41+K50+K59+K68+K77+K86+K95 -> 0 | L13: =L23+L32+L41+L50+L59+L68+L77+L86+L95 -> 0 | ... O13: =O23+O32+O41+O50+O59+O68+O77+O86+O95 -> 0
B14: 営業・一般管理費
C15: プログラム開発費（PoC含む） | E15: =SUM(E16:E23) -> 0 | F15: =SUM(F16:F23) -> 10000 | G15: =SUM(G16:G23) -> 10000 | H15: =SUM(H16:H23) -> 10000 | I15: =SUM(I16:I23) -> 10000 | J15: =SUM(J16:J23) -> 10000 | K15: =SUM(K16:K23) -> 10000 | L15: =SUM(L16:L23) -> 10000 | ... O15: =SUM(O16:O23) -> 10000
C16: プログラム開発費（PoC含む） | D16: アプリ
C17: プログラム開発費（PoC含む） | D17: スタンド（宅急便）
C18: プログラム開発費（PoC含む） | D18: スタンド（ＦＳ）
C19: プログラム開発費（PoC含む） | D19: スタンド（社外）
C20: プログラム開発費（PoC含む） | D20: フロー（セミナー等） | F20: =$R$20 -> 10000 | G20: =$R$20 -> 10000 | H20: =$R$20 -> 10000 | I20: =$R$20 -> 10000 | J20: =$R$20 -> 10000 | K20: =$R$20 -> 10000 | L20: =$R$20 -> 10000 | M20: =$R$20 -> 10000 | ... O20: =$R$20 -> 10000 | Q20: 年間 | R20: 10000 | S20: 千円
C21: プログラム開発費（PoC含む） | D21: ＥＣストア
C22: プログラム開発費（PoC含む） | D22: 卸売
C23: プログラム開発費（PoC含む） | D23: 企業内手売
C24: プログラム外部サービサー連携 | E24: =SUM(E25:E32) -> 0 | F24: =SUM(F26:F32) -> 370 | G24: =SUM(G26:G32) -> 600 | H24: =SUM(H26:H32) -> 600 | I24: =SUM(I26:I32) -> 600 | J24: =SUM(J26:J32) -> 600 | K24: =SUM(K26:K32) -> 600 | L24: =SUM(L26:L32) -> 600 | M24: =SUM(M26:M32) -> 600 | ... O24: =SUM(O26:O32) -> 600
C25: プログラム外部サービサー連携 | D25: アプリ
C26: プログラム外部サービサー連携 | D26: スタンド（宅急便）
C27: プログラム外部サービサー連携 | D27: スタンド（ＦＳ）
C28: プログラム外部サービサー連携 | D28: スタンド（社外）
C29: プログラム外部サービサー連携 | D29: フロー（セミナー等） | F29: 370 | G29: 600 | H29: =G29 -> 600 | I29: =H29 -> 600 | J29: =I29 -> 600 | K29: =J29 -> 600 | L29: =K29 -> 600 | M29: =L29 -> 600 | N29: =M29 -> 600 | O29: =N29 -> 600
C30: プログラム外部サービサー連携 | D30: ＥＣストア
C31: プログラム外部サービサー連携 | D31: 卸売
C32: プログラム外部サービサー連携 | D32: 企業内手売
C33: LIGアプリ開発費 | E33: =SUM(E34:E41) -> 0 | F33: =SUM(F34:F41) -> 11000 | G33: =SUM(G34:G41) -> 21000 | H33: =SUM(H34:H41) -> 26000 | I33: =SUM(I34:I41) -> 31000 | J33: =SUM(J34:J41) -> 36000 | K33: =SUM(K34:K41) -> 41000 | L33: =SUM(L34:L41) -> 46000 | ... O33: =SUM(O34:O41) -> 61000
C34: LIGアプリ開発費 | D34: アプリ | F34: =$R$34/$R$35 -> 11000 | G34: =$R$34/$R$35+$R$36/$R$35 -> 21000 | H34: =$R$34/$R$35+$R$36/$R$35+$R$37/$R$35 -> 26000 | I34: =$R$34/$R$35+$R$36/$R$35+$R$37*2/$R$35 -> 31000 | J34: =$R$34/$R$35+$R$36/$R$35+$R$37*3/$R$35 -> 36000 | K34: =$R$34/$R$35+$R$36/$R$35+$R$37*4/$R$35 -> 41000 | L34: =$R$34/$R$35+$R$36/$R$35+$R$37*5/$R$35 -> 46000 | M34: =$R$34/$R$35+$R$36/$R$35+$R$37*6/$R$35 -> 51000 | N34: =$R$34/$R$35+$R$36/$R$35+$R$37*7/$R$35 -> 56000 | O34: =$R$34/$R$35+$R$36/$R$35+$R$37*8/$R$35 -> 61000 | Q34: 初期 | R34: 110000 | S34: 千円
C35: LIGアプリ開発費 | D35: スタンド（宅急便） | Q35: 償却 | R35: 10 | S35: 年
C36: LIGアプリ開発費 | D36: スタンド（ＦＳ） | Q36: 2年目 | R36: 100000 | S36: 千円
C37: LIGアプリ開発費 | D37: スタンド（社外） | Q37: 3年目以降 | R37: 50000 | S37: 千円
C38: LIGアプリ開発費 | D38: フロー（セミナー等）
C39: LIGアプリ開発費 | D39: ＥＣストア
C40: LIGアプリ開発費 | D40: 卸売
C41: LIGアプリ開発費 | D41: 企業内手売
C42: OneQR自販機連携追加機能開発費 | E42: =SUM(E43:E50) -> 0 | F42: =SUM(F43:F50) -> 0 | G42: =SUM(G43:G50) -> 20000 | H42: =SUM(H43:H50) -> 20000 | I42: =SUM(I43:I50) -> 20000 | J42: =SUM(J43:J50) -> 20000 | K42: =SUM(K43:K50) -> 20000 | L42: =SUM(L43:L50) -> 20000 | ... O42: =SUM(O43:O50) -> 20000
C43: OneQR自販機連携追加機能開発費 | D43: アプリ | G43: =R43/R44 -> 20000 | H43: =G43 -> 20000 | I43: =H43 -> 20000 | J43: =I43 -> 20000 | K43: =J43 -> 20000 | L43: =K43 -> 20000 | M43: =L43 -> 20000 | N43: =M43 -> 20000 | O43: =N43 -> 20000 | Q43: イニシャル | R43: 200000 | S43: 千円
C44: OneQR自販機連携追加機能開発費 | D44: スタンド（宅急便） | Q44: 償却 | R44: 10 | S44: 年
C45: OneQR自販機連携追加機能開発費 | D45: スタンド（ＦＳ）
C46: OneQR自販機連携追加機能開発費 | D46: スタンド（社外）
C47: OneQR自販機連携追加機能開発費 | D47: フロー（セミナー等）
C48: OneQR自販機連携追加機能開発費 | D48: ＥＣストア
C49: OneQR自販機連携追加機能開発費 | D49: 卸売
C50: OneQR自販機連携追加機能開発費 | D50: 企業内手売
C51: 交通旅費 | E51: 416 | F51: 416 | G51: =F51*2 -> 832 | H51: =G51 -> 832 | I51: =H51 -> 832 | J51: =I51 -> 832 | K51: =J51 -> 832 | L51: =K51 -> 832 | M51: =L51 -> 832 | N51: =M51 -> 832 | O51: =N51 -> 832
C52: 交通旅費 | D52: アプリ
C53: 交通旅費 | D53: スタンド（宅急便）
C54: 交通旅費 | D54: スタンド（ＦＳ）
C55: 交通旅費 | D55: スタンド（社外）
C56: 交通旅費 | D56: フロー（セミナー等）
C57: 交通旅費 | D57: ＥＣストア
C58: 交通旅費 | D58: 卸売
C59: 交通旅費 | D59: 企業内手売
C60: 交際費 | E60: 270 | F60: 270 | G60: =F60*2 -> 540 | H60: =G60 -> 540 | I60: =H60 -> 540 | J60: =I60 -> 540 | K60: =J60 -> 540 | L60: =K60 -> 540 | M60: =L60 -> 540 | N60: =M60 -> 540 | O60: =N60 -> 540
C61: 交際費 | D61: アプリ
C62: 交際費 | D62: スタンド（宅急便）
C63: 交際費 | D63: スタンド（ＦＳ）
C64: 交際費 | D64: スタンド（社外）
C65: 交際費 | D65: フロー（セミナー等）
C66: 交際費 | D66: ＥＣストア
C67: 交際費 | D67: 卸売
C68: 交際費 | D68: 企業内手売
C69: 人件費（専任） | E69: =10000*7 -> 70000 | F69: =10000*R69 -> 80000 | G69: =10000*$R$70 -> 100000 | H69: =10000*$R$70 -> 100000 | I69: =10000*$R$70 -> 100000 | J69: =10000*$R$70 -> 100000 | K69: =10000*$R$70 -> 100000 | L69: =10000*$R$70 -> 100000 | M69: =10000*$R$70 -> 100000 | N69: =10000*$R$70 -> 100000 | O69: =10000*$R$70 -> 100000 | Q69: 25年 | R69: 8 | S69: 名
C70: 人件費（専任） | D70: アプリ | Q70: 26年以降 | R70: 10 | S70: 名
C71: 人件費（専任） | D71: スタンド（宅急便）
C72: 人件費（専任） | D72: スタンド（ＦＳ）
C73: 人件費（専任） | D73: スタンド（社外）
C74: 人件費（専任） | D74: フロー（セミナー等）
C75: 人件費（専任） | D75: ＥＣストア
C76: 人件費（専任） | D76: 卸売
C77: 人件費（専任） | D77: 企業内手売
C78: 人件費（法人営業） | E78: =F78/3 -> 348 | F78: =(契約数!F18+契約数!F39)*$R$78*$R$79*$R$80 -> 1044 | G78: =(契約数!G18+契約数!G39)*$R$78*$R$79*$R$80 -> 3058.92 | H78: =(契約数!H18+契約数!H39)*$R$78*$R$79*$R$80 -> 7020.7956 | I78: =(契約数!I18+契約数!I39)*$R$78*$R$79*$R$80 -> 10705.34 | J78: =(契約数!J18+契約数!J39)*$R$78*$R$79*$R$80 -> 14131.966 | K78: =(契約数!K18+契約数!K39)*$R$78*$R$79*$R$80 -> 17318.728 | L78: =(契約数!L18+契約数!L39)*$R$78*$R$79*$R$80 -> 20282.417 | M78: =(契約数!M18+契約数!M39)*$R$78*$R$79*$R$80 -> 23038.648 | ... O78: =(契約数!O18+契約数!O39)*$R$78*$R$79*$R$80 -> 27985.807 | Q78: 1企業あたりの商談数 | R78: 12 | S78: 回/年
C79: 人件費（営業） | D79: アプリ | Q79: 1商談あたりの時間 | R79: 1.5 | S79: H
C80: 人件費（営業） | D80: スタンド（宅急便） | Q80: １Hあたりの時給 | R80: 5.8 | S80: 千円
C81: 人件費（営業） | D81: スタンド（ＦＳ）
C82: 人件費（営業） | D82: スタンド（社外）
C83: 人件費（営業） | D83: フロー（セミナー等）
C84: 人件費（営業） | D84: ＥＣストア
C85: 人件費（営業） | D85: 卸売
C86: 人件費（営業） | D86: 企業内手売
C87: ＯＰ費（販社） | E87: =SUM(E88:E95) -> 210.86856 | F87: =SUM(F88:F95) -> 4603.5619 | G87: =SUM(G88:G95) -> 14252.353 | H87: =SUM(H88:H95) -> 27429.391 | I87: =SUM(I88:I95) -> 41411.011 | J87: =SUM(J88:J95) -> 53714.838 | K87: =SUM(K88:K95) -> 64542.205 | L87: =SUM(L88:L95) -> 74070.287 | ... O87: =SUM(O88:O95) -> 96326.67
C88: ＯＰ費（販社） | D88: アプリ
C89: ＯＰ費（販社） | D89: スタンド（宅急便）
C90: ＯＰ費（販社） | D90: スタンド（ＦＳ） | E90: =売上高!E7*$R$90 -> 210.86856 | F90: =売上高!F7*$R$90 -> 4603.5619 | G90: =売上高!G7*$R$90 -> 14252.353 | H90: =売上高!H7*$R$90 -> 27429.391 | I90: =売上高!I7*$R$90 -> 41411.011 | J90: =売上高!J7*$R$90 -> 53714.838 | K90: =売上高!K7*$R$90 -> 64542.205 | L90: =売上高!L7*$R$90 -> 74070.287 | ... O90: =売上高!O7*$R$90 -> 96326.67 | Q90: 高比 | R90: 0.14 | S90: 平均（ルートと宅急便50%）
C91: ＯＰ費（販社） | D91: スタンド（社外）
C92: ＯＰ費（販社） | D92: フロー（セミナー等）
C93: ＯＰ費（販社） | D93: ＥＣストア
C94: ＯＰ費（販社） | D94: 卸売
C95: ＯＰ費（販社） | D95: 企業内手売

Sheet 月次PDCA＞＞

Sheet サマリ
A1: 7 | C1: ←対象月へ変更
A3: ■売上高
A4: チャネル | C4: =A1 -> 7 | K4: =A1 -> 7
C5: 実績 | D5: 予算 | E5: 前年 | F5: 予算比 | G5: 予算差 | H5: 前年比 | I5: 前年差 | K5: 実績 | L5: 予算 | M5: 前年 | N5: 予算比 | O5: 予算差 | P5: 前年比 | Q5: 前年差
A6: 新規（WEB） | C6: =SUMIFS('25年PDCA'!$AZ$5:$AZ$34,'25年PDCA'!$AK$5:$AK$34,サマリ!$A6,'25年PDCA'!$AL$5:$AL$34,"計") -> 1365.946 | D6: =SUMIFS('25年PDCA'!$BR$5:$BR$34,'25年PDCA'!$BC$5:$BC$34,サマリ!$A6,'25年PDCA'!$BD$5:$BD$34,"計") -> 5844.2355 | E6: =SUMIFS('25年PDCA'!$CM$5:$CM$34,'25年PDCA'!$BX$5:$BX$34,サマリ!$A6,'25年PDCA'!$BY$5:$BY$34,"計") -> 13923.231 | F6: =IFERROR(C6/D6,0) -> 0.23372535 | G6: =C6-D6 -> -4478.2895 | H6: =IFERROR(C6/E6,0) -> 0.098105534 | I6: =C6-E6 -> -12557.285 | K6: =SUMIFS('25年PDCA'!$BA$5:$BA$34,'25年PDCA'!$AK$5:$AK$34,サマリ!$A6,'25年PDCA'!$AL$5:$AL$34,"計") -> 187.055 | L6: =SUMIFS('25年PDCA'!$BS$5:$BS$34,'25年PDCA'!$BC$5:$BC$34,サマリ!$A6,'25年PDCA'!$BD$5:$BD$34,"計") -> 4051.1355 | M6: =SUMIFS('25年PDCA'!$CN$5:$CN$34,'25年PDCA'!$BX$5:$BX$34,サマリ!$A6,'25年PDCA'!$BY$5:$BY$34,"計") -> 2174.0536 | N6: =IFERROR(K6/L6,0) -> 0.046173474 | O6: =K6-L6 -> -3864.0805 | P6: =IFERROR(K6/M6,0) -> 0.086039736 | Q6: =K6-M6 -> -1986.9986
A7: 新規（法人） | C7: =SUMIFS('25年PDCA'!$AZ$5:$AZ$34,'25年PDCA'!$AK$5:$AK$34,サマリ!$A7,'25年PDCA'!$AL$5:$AL$34,"計") -> 2005.4356 | D7: =SUMIFS('25年PDCA'!$BR$5:$BR$34,'25年PDCA'!$BC$5:$BC$34,サマリ!$A7,'25年PDCA'!$BD$5:$BD$34,"計") -> 1432.1085 | E7: =SUMIFS('25年PDCA'!$CM$5:$CM$34,'25年PDCA'!$BX$5:$BX$34,サマリ!$A7,'25年PDCA'!$BY$5:$BY$34,"計") -> 3210.3891 | F7: =IFERROR(C7/D7,0) -> 1.4003378 | G7: =C7-D7 -> 573.32714 | H7: =IFERROR(C7/E7,0) -> 0.62467059 | I7: =C7-E7 -> -1204.9535 | K7: =SUMIFS('25年PDCA'!$BA$5:$BA$34,'25年PDCA'!$AK$5:$AK$34,サマリ!$A7,'25年PDCA'!$AL$5:$AL$34,"計") -> 323.727 | L7: =SUMIFS('25年PDCA'!$BS$5:$BS$34,'25年PDCA'!$BC$5:$BC$34,サマリ!$A7,'25年PDCA'!$BD$5:$BD$34,"計") -> 750.7305 | M7: =SUMIFS('25年PDCA'!$CN$5:$CN$34,'25年PDCA'!$BX$5:$BX$34,サマリ!$A7,'25年PDCA'!$BY$5:$BY$34,"計") -> 829.50182 | N7: =IFERROR(K7/L7,0) -> 0.431216 | O7: =K7-L7 -> -427.0035 | P7: =IFERROR(K7/M7,0) -> 0.39026678 | Q7: =K7-M7 -> -505.77482
A8: 新規（代理店） | C8: =SUMIFS('25年PDCA'!$AZ$5:$AZ$34,'25年PDCA'!$AK$5:$AK$34,サマリ!$A8,'25年PDCA'!$AL$5:$AL$34,"計") -> 35.345 | D8: =SUMIFS('25年PDCA'!$BR$5:$BR$34,'25年PDCA'!$BC$5:$BC$34,サマリ!$A8,'25年PDCA'!$BD$5:$BD$34,"計") -> 180 | E8: =SUMIFS('25年PDCA'!$CM$5:$CM$34,'25年PDCA'!$BX$5:$BX$34,サマリ!$A8,'25年PDCA'!$BY$5:$BY$34,"計") -> 0 | F8: =IFERROR(C8/D8,0) -> 0.19636111 | G8: =C8-D8 -> -144.655 | H8: =IFERROR(C8/E8,0) -> 0 | I8: =C8-E8 -> 35.345 | K8: =SUMIFS('25年PDCA'!$BA$5:$BA$34,'25年PDCA'!$AK$5:$AK$34,サマリ!$A8,'25年PDCA'!$AL$5:$AL$34,"計") -> 0 | L8: =SUMIFS('25年PDCA'!$BS$5:$BS$34,'25年PDCA'!$BC$5:$BC$34,サマリ!$A8,'25年PDCA'!$BD$5:$BD$34,"計") -> 180 | M8: =SUMIFS('25年PDCA'!$CN$5:$CN$34,'25年PDCA'!$BX$5:$BX$34,サマリ!$A8,'25年PDCA'!$BY$5:$BY$34,"計") -> 0 | N8: =IFERROR(K8/L8,0) -> 0 | O8: =K8-L8 -> -180 | P8: =IFERROR(K8/M8,0) -> 0 | Q8: =K8-M8 -> 0
A9: 新規 ストック計 | C9: =SUM(C6:C8) -> 3406.7266 | D9: =SUM(D6:D8) -> 7456.344 | E9: =SUM(E6:E8) -> 17133.62 | F9: =IFERROR(C9/D9,0) -> 0.45688968 | G9: =C9-D9 -> -4049.6174 | H9: =IFERROR(C9/E9,0) -> 0.19883286 | I9: =C9-E9 -> -13726.893 | K9: =SUM(K6:K8) -> 510.782 | L9: =SUM(L6:L8) -> 4981.866 | M9: =SUM(M6:M8) -> 3003.5555 | N9: =IFERROR(K9/L9,0) -> 0.10252825 | O9: =K9-L9 -> -4471.084 | P9: =IFERROR(K9/M9,0) -> 0.17005912 | Q9: =K9-M9 -> -2492.7735
A10: クロスセル | C10: =SUMIFS('25年PDCA'!$AZ$5:$AZ$34,'25年PDCA'!$AK$5:$AK$34,サマリ!$A10,'25年PDCA'!$AL$5:$AL$34,"計") -> 0 | D10: =SUMIFS('25年PDCA'!$BR$5:$BR$34,'25年PDCA'!$BC$5:$BC$34,サマリ!$A10,'25年PDCA'!$BD$5:$BD$34,"計") -> 800 | E10: =SUMIFS('25年PDCA'!$CM$5:$CM$34,'25年PDCA'!$BX$5:$BX$34,サマリ!$A10,'25年PDCA'!$BY$5:$BY$34,"計") -> 0 | F10: =IFERROR(C10/D10,0) -> 0 | G10: =C10-D10 -> -800 | H10: =IFERROR(C10/E10,0) -> 0 | I10: =C10-E10 -> 0 | K10: =SUMIFS('25年PDCA'!$BA$5:$BA$34,'25年PDCA'!$AK$5:$AK$34,サマリ!$A10,'25年PDCA'!$AL$5:$AL$34,"計") -> 0 | L10: =SUMIFS('25年PDCA'!$BS$5:$BS$34,'25年PDCA'!$BC$5:$BC$34,サマリ!$A10,'25年PDCA'!$BD$5:$BD$34,"計") -> 800 | M10: =SUMIFS('25年PDCA'!$CN$5:$CN$34,'25年PDCA'!$BX$5:$BX$34,サマリ!$A10,'25年PDCA'!$BY$5:$BY$34,"計") -> 0 | N10: =IFERROR(K10/L10,0) -> 0 | O10: =K10-L10 -> -800 | P10: =IFERROR(K10/M10,0) -> 0 | Q10: =K10-M10 -> 0
A11: 既存（25年以前） | C11: =SUMIFS('25年PDCA'!$AZ$5:$AZ$34,'25年PDCA'!$AK$5:$AK$34,サマリ!$A11,'25年PDCA'!$AL$5:$AL$34,"計") -> 55185.001 | D11: =SUMIFS('25年PDCA'!$BR$5:$BR$34,'25年PDCA'!$BC$5:$BC$34,サマリ!$A11,'25年PDCA'!$BD$5:$BD$34,"計") -> 53630.794 | E11: =SUMIFS('25年PDCA'!$CM$5:$CM$34,'25年PDCA'!$BX$5:$BX$34,サマリ!$A11,'25年PDCA'!$BY$5:$BY$34,"計") -> 31804.333 | F11: =IFERROR(C11/D11,0) -> 1.0289798 | G11: =C11-D11 -> 1554.2073 | H11: =IFERROR(C11/E11,0) -> 1.735141 | I11: =C11-E11 -> 23380.669 | K11: =SUMIFS('25年PDCA'!$BA$5:$BA$34,'25年PDCA'!$AK$5:$AK$34,サマリ!$A11,'25年PDCA'!$AL$5:$AL$34,"計") -> 7199.17 | L11: =SUMIFS('25年PDCA'!$BS$5:$BS$34,'25年PDCA'!$BC$5:$BC$34,サマリ!$A11,'25年PDCA'!$BD$5:$BD$34,"計") -> 7746.7506 | M11: =SUMIFS('25年PDCA'!$CN$5:$CN$34,'25年PDCA'!$BX$5:$BX$34,サマリ!$A11,'25年PDCA'!$BY$5:$BY$34,"計") -> 4643.0682 | N11: =IFERROR(K11/L11,0) -> 0.9293148 | O11: =K11-L11 -> -547.58064 | P11: =IFERROR(K11/M11,0) -> 1.55052 | Q11: =K11-M11 -> 2556.1018
A12: 既存 ストック計 | C12: =SUM(C10:C11) -> 55185.001 | D12: =SUM(D10:D11) -> 54430.794 | E12: =SUM(E10:E11) -> 31804.333 | F12: =IFERROR(C12/D12,0) -> 1.0138563 | G12: =C12-D12 -> 754.20727 | H12: =IFERROR(C12/E12,0) -> 1.735141 | I12: =C12-E12 -> 23380.669 | K12: =SUM(K10:K11) -> 7199.17 | L12: =SUM(L10:L11) -> 8546.7506 | M12: =SUM(M10:M11) -> 4643.0682 | N12: =IFERROR(K12/L12,0) -> 0.84232831 | O12: =K12-L12 -> -1347.5806 | P12: =IFERROR(K12/M12,0) -> 1.55052 | Q12: =K12-M12 -> 2556.1018
A13: セミナー＋プログラム | C13: =SUMIF('25年PDCA'!$AL$5:$AL$34,サマリ!$A13,'25年PDCA'!$AZ$5:$AZ$34) -> 28899.125 | D13: =SUMIF('25年PDCA'!$BD$5:$BD$34,サマリ!$A13,'25年PDCA'!$BR$5:$BR$34) -> 25536.592 | E13: =SUMIF('25年PDCA'!$BY$5:$BY$34,サマリ!$A13,'25年PDCA'!$CM$5:$CM$35) -> 18228.727 | F13: =IFERROR(C13/D13,0) -> 1.1316751 | G13: =C13-D13 -> 3362.5322 | H13: =IFERROR(C13/E13,0) -> 1.5853616 | I13: =C13-E13 -> 10670.397 | K13: =SUMIF('25年PDCA'!$AL$5:$AL$34,サマリ!$A13,'25年PDCA'!$BA$5:$BA$34) -> 4108.7364 | L13: =SUMIF('25年PDCA'!$BD$5:$BD$34,サマリ!$A13,'25年PDCA'!$BS$5:$BS$34) -> 3137.093 | M13: =SUMIF('25年PDCA'!$BY$5:$BY$34,サマリ!$A13,'25年PDCA'!$CN$5:$CN$34) -> 2121.7273 | N13: =IFERROR(K13/L13,0) -> 1.3097273 | O13: =K13-L13 -> 971.64339 | P13: =IFERROR(K13/M13,0) -> 1.9365054 | Q13: =K13-M13 -> 1987.0091
A14: ストア内EC | C14: =SUMIF('25年PDCA'!$AL$5:$AL$34,サマリ!$A14,'25年PDCA'!$AZ$5:$AZ$34) -> 99 | D14: =SUMIF('25年PDCA'!$BD$5:$BD$34,サマリ!$A14,'25年PDCA'!$BR$5:$BR$34) -> 428.41667 | E14: =SUMIF('25年PDCA'!$BY$5:$BY$34,サマリ!$A14,'25年PDCA'!$CM$5:$CM$35) -> 396.63664 | F14: =IFERROR(C14/D14,0) -> 0.23108345 | G14: =C14-D14 -> -329.41667 | H14: =IFERROR(C14/E14,0) -> 0.24959873 | I14: =C14-E14 -> -297.63664 | K14: =SUMIF('25年PDCA'!$AL$5:$AL$34,サマリ!$A14,'25年PDCA'!$BA$5:$BA$34) -> 18 | L14: =SUMIF('25年PDCA'!$BD$5:$BD$34,サマリ!$A14,'25年PDCA'!$BS$5:$BS$34) -> 78.083333 | M14: =SUMIF('25年PDCA'!$BY$5:$BY$34,サマリ!$A14,'25年PDCA'!$CN$5:$CN$34) -> 100.906 | N14: =IFERROR(K14/L14,0) -> 0.23052295 | O14: =K14-L14 -> -60.083333 | P14: =IFERROR(K14/M14,0) -> 0.17838384 | Q14: =K14-M14 -> -82.906
A15: 通信+ちゃんねる | C15: =SUMIF('25年PDCA'!$AL$5:$AL$34,サマリ!$A15,'25年PDCA'!$AZ$5:$AZ$34) -> 1140 | D15: =SUMIF('25年PDCA'!$BD$5:$BD$34,サマリ!$A15,'25年PDCA'!$BR$5:$BR$34) -> 502.852 | E15: =SUMIF('25年PDCA'!$BY$5:$BY$34,サマリ!$A15,'25年PDCA'!$CM$5:$CM$35) -> 150 | F15: =IFERROR(C15/D15,0) -> 2.2670686 | G15: =C15-D15 -> 637.148 | H15: =IFERROR(C15/E15,0) -> 7.6 | I15: =C15-E15 -> 990 | K15: =SUMIF('25年PDCA'!$AL$5:$AL$34,サマリ!$A15,'25年PDCA'!$BA$5:$BA$34) -> 182.5 | L15: =SUMIF('25年PDCA'!$BD$5:$BD$34,サマリ!$A15,'25年PDCA'!$BS$5:$BS$34) -> 95.548 | M15: =SUMIF('25年PDCA'!$BY$5:$BY$34,サマリ!$A15,'25年PDCA'!$CN$5:$CN$34) -> 45 | N15: =IFERROR(K15/L15,0) -> 1.9100347 | O15: =K15-L15 -> 86.952 | P15: =IFERROR(K15/M15,0) -> 4.0555556 | Q15: =K15-M15 -> 137.5
A16: 通販 | C16: =SUMIF('25年PDCA'!$AL$5:$AL$34,サマリ!$A16,'25年PDCA'!$AZ$5:$AZ$34) -> 16204 | D16: =SUMIF('25年PDCA'!$BD$5:$BD$34,サマリ!$A16,'25年PDCA'!$BR$5:$BR$34) -> 20644.301 | E16: =SUMIF('25年PDCA'!$BY$5:$BY$34,サマリ!$A16,'25年PDCA'!$CM$5:$CM$35) -> 18772 | F16: =IFERROR(C16/D16,0) -> 0.78491397 | G16: =C16-D16 -> -4440.3006 | H16: =IFERROR(C16/E16,0) -> 0.86320051 | I16: =C16-E16 -> -2568 | K16: =SUMIF('25年PDCA'!$AL$5:$AL$34,サマリ!$A16,'25年PDCA'!$BA$5:$BA$34) -> 0 | L16: =SUMIF('25年PDCA'!$BD$5:$BD$34,サマリ!$A16,'25年PDCA'!$BS$5:$BS$34) -> 1598.3 | M16: =SUMIF('25年PDCA'!$BY$5:$BY$34,サマリ!$A16,'25年PDCA'!$CN$5:$CN$34) -> 9511 | N16: =IFERROR(K16/L16,0) -> 0 | O16: =K16-L16 -> -1598.3 | P16: =IFERROR(K16/M16,0) -> 0 | Q16: =K16-M16 -> -9511
A17: 卸売り＋企業内手売り | C17: =SUMIF('25年PDCA'!$AL$5:$AL$34,サマリ!$A17,'25年PDCA'!$AZ$5:$AZ$34) -> 33907.574 | D17: =SUMIF('25年PDCA'!$BD$5:$BD$34,サマリ!$A17,'25年PDCA'!$BR$5:$BR$34) -> 36967.255 | E17: =SUMIF('25年PDCA'!$BY$5:$BY$34,サマリ!$A17,'25年PDCA'!$CM$5:$CM$35) -> 26538.688 | F17: =IFERROR(C17/D17,0) -> 0.91723267 | G17: =C17-D17 -> -3059.681 | H17: =IFERROR(C17/E17,0) -> 1.2776658 | I17: =C17-E17 -> 7368.8863 | K17: =SUMIF('25年PDCA'!$AL$5:$AL$34,サマリ!$A17,'25年PDCA'!$BA$5:$BA$34) -> 9000.9173 | L17: =SUMIF('25年PDCA'!$BD$5:$BD$34,サマリ!$A17,'25年PDCA'!$BS$5:$BS$34) -> 9568.4191 | M17: =SUMIF('25年PDCA'!$BY$5:$BY$34,サマリ!$A17,'25年PDCA'!$CN$5:$CN$34) -> 5601.7809 | N17: =IFERROR(K17/L17,0) -> 0.94069012 | O17: =K17-L17 -> -567.50182 | P17: =IFERROR(K17/M17,0) -> 1.6067957 | Q17: =K17-M17 -> 3399.1364
A18: フロー計 | C18: =SUM(C13:C17) -> 80249.699 | D18: =SUM(D13:D17) -> 84079.417 | E18: =SUM(E13:E17) -> 64086.052 | F18: =IFERROR(C18/D18,0) -> 0.95445118 | G18: =C18-D18 -> -3829.7181 | H18: =IFERROR(C18/E18,0) -> 1.2522179 | I18: =C18-E18 -> 16163.647 | K18: =SUM(K13:K17) -> 13310.154 | L18: =SUM(L13:L17) -> 14477.443 | M18: =SUM(M13:M17) -> 17380.414 | N18: =IFERROR(K18/L18,0) -> 0.91937183 | O18: =K18-L18 -> -1167.2898 | P18: =IFERROR(K18/M18,0) -> 0.76581337 | Q18: =K18-M18 -> -4070.2605
A19: 計 | C19: =C9+C12+C18 -> 138841.43 | D19: =D9+D12+D18 -> 145966.56 | E19: =E9+E12+E18 -> 113024 | F19: =IFERROR(C19/D19,0) -> 0.95118657 | G19: =C19-D19 -> -7125.1282 | H19: =IFERROR(C19/E19,0) -> 1.2284242 | I19: =C19-E19 -> 25817.422 | K19: =K9+K12+K18 -> 21020.106 | L19: =L9+L12+L18 -> 28006.06 | M19: =M9+M12+M18 -> 25027.038 | N19: =IFERROR(K19/L19,0) -> 0.75055562 | O19: =K19-L19 -> -6985.9544 | P19: =IFERROR(K19/M19,0) -> 0.83989587 | Q19: =K19-M19 -> -4006.9322
A21: ■KPI
A22: チャネル | B22: 項目 | C22: =A1 -> 7 | K22: =A1 -> 7
C23: 実績 | D23: 予算 | E23: 前年 | F23: 予算比 | G23: 予算差 | H23: 前年比 | I23: 前年差 | K23: 実績 | L23: 予算 | M23: 前年 | N23: 予算比 | O23: 予算差 | P23: 前年比 | Q23: 前年差
A24: 新規（WEB） | B24: 新規リード数 | C24: =SUMIFS('25年PDCA'!$AZ$102:$AZ$140,'25年PDCA'!$AK$102:$AK$140,サマリ!$A24,'25年PDCA'!$AL$102:$AL$140,サマリ!$B24) -> 3095 | D24: =SUMIFS('25年PDCA'!$BR$102:$BR$140,'25年PDCA'!$BC$102:$BC$140,サマリ!$A24,'25年PDCA'!$BD$102:$BD$140,サマリ!$B24) -> 2319 | E24: 275 | F24: =IFERROR(C24/D24,0) -> 1.334627 | G24: =C24-D24 -> 776 | H24: =IFERROR(C24/E24,0) -> 11.254545 | I24: =C24-E24 -> 2820 | K24: =SUMIFS('25年PDCA'!$BA$102:$BA$140,'25年PDCA'!$AK$102:$AK$140,サマリ!$A24,'25年PDCA'!$AL$102:$AL$140,サマリ!$B24) -> 288 | L24: =SUMIFS('25年PDCA'!$BS$102:$BS$140,'25年PDCA'!$BC$102:$BC$140,サマリ!$A24,'25年PDCA'!$BD$102:$BD$140,サマリ!$B24) -> 518 | M24: 63 | N24: =IFERROR(K24/L24,0) -> 0.55598456 | O24: =K24-L24 -> -230 | P24: =IFERROR(K24/M24,0) -> 4.5714286 | Q24: =K24-M24 -> 225
B25: 商談ステージ | K25: =SUMIFS('25年PDCA'!$BA$102:$BA$140,'25年PDCA'!$AK$102:$AK$140,サマリ!$A24,'25年PDCA'!$AL$102:$AL$140,サマリ!$B25) -> 503 | L25: =SUMIFS('25年PDCA'!$BS$102:$BS$140,'25年PDCA'!$BC$102:$BC$140,サマリ!$A24,'25年PDCA'!$BD$102:$BD$140,サマリ!$B25) -> 3147.3333 | N25: =IFERROR(K25/L25,0) -> 0.15981784 | O25: =K25-L25 -> -2644.3333 | P25: =IFERROR(K25/M25,0) -> 0 | Q25: =K25-M25 -> 503
B26: 具体検討ステージ | K26: =SUMIFS('25年PDCA'!$BA$102:$BA$140,'25年PDCA'!$AK$102:$AK$140,サマリ!$A24,'25年PDCA'!$AL$102:$AL$140,サマリ!$B26) -> 9 | L26: =SUMIFS('25年PDCA'!$BS$102:$BS$140,'25年PDCA'!$BC$102:$BC$140,サマリ!$A24,'25年PDCA'!$BD$102:$BD$140,サマリ!$B26) -> 322 | N26: =IFERROR(K26/L26,0) -> 0.027950311 | O26: =K26-L26 -> -313 | P26: =IFERROR(K26/M26,0) -> 0 | Q26: =K26-M26 -> 9
B27: 内諾ステージ | K27: =SUMIFS('25年PDCA'!$BA$102:$BA$140,'25年PDCA'!$AK$102:$AK$140,サマリ!$A24,'25年PDCA'!$AL$102:$AL$140,サマリ!$B27) -> 3 | L27: =SUMIFS('25年PDCA'!$BS$102:$BS$140,'25年PDCA'!$BC$102:$BC$140,サマリ!$A24,'25年PDCA'!$BD$102:$BD$140,サマリ!$B27) -> 26 | N27: =IFERROR(K27/L27,0) -> 0.11538462 | O27: =K27-L27 -> -23 | P27: =IFERROR(K27/M27,0) -> 0 | Q27: =K27-M27 -> 3
B28: 新規アプリ獲得数（単月） | C28: =SUMIFS('25年PDCA'!$AZ$102:$AZ$140,'25年PDCA'!$AK$102:$AK$140,サマリ!$A24,'25年PDCA'!$AL$102:$AL$140,サマリ!$B28) -> 0 | D28: =SUMIFS('25年PDCA'!$BR$102:$BR$140,'25年PDCA'!$BC$102:$BC$140,サマリ!$A24,'25年PDCA'!$BD$102:$BD$140,サマリ!$B28) -> 14 | F28: =IFERROR(C28/D28,0) -> 0 | G28: =C28-D28 -> -14 | H28: =IFERROR(C28/E28,0) -> 0 | I28: =C28-E28 -> 0 | K28: =SUMIFS('25年PDCA'!$BA$102:$BA$140,'25年PDCA'!$AK$102:$AK$140,サマリ!$A24,'25年PDCA'!$AL$102:$AL$140,サマリ!$B28) -> 0 | L28: =SUMIFS('25年PDCA'!$BS$102:$BS$140,'25年PDCA'!$BC$102:$BC$140,サマリ!$A24,'25年PDCA'!$BD$102:$BD$140,サマリ!$B28) -> 14 | N28: =IFERROR(K28/L28,0) -> 0 | O28: =K28-L28 -> -14 | P28: =IFERROR(K28/M28,0) -> 0 | Q28: =K28-M28 -> 0
A29: 新規（法人） | B29: 新規リード数 | C29: =SUMIFS('25年PDCA'!$AZ$102:$AZ$140,'25年PDCA'!$AK$102:$AK$140,サマリ!$A29,'25年PDCA'!$AL$102:$AL$140,サマリ!$B29) -> 0 | D29: =SUMIFS('25年PDCA'!$BR$102:$BR$140,'25年PDCA'!$BC$102:$BC$140,サマリ!$A29,'25年PDCA'!$BD$102:$BD$140,サマリ!$B29) -> 0 | F29: =IFERROR(C29/D29,0) -> 0 | G29: =C29-D29 -> 0 | H29: =IFERROR(C29/E29,0) -> 0 | I29: =C29-E29 -> 0 | K29: =SUMIFS('25年PDCA'!$BA$102:$BA$140,'25年PDCA'!$AK$102:$AK$140,サマリ!$A29,'25年PDCA'!$AL$102:$AL$140,サマリ!$B29) -> 0 | L29: =SUMIFS('25年PDCA'!$BS$102:$BS$140,'25年PDCA'!$BC$102:$BC$140,サマリ!$A29,'25年PDCA'!$BD$102:$BD$140,サマリ!$B29) -> 0 | N29: =IFERROR(K29/L29,0) -> 0 | O29: =K29-L29 -> 0 | P29: =IFERROR(K29/M29,0) -> 0 | Q29: =K29-M29 -> 0 | R29: ※データに存在しないが項目として仮設定
B30: 商談ステージ | K30: =SUMIFS('25年PDCA'!$BA$102:$BA$140,'25年PDCA'!$AK$102:$AK$140,サマリ!$A29,'25年PDCA'!$AL$102:$AL$140,サマリ!$B30) -> 77 | L30: =SUMIFS('25年PDCA'!$BS$102:$BS$140,'25年PDCA'!$BC$102:$BC$140,サマリ!$A29,'25年PDCA'!$BD$102:$BD$140,サマリ!$B30) -> 85 | N30: =IFERROR(K30/L30,0) -> 0.90588235 | O30: =K30-L30 -> -8 | P30: =IFERROR(K30/M30,0) -> 0 | Q30: =K30-M30 -> 77
B31: 具体検討ステージ | K31: =SUMIFS('25年PDCA'!$BA$102:$BA$140,'25年PDCA'!$AK$102:$AK$140,サマリ!$A29,'25年PDCA'!$AL$102:$AL$140,サマリ!$B31) -> 0 | L31: =SUMIFS('25年PDCA'!$BS$102:$BS$140,'25年PDCA'!$BC$102:$BC$140,サマリ!$A29,'25年PDCA'!$BD$102:$BD$140,サマリ!$B31) -> 22 | N31: =IFERROR(K31/L31,0) -> 0 | O31: =K31-L31 -> -22 | P31: =IFERROR(K31/M31,0) -> 0 | Q31: =K31-M31 -> 0
B32: 内諾ステージ | K32: =SUMIFS('25年PDCA'!$BA$102:$BA$140,'25年PDCA'!$AK$102:$AK$140,サマリ!$A29,'25年PDCA'!$AL$102:$AL$140,サマリ!$B32) -> 3 | L32: =SUMIFS('25年PDCA'!$BS$102:$BS$140,'25年PDCA'!$BC$102:$BC$140,サマリ!$A29,'25年PDCA'!$BD$102:$BD$140,サマリ!$B32) -> 4 | N32: =IFERROR(K32/L32,0) -> 0.75 | O32: =K32-L32 -> -1 | P32: =IFERROR(K32/M32,0) -> 0 | Q32: =K32-M32 -> 3
B33: 新規アプリ獲得数（単月） | C33: =SUMIFS('25年PDCA'!$AZ$102:$AZ$140,'25年PDCA'!$AK$102:$AK$140,サマリ!$A29,'25年PDCA'!$AL$102:$AL$140,サマリ!$B33) -> 0 | D33: =SUMIFS('25年PDCA'!$BR$102:$BR$140,'25年PDCA'!$BC$102:$BC$140,サマリ!$A29,'25年PDCA'!$BD$102:$BD$140,サマリ!$B33) -> 1 | F33: =IFERROR(C33/D33,0) -> 0 | G33: =C33-D33 -> -1 | H33: =IFERROR(C33/E33,0) -> 0 | I33: =C33-E33 -> 0 | K33: =SUMIFS('25年PDCA'!$BA$102:$BA$140,'25年PDCA'!$AK$102:$AK$140,サマリ!$A29,'25年PDCA'!$AL$102:$AL$140,サマリ!$B33) -> 0 | L33: =SUMIFS('25年PDCA'!$BS$102:$BS$140,'25年PDCA'!$BC$102:$BC$140,サマリ!$A29,'25年PDCA'!$BD$102:$BD$140,サマリ!$B33) -> 1 | N33: =IFERROR(K33/L33,0) -> 0 | O33: =K33-L33 -> -1 | P33: =IFERROR(K33/M33,0) -> 0 | Q33: =K33-M33 -> 0
A34: 新規（代理店） | B34: 新規リード数 | C34: =SUMIFS('25年PDCA'!$AZ$102:$AZ$140,'25年PDCA'!$AK$102:$AK$140,サマリ!$A34,'25年PDCA'!$AL$102:$AL$140,サマリ!$B34) -> 21 | D34: =SUMIFS('25年PDCA'!$BR$102:$BR$140,'25年PDCA'!$BC$102:$BC$140,サマリ!$A34,'25年PDCA'!$BD$102:$BD$140,サマリ!$B34) -> 524.44444 | F34: =IFERROR(C34/D34,0) -> 0.040042373 | G34: =C34-D34 -> -503.44444 | H34: =IFERROR(C34/E34,0) -> 0 | I34: =C34-E34 -> 21 | K34: =SUMIFS('25年PDCA'!$BA$102:$BA$140,'25年PDCA'!$AK$102:$AK$140,サマリ!$A34,'25年PDCA'!$AL$102:$AL$140,サマリ!$B34) -> 1 | L34: =SUMIFS('25年PDCA'!$BS$102:$BS$140,'25年PDCA'!$BC$102:$BC$140,サマリ!$A34,'25年PDCA'!$BD$102:$BD$140,サマリ!$B34) -> 182.22222 | N34: =IFERROR(K34/L34,0) -> 0.0054878049 | O34: =K34-L34 -> -181.22222 | P34: =IFERROR(K34/M34,0) -> 0 | Q34: =K34-M34 -> 1
B35: 商談ステージ | K35: =SUMIFS('25年PDCA'!$BA$102:$BA$140,'25年PDCA'!$AK$102:$AK$140,サマリ!$A34,'25年PDCA'!$AL$102:$AL$140,サマリ!$B35) -> 5 | L35: =SUMIFS('25年PDCA'!$BS$102:$BS$140,'25年PDCA'!$BC$102:$BC$140,サマリ!$A34,'25年PDCA'!$BD$102:$BD$140,サマリ!$B35) -> 421.77778 | N35: =IFERROR(K35/L35,0) -> 0.011854584 | O35: =K35-L35 -> -416.77778 | P35: =IFERROR(K35/M35,0) -> 0 | Q35: =K35-M35 -> 5
B36: 具体検討ステージ | K36: =SUMIFS('25年PDCA'!$BA$102:$BA$140,'25年PDCA'!$AK$102:$AK$140,サマリ!$A34,'25年PDCA'!$AL$102:$AL$140,サマリ!$B36) -> 3 | L36: =SUMIFS('25年PDCA'!$BS$102:$BS$140,'25年PDCA'!$BC$102:$BC$140,サマリ!$A34,'25年PDCA'!$BD$102:$BD$140,サマリ!$B36) -> 42 | N36: =IFERROR(K36/L36,0) -> 0.071428571 | O36: =K36-L36 -> -39 | P36: =IFERROR(K36/M36,0) -> 0 | Q36: =K36-M36 -> 3
B37: 内諾ステージ | K37: =SUMIFS('25年PDCA'!$BA$102:$BA$140,'25年PDCA'!$AK$102:$AK$140,サマリ!$A34,'25年PDCA'!$AL$102:$AL$140,サマリ!$B37) -> 0 | L37: =SUMIFS('25年PDCA'!$BS$102:$BS$140,'25年PDCA'!$BC$102:$BC$140,サマリ!$A34,'25年PDCA'!$BD$102:$BD$140,サマリ!$B37) -> 12 | N37: =IFERROR(K37/L37,0) -> 0 | O37: =K37-L37 -> -12 | P37: =IFERROR(K37/M37,0) -> 0 | Q37: =K37-M37 -> 0
B38: 新規アプリ獲得数（単月） | C38: =SUMIFS('25年PDCA'!$AZ$102:$AZ$140,'25年PDCA'!$AK$102:$AK$140,サマリ!$A34,'25年PDCA'!$AL$102:$AL$140,サマリ!$B38) -> 0 | D38: =SUMIFS('25年PDCA'!$BR$102:$BR$140,'25年PDCA'!$BC$102:$BC$140,サマリ!$A34,'25年PDCA'!$BD$102:$BD$140,サマリ!$B38) -> 5 | F38: =IFERROR(C38/D38,0) -> 0 | G38: =C38-D38 -> -5 | H38: =IFERROR(C38/E38,0) -> 0 | I38: =C38-E38 -> 0 | K38: =SUMIFS('25年PDCA'!$BA$102:$BA$140,'25年PDCA'!$AK$102:$AK$140,サマリ!$A34,'25年PDCA'!$AL$102:$AL$140,サマリ!$B38) -> 0 | L38: =SUMIFS('25年PDCA'!$BS$102:$BS$140,'25年PDCA'!$BC$102:$BC$140,サマリ!$A34,'25年PDCA'!$BD$102:$BD$140,サマリ!$B38) -> 5 | N38: =IFERROR(K38/L38,0) -> 0 | O38: =K38-L38 -> -5 | P38: =IFERROR(K38/M38,0) -> 0 | Q38: =K38-M38 -> 0
A39: クロスセル | B39: 商談ステージ | C39: =SUMIFS('25年PDCA'!$AZ$102:$AZ$140,'25年PDCA'!$AK$102:$AK$140,サマリ!$A39,'25年PDCA'!$AL$102:$AL$140,サマリ!$B39) -> 310 | D39: =SUMIFS('25年PDCA'!$BR$102:$BR$140,'25年PDCA'!$BC$102:$BC$140,サマリ!$A39,'25年PDCA'!$BD$102:$BD$140,サマリ!$B39) -> 805.24364 | F39: =IFERROR(C39/D39,0) -> 0.38497665 | G39: =C39-D39 -> -495.24364 | H39: =IFERROR(C39/E39,0) -> 0 | I39: =C39-E39 -> 310 | K39: =SUMIFS('25年PDCA'!$BA$102:$BA$140,'25年PDCA'!$AK$102:$AK$140,サマリ!$A39,'25年PDCA'!$AL$102:$AL$140,サマリ!$B39) -> 40 | L39: =SUMIFS('25年PDCA'!$BS$102:$BS$140,'25年PDCA'!$BC$102:$BC$140,サマリ!$A39,'25年PDCA'!$BD$102:$BD$140,サマリ!$B39) -> 198.42345 | N39: =IFERROR(K39/L39,0) -> 0.20158908 | O39: =K39-L39 -> -158.42345 | P39: =IFERROR(K39/M39,0) -> 0 | Q39: =K39-M39 -> 40
B40: 具体検討ステージ | K40: =SUMIFS('25年PDCA'!$BA$102:$BA$140,'25年PDCA'!$AK$102:$AK$140,サマリ!$A39,'25年PDCA'!$AL$102:$AL$140,サマリ!$B40) -> 30 | L40: =SUMIFS('25年PDCA'!$BS$102:$BS$140,'25年PDCA'!$BC$102:$BC$140,サマリ!$A39,'25年PDCA'!$BD$102:$BD$140,サマリ!$B40) -> 60.551914 | N40: =IFERROR(K40/L40,0) -> 0.49544264 | O40: =K40-L40 -> -30.551914 | P40: =IFERROR(K40/M40,0) -> 0 | Q40: =K40-M40 -> 30
B41: 内諾ステージ | K41: =SUMIFS('25年PDCA'!$BA$102:$BA$140,'25年PDCA'!$AK$102:$AK$140,サマリ!$A39,'25年PDCA'!$AL$102:$AL$140,サマリ!$B41) -> 0 | L41: =SUMIFS('25年PDCA'!$BS$102:$BS$140,'25年PDCA'!$BC$102:$BC$140,サマリ!$A39,'25年PDCA'!$BD$102:$BD$140,サマリ!$B41) -> 11.02464 | N41: =IFERROR(K41/L41,0) -> 0 | O41: =K41-L41 -> -11.02464 | P41: =IFERROR(K41/M41,0) -> 0 | Q41: =K41-M41 -> 0
B42: 新規アプリ獲得数（単月） | C42: =SUMIFS('25年PDCA'!$AZ$102:$AZ$140,'25年PDCA'!$AK$102:$AK$140,サマリ!$A39,'25年PDCA'!$AL$102:$AL$140,サマリ!$B42) -> 0 | D42: =SUMIFS('25年PDCA'!$BR$102:$BR$140,'25年PDCA'!$BC$102:$BC$140,サマリ!$A39,'25年PDCA'!$BD$102:$BD$140,サマリ!$B42) -> 3.888 | F42: =IFERROR(C42/D42,0) -> 0 | G42: =C42-D42 -> -3.888 | H42: =IFERROR(C42/E42,0) -> 0 | I42: =C42-E42 -> 0 | K42: =SUMIFS('25年PDCA'!$BA$102:$BA$140,'25年PDCA'!$AK$102:$AK$140,サマリ!$A39,'25年PDCA'!$AL$102:$AL$140,サマリ!$B42) -> 0 | L42: =SUMIFS('25年PDCA'!$BS$102:$BS$140,'25年PDCA'!$BC$102:$BC$140,サマリ!$A39,'25年PDCA'!$BD$102:$BD$140,サマリ!$B42) -> 3.888 | N42: =IFERROR(K42/L42,0) -> 0 | O42: =K42-L42 -> -3.888 | P42: =IFERROR(K42/M42,0) -> 0 | Q42: =K42-M42 -> 0

Sheet グラフ
D1: １月 | E1: ２月 | F1: ３月 | G1: ４月 | H1: ５月 | I1: ６月 | J1: ７月 | K1: ８月 | L1: ９月 | M1: １０月 | N1: １１月 | O1: １２月
A2: 商談ステージ数 | B2: WEB | C2: 計画 | D2: {='25年PDCA'!BE105:BP105} -> 0 | E2: 0 | F2: 207.40741 | G2: 656.2963 | H2: 1271.8519 | I2: 2114.5185 | J2: 3147.3333 | K2: 4486.8148 | L2: 5587.4815 | M2: 6724.5926 | N2: 6237.2593 | O2: 0
C3: 実績 | D3: {='25年PDCA'!AM105:AX105} -> 0 | E3: 0 | F3: 0 | G3: 404 | H3: 454 | I3: 496 | J3: 503 | K3: 0 | L3: 0 | M3: 0 | N3: 0 | O3: 0
B4: 法人 | C4: 計画 | D4: {='25年PDCA'!BE114:BP114} -> 0 | E4: 6.5789474 | F4: 23.815789 | G4: 42.631579 | H4: 58.947368 | I4: 75.263158 | J4: 85 | K4: 77.5 | L4: 77.5 | M4: 77.5 | N4: 77.5 | O4: 77.5
C5: 実績 | D5: {='25年PDCA'!AM114:AX114} -> 0 | E5: 2 | F5: 13 | G5: 29 | H5: 50 | I5: 63 | J5: 77 | K5: 0 | L5: 0 | M5: 0 | N5: 0 | O5: 0
B6: 代理店 | C6: 計画 | D6: {='25年PDCA'!BE124:BP124} -> 0 | E6: 0 | F6: 27.777778 | G6: 72.222222 | H6: 102.22222 | I6: 140 | J6: 182.22222 | K6: 217.77778 | L6: 164.44444 | M6: 164.44444 | N6: 0 | O6: 0
C7: 実績 | D7: {='25年PDCA'!AM124:AX124} -> 2 | E7: 2 | F7: 4 | G7: 2 | H7: 7 | I7: 3 | J7: 1 | K7: 0 | L7: 0 | M7: 0 | N7: 0 | O7: 0
B8: クロスセル | C8: 計画 | D8: {='25年PDCA'!BE136:BP136} -> 0 | E8: 0 | F8: 57.2 | G8: 156.8 | H8: 199.2384 | I8: 193.58179 | J8: 198.42345 | K8: 201.57955 | L8: 205.57019 | M8: 208.81753 | N8: 270 | O8: 270
C9: 実績 | D9: {='25年PDCA'!AM136:AX136} -> 0 | E9: 0 | F9: 36 | G9: 71 | H9: 81 | I9: 82 | J9: 40 | K9: 0 | L9: 0 | M9: 0 | N9: 0 | O9: 0
A11: 具体検討ステージ数 | B11: WEB | C11: 計画 | D11: {='25年PDCA'!BE106:BP106} -> 0 | E11: 0 | F11: 0 | G11: 62.222222 | H11: 153.33333 | I11: 230.66667 | J11: 322 | K11: 406.44444 | L11: 523.77778 | M11: 487.33333 | N11: 487.33333 | O11: 0
C12: 実績 | D12: {='25年PDCA'!AM106:AX106} -> 0 | E12: 2 | F12: 0 | G12: 1 | H12: 8 | I12: 10 | J12: 9 | K12: 0 | L12: 0 | M12: 0 | N12: 0 | O12: 0
B13: 法人 | C13: 計画 | D13: {='25年PDCA'!BE117:BP117} -> 0 | E13: 0 | F13: 2.5 | G13: 7.5 | H13: 11.5 | I13: 16 | J13: 22 | K13: 25.5 | L13: 24 | M13: 28.5 | N13: 0 | O13: 0
C14: 実績 | D14: {='25年PDCA'!AM128:AX128} -> 0 | E14: 0 | F14: 0 | G14: 0 | H14: 1 | I14: 3 | J14: 3 | K14: 0 | L14: 0 | M14: 0 | N14: 0 | O14: 0
B15: 代理店 | C15: 計画 | D15: {='25年PDCA'!BE128:BP128} -> 0 | E15: 0 | F15: 0 | G15: 8.3333333 | H15: 21.666667 | I15: 30.666667 | J15: 42 | K15: 54.666667 | L15: 65.333333 | M15: 49.333333 | N15: 49.333333 | O15: 0
C16: 実績 | D16: {='25年PDCA'!AM128:AX128} -> 0 | E16: 0 | F16: 0 | G16: 0 | H16: 1 | I16: 3 | J16: 3 | K16: 0 | L16: 0 | M16: 0 | N16: 0 | O16: 0
B17: クロスセル | C17: 計画 | D17: {='25年PDCA'!BE137:BP137} -> 0 | E17: 0 | F17: 10.8 | G17: 43.2 | H17: 66.4416 | I17: 63.458208 | J17: 60.551914 | K17: 64.429808 | L17: 61.18247 | M17: 58.035055 | N17: 0 | O17: 0
C18: 実績 | D18: {='25年PDCA'!AM137:AX137} -> 0 | E18: 0 | F18: 7 | G18: 12 | H18: 15 | I18: 15 | J18: 30 | K18: 0 | L18: 0 | M18: 0 | N18: 0 | O18: 0
A20: 内諾ステージ | B20: WEB | C20: 計画 | D20: {='25年PDCA'!BE107:BP107} -> 0 | E20: 0 | F20: 0 | G20: 0 | H20: 15.555556 | I20: 26.666667 | J20: 26 | K20: 29.333333 | L20: 28.444444 | M20: 36.444444 | N20: 0 | O20: 0
C21: 実績 | D21: {='25年PDCA'!AM107:AX107} -> 0 | E21: 0 | F21: 2 | G21: 2 | H21: 2 | I21: 2 | J21: 3 | K21: 0 | L21: 0 | M21: 0 | N21: 0 | O21: 0
B22: 法人 | C22: 計画 | D22: {='25年PDCA'!BE120:BP120} -> 0 | E22: 0 | F22: 0 | G22: 0 | H22: 1 | I22: 3 | J22: 4 | K22: 4 | L22: 4 | M22: 3 | N22: 0 | O22: 0
C23: 実績 | D23: {='25年PDCA'!AM120:AX120} -> 0 | E23: 0 | F23: 2 | G23: 2 | H23: 3 | I23: 3 | J23: 3 | K23: 0 | L23: 0 | M23: 0 | N23: 0 | O23: 0
B24: 代理店 | C24: 計画 | D24: {='25年PDCA'!BE129:BP129} -> 0 | E24: 0 | F24: 0 | G24: 0 | H24: 5 | I24: 11 | J24: 12 | K24: 14 | L24: 16 | M24: 16 | N24: 0 | O24: 0
C25: 実績 | D25: {='25年PDCA'!AM129:AX129} -> 0 | E25: 0 | F25: 0 | G25: 0 | H25: 0 | I25: 0 | J25: 0 | K25: 0 | L25: 0 | M25: 0 | N25: 0 | O25: 0
B26: クロスセル | C26: 計画 | D26: {='25年PDCA'!BE138:BP138} -> 0 | E26: 0 | F26: 0 | G26: 0 | H26: 4.32 | I26: 12.96 | J26: 11.02464 | K26: 3.9906432 | L26: 3.2473382 | M26: 3.1474151 | N26: 0 | O26: 0
C27: 実績 | D27: {='25年PDCA'!AM138:AX138} -> 0 | E27: 0 | F27: 0 | G27: 0 | H27: 0 | I27: 0 | J27: 0 | K27: 0 | L27: 0 | M27: 0 | N27: 0 | O27: 0
A30: 具体検討移行率 | B30: WEB | C30: 計画 | D30: ='25年PDCA'!BE142 -> 1 | E30: ='25年PDCA'!BF142 -> 2 | F30: ='25年PDCA'!BG142 -> 3 | G30: ='25年PDCA'!BH142 -> 4 | H30: ='25年PDCA'!BI142 -> 5 | I30: ='25年PDCA'!BJ142 -> 6 | J30: ='25年PDCA'!BK142 -> 7 | K30: ='25年PDCA'!BL142 -> 8 | ... O30: ='25年PDCA'!BP142 -> 12
C31: 実績 | D31: ='25年PDCA'!AM142 -> 1 | E31: ='25年PDCA'!AN142 -> 2 | F31: ='25年PDCA'!AO142 -> 3 | G31: ='25年PDCA'!AP142 -> 4 | H31: ='25年PDCA'!AQ142 -> 5 | I31: ='25年PDCA'!AR142 -> 6 | J31: ='25年PDCA'!AS142 -> 7 | K31: ='25年PDCA'!AT142 -> 8 | ... O31: ='25年PDCA'!AX142 -> 12
B32: 法人 | C32: 計画 | D32: ='25年PDCA'!#REF! -> #REF! | E32: ='25年PDCA'!#REF! -> #REF! | F32: ='25年PDCA'!#REF! -> #REF! | G32: ='25年PDCA'!#REF! -> #REF! | H32: ='25年PDCA'!#REF! -> #REF! | I32: ='25年PDCA'!#REF! -> #REF! | J32: ='25年PDCA'!#REF! -> #REF! | K32: ='25年PDCA'!#REF! -> #REF! | ... O32: ='25年PDCA'!#REF! -> #REF!
C33: 実績 | D33: ='25年PDCA'!#REF! -> #REF! | E33: ='25年PDCA'!#REF! -> #REF! | F33: ='25年PDCA'!#REF! -> #REF! | G33: ='25年PDCA'!#REF! -> #REF! | H33: ='25年PDCA'!#REF! -> #REF! | I33: ='25年PDCA'!#REF! -> #REF! | J33: ='25年PDCA'!#REF! -> #REF! | K33: ='25年PDCA'!#REF! -> #REF! | ... O33: ='25年PDCA'!#REF! -> #REF!
B34: 代理店 | C34: 計画 | D34: ='25年PDCA'!#REF! -> #REF! | E34: ='25年PDCA'!#REF! -> #REF! | F34: ='25年PDCA'!#REF! -> #REF! | G34: ='25年PDCA'!#REF! -> #REF! | H34: ='25年PDCA'!#REF! -> #REF! | I34: ='25年PDCA'!#REF! -> #REF! | J34: ='25年PDCA'!#REF! -> #REF! | K34: ='25年PDCA'!#REF! -> #REF! | ... O34: ='25年PDCA'!#REF! -> #REF!
C35: 実績 | D35: ='25年PDCA'!#REF! -> #REF! | E35: ='25年PDCA'!#REF! -> #REF! | F35: ='25年PDCA'!#REF! -> #REF! | G35: ='25年PDCA'!#REF! -> #REF! | H35: ='25年PDCA'!#REF! -> #REF! | I35: ='25年PDCA'!#REF! -> #REF! | J35: ='25年PDCA'!#REF! -> #REF! | K35: ='25年PDCA'!#REF! -> #REF! | ... O35: ='25年PDCA'!#REF! -> #REF!
B36: クロスセル | C36: 計画 | D36: ='25年PDCA'!BE143 -> 0 | E36: ='25年PDCA'!BF143 -> 0 | F36: ='25年PDCA'!BG143 -> 0 | G36: ='25年PDCA'!BH143 -> 0 | H36: ='25年PDCA'!BI143 -> 0 | I36: ='25年PDCA'!BJ143 -> 0 | J36: ='25年PDCA'!BK143 -> 0 | K36: ='25年PDCA'!BL143 -> 0 | ... O36: ='25年PDCA'!BP143 -> 0
C37: 実績 | D37: ='25年PDCA'!AM143 -> 0 | E37: ='25年PDCA'!AN143 -> 0 | F37: ='25年PDCA'!AO143 -> 0 | G37: ='25年PDCA'!AP143 -> 0 | H37: ='25年PDCA'!AQ143 -> 0 | I37: ='25年PDCA'!AR143 -> 0 | J37: ='25年PDCA'!AS143 -> 0 | K37: ='25年PDCA'!AT143 -> 0 | ... O37: ='25年PDCA'!AX143 -> 0
B39: 通販 | C39: 計画 | D39: ='25年PDCA'!BE32 -> 0 | E39: ='25年PDCA'!BF32 -> 0 | F39: ='25年PDCA'!BG32 -> 28.426 | G39: ='25年PDCA'!BH32 -> 4096.135 | H39: ='25年PDCA'!BI32 -> 5309.5336 | I39: ='25年PDCA'!BJ32 -> 9611.906 | J39: ='25年PDCA'!BK32 -> 1598.3 | K39: ='25年PDCA'!BL32 -> 2495.017 | ... O39: ='25年PDCA'!BP32 -> 186.689
C40: 実績 | D40: ='25年PDCA'!AM32 -> 0 | E40: ='25年PDCA'!AN32 -> 0 | F40: ='25年PDCA'!AO32 -> 0 | G40: ='25年PDCA'!AP32 -> 5004 | H40: ='25年PDCA'!AQ32 -> 0 | I40: ='25年PDCA'!AR32 -> 11200 | J40: ='25年PDCA'!AS32 -> 0 | K40: ='25年PDCA'!AT32 -> 0 | ... O40: ='25年PDCA'!AX32 -> 0
B41: 卸売り＋企業内手売り | C41: 計画 | D41: ='25年PDCA'!BE33 -> 3900.0635 | E41: ='25年PDCA'!BF33 -> 1929.871 | F41: ='25年PDCA'!BG33 -> 2686.5591 | G41: ='25年PDCA'!BH33 -> 2581.7973 | H41: ='25年PDCA'!BI33 -> 10698.765 | I41: ='25年PDCA'!BJ33 -> 5601.7809 | J41: ='25年PDCA'!BK33 -> 9568.4191 | K41: ='25年PDCA'!BL33 -> 7611.4327 | ... O41: ='25年PDCA'!BP33 -> 9966.4
C42: 実績 | D42: ='25年PDCA'!AM33 -> 3895.0635 | E42: ='25年PDCA'!AN33 -> 1893.9274 | F42: ='25年PDCA'!AO33 -> 3463.8223 | G42: ='25年PDCA'!AP33 -> 2307.9295 | H42: ='25年PDCA'!AQ33 -> 5646.6851 | I42: ='25年PDCA'!AR33 -> 7699.2295 | J42: ='25年PDCA'!AS33 -> 9000.9173 | K42: ='25年PDCA'!AT33 -> 0 | ... O42: ='25年PDCA'!AX33 -> 0
B49: WEB | F49: 法人 | J49: 代理店 | N49: クロスセル

Sheet 代理店
C1: 1月 | F1: 2月 | I1: 3月 | L1: 4月 | O1: 5月 | R1: 6月 | U1: 7月 | X1: 8月 | AA1: 9月 | AD1: 10月 | AG1: 11月 | AJ1: 12月
C2: 実績 | D2: 計画 | F2: 実績 | G2: 計画 | I2: 実績 | J2: 計画 | L2: 実績 | M2: 計画 | O2: 実績 | P2: 計画 | R2: 実績 | S2: 計画 | U2: 実績 | V2: 計画 | X2: 実績 | Y2: 計画 | AA2: 実績 | AB2: 計画 | AD2: 実績 | AE2: 計画 | AG2: 実績 | AH2: 計画 | AJ2: 実績 | AK2: 計画
A3: 新規リード | B3: ＴＪＫ | C3: 0 | D3: ='25年PDCA'!BE161 -> 0 | F3: 0 | G3: ='25年PDCA'!BF161 -> 0 | I3: 3 | J3: ='25年PDCA'!BG161 -> 27.777778 | L3: 2 | M3: ='25年PDCA'!BH161 -> 72.222222 | O3: 6 | P3: ='25年PDCA'!BI161 -> 80 | R3: 2 | S3: ='25年PDCA'!BJ161 -> 98 | U3: ='25年PDCA'!AS161 -> 1 | V3: ='25年PDCA'!BK161 -> 19 | X3: ='25年PDCA'!AT161 -> 0 | Y3: ='25年PDCA'!BL161 -> 21 | AA3: ='25年PDCA'!AU161 -> 0 | AB3: ='25年PDCA'!BM161 -> 16 | AD3: ='25年PDCA'!AV161 -> 0 | AE3: ='25年PDCA'!BN161 -> 16 | AG3: ='25年PDCA'!AW161 -> 0 | AH3: ='25年PDCA'!BO161 -> 0 | AJ3: ='25年PDCA'!AX161 -> 0 | AK3: ='25年PDCA'!BP161 -> 0
A4: 新規リード | B4: 社労士 | C4: 2 | D4: ='25年PDCA'!BE162 -> 0 | F4: 2 | G4: ='25年PDCA'!BF162 -> 0 | I4: 1 | J4: ='25年PDCA'!BG162 -> 0 | L4: 0 | M4: ='25年PDCA'!BH162 -> 0 | O4: 0 | P4: ='25年PDCA'!BI162 -> 20 | R4: 0 | S4: ='25年PDCA'!BJ162 -> 28 | U4: ='25年PDCA'!AS162 -> 0 | V4: ='25年PDCA'!BK162 -> 36 | X4: ='25年PDCA'!AT162 -> 0 | Y4: ='25年PDCA'!BL162 -> 44 | AA4: ='25年PDCA'!AU162 -> 0 | AB4: ='25年PDCA'!BM162 -> 33 | AD4: ='25年PDCA'!AV162 -> 0 | AE4: ='25年PDCA'!BN162 -> 33 | AG4: ='25年PDCA'!AW162 -> 0 | AH4: ='25年PDCA'!BO162 -> 0 | AJ4: ='25年PDCA'!AX162 -> 0 | AK4: ='25年PDCA'!BP162 -> 0
A5: 新規リード | B5: その他 | C5: 0 | D5: ='25年PDCA'!BE163 -> 0 | F5: 0 | G5: ='25年PDCA'!BF163 -> 0 | I5: 0 | J5: ='25年PDCA'!BG163 -> 0 | L5: 0 | M5: ='25年PDCA'!BH163 -> 0 | O5: 1 | P5: ='25年PDCA'!BI163 -> 2 | R5: 1 | S5: ='25年PDCA'!BJ163 -> 14 | U5: ='25年PDCA'!AS163 -> 0 | V5: ='25年PDCA'!BK163 -> 127 | X5: ='25年PDCA'!AT163 -> 0 | Y5: ='25年PDCA'!BL163 -> 153 | AA5: ='25年PDCA'!AU163 -> 0 | AB5: ='25年PDCA'!BM163 -> 115 | AD5: ='25年PDCA'!AV163 -> 0 | AE5: ='25年PDCA'!BN163 -> 115 | AG5: ='25年PDCA'!AW163 -> 0 | AH5: ='25年PDCA'!BO163 -> 0 | AJ5: ='25年PDCA'!AX163 -> 0 | AK5: ='25年PDCA'!BP163 -> 0
A6: 有効ステージ | B6: ＴＪＫ | C6: 0 | D6: ='25年PDCA'!BE164 -> 0 | F6: 0 | G6: ='25年PDCA'!BF164 -> 0 | I6: 3 | J6: ='25年PDCA'!BG164 -> 0 | L6: 3 | M6: ='25年PDCA'!BH164 -> 0 | O6: 3 | P6: ='25年PDCA'!BI164 -> 0 | R6: 3 | S6: ='25年PDCA'!BJ164 -> 0 | U6: ='25年PDCA'!AS164 -> 3 | V6: ='25年PDCA'!BK164 -> 0 | X6: ='25年PDCA'!AT164 -> 0 | Y6: ='25年PDCA'!BL164 -> 0 | AA6: ='25年PDCA'!AU164 -> 0 | AB6: ='25年PDCA'!BM164 -> 0 | AD6: ='25年PDCA'!AV164 -> 0 | AE6: ='25年PDCA'!BN164 -> 0 | AG6: ='25年PDCA'!AW164 -> 0 | AH6: ='25年PDCA'!BO164 -> 0 | AJ6: ='25年PDCA'!AX164 -> 0 | AK6: ='25年PDCA'!BP164 -> 0
A7: 有効ステージ | B7: 社労士 | C7: 1 | D7: ='25年PDCA'!BE165 -> 0 | F7: 1 | G7: ='25年PDCA'!BF165 -> 0 | I7: 0 | J7: ='25年PDCA'!BG165 -> 0 | L7: 0 | M7: ='25年PDCA'!BH165 -> 0 | O7: 0 | P7: ='25年PDCA'!BI165 -> 0 | R7: 0 | S7: ='25年PDCA'!BJ165 -> 0 | U7: ='25年PDCA'!AS165 -> 0 | V7: ='25年PDCA'!BK165 -> 0 | X7: ='25年PDCA'!AT165 -> 0 | Y7: ='25年PDCA'!BL165 -> 0 | AA7: ='25年PDCA'!AU165 -> 0 | AB7: ='25年PDCA'!BM165 -> 0 | AD7: ='25年PDCA'!AV165 -> 0 | AE7: ='25年PDCA'!BN165 -> 0 | AG7: ='25年PDCA'!AW165 -> 0 | AH7: ='25年PDCA'!BO165 -> 0 | AJ7: ='25年PDCA'!AX165 -> 0 | AK7: ='25年PDCA'!BP165 -> 0
A8: 有効ステージ | B8: その他 | C8: 0 | D8: ='25年PDCA'!BE166 -> 0 | F8: 0 | G8: ='25年PDCA'!BF166 -> 0 | I8: 0 | J8: ='25年PDCA'!BG166 -> 0 | L8: 0 | M8: ='25年PDCA'!BH166 -> 0 | O8: 1 | P8: ='25年PDCA'!BI166 -> 0 | R8: 0 | S8: ='25年PDCA'!BJ166 -> 0 | U8: ='25年PDCA'!AS166 -> 1 | V8: ='25年PDCA'!BK166 -> 0 | X8: ='25年PDCA'!AT166 -> 0 | Y8: ='25年PDCA'!BL166 -> 0 | AA8: ='25年PDCA'!AU166 -> 0 | AB8: ='25年PDCA'!BM166 -> 0 | AD8: ='25年PDCA'!AV166 -> 0 | AE8: ='25年PDCA'!BN166 -> 0 | AG8: ='25年PDCA'!AW166 -> 0 | AH8: ='25年PDCA'!BO166 -> 0 | AJ8: ='25年PDCA'!AX166 -> 0 | AK8: ='25年PDCA'!BP166 -> 0
A9: 断念ステージ | B9: ＴＪＫ | C9: 0 | D9: ='25年PDCA'!BE167 -> 0 | F9: 0 | G9: ='25年PDCA'!BF167 -> 0 | I9: 0 | J9: ='25年PDCA'!BG167 -> 0 | L9: 1 | M9: ='25年PDCA'!BH167 -> 0 | O9: 0 | P9: ='25年PDCA'!BI167 -> 0 | R9: 0 | S9: ='25年PDCA'!BJ167 -> 0 | U9: ='25年PDCA'!AS167 -> 0 | V9: ='25年PDCA'!BK167 -> 0 | X9: ='25年PDCA'!AT167 -> 0 | Y9: ='25年PDCA'!BL167 -> 0 | AA9: ='25年PDCA'!AU167 -> 0 | AB9: ='25年PDCA'!BM167 -> 0 | AD9: ='25年PDCA'!AV167 -> 0 | AE9: ='25年PDCA'!BN167 -> 0 | AG9: ='25年PDCA'!AW167 -> 0 | AH9: ='25年PDCA'!BO167 -> 0 | AJ9: ='25年PDCA'!AX167 -> 0 | AK9: ='25年PDCA'!BP167 -> 0
A10: 断念ステージ | B10: 社労士 | C10: 0 | D10: ='25年PDCA'!BE168 -> 0 | F10: 0 | G10: ='25年PDCA'!BF168 -> 0 | I10: 1 | J10: ='25年PDCA'!BG168 -> 0 | L10: 1 | M10: ='25年PDCA'!BH168 -> 0 | O10: 1 | P10: ='25年PDCA'!BI168 -> 0 | R10: 1 | S10: ='25年PDCA'!BJ168 -> 0 | U10: ='25年PDCA'!AS168 -> 1 | V10: ='25年PDCA'!BK168 -> 0 | X10: ='25年PDCA'!AT168 -> 0 | Y10: ='25年PDCA'!BL168 -> 0 | AA10: ='25年PDCA'!AU168 -> 0 | AB10: ='25年PDCA'!BM168 -> 0 | AD10: ='25年PDCA'!AV168 -> 0 | AE10: ='25年PDCA'!BN168 -> 0 | AG10: ='25年PDCA'!AW168 -> 0 | AH10: ='25年PDCA'!BO168 -> 0 | AJ10: ='25年PDCA'!AX168 -> 0 | AK10: ='25年PDCA'!BP168 -> 0
A11: 断念ステージ | B11: その他 | C11: 0 | D11: ='25年PDCA'!BE169 -> 0 | F11: 0 | G11: ='25年PDCA'!BF169 -> 0 | I11: 0 | J11: ='25年PDCA'!BG169 -> 0 | L11: 0 | M11: ='25年PDCA'!BH169 -> 0 | O11: 0 | P11: ='25年PDCA'!BI169 -> 0 | R11: 0 | S11: ='25年PDCA'!BJ169 -> 0 | U11: ='25年PDCA'!AS169 -> 0 | V11: ='25年PDCA'!BK169 -> 0 | X11: ='25年PDCA'!AT169 -> 0 | Y11: ='25年PDCA'!BL169 -> 0 | AA11: ='25年PDCA'!AU169 -> 0 | AB11: ='25年PDCA'!BM169 -> 0 | AD11: ='25年PDCA'!AV169 -> 0 | AE11: ='25年PDCA'!BN169 -> 0 | AG11: ='25年PDCA'!AW169 -> 0 | AH11: ='25年PDCA'!BO169 -> 0 | AJ11: ='25年PDCA'!AX169 -> 0 | AK11: ='25年PDCA'!BP169 -> 0
A12: 商談ステージ | B12: ＴＪＫ | C12: 0 | D12: ='25年PDCA'!BE170 -> 0 | F12: 0 | G12: ='25年PDCA'!BF170 -> 0 | I12: 0 | J12: ='25年PDCA'!BG170 -> 27.777778 | L12: 1 | M12: ='25年PDCA'!BH170 -> 91.666667 | O12: 2 | P12: ='25年PDCA'!BI170 -> 120 | R12: 1 | S12: ='25年PDCA'!BJ170 -> 197 | U12: ='25年PDCA'!AS170 -> 1 | V12: ='25年PDCA'!BK170 -> 43 | X12: ='25年PDCA'!AT170 -> 0 | Y12: ='25年PDCA'!BL170 -> 58 | AA12: ='25年PDCA'!AU170 -> 0 | AB12: ='25年PDCA'!BM170 -> 68 | AD12: ='25年PDCA'!AV170 -> 0 | AE12: ='25年PDCA'!BN170 -> 80 | AG12: ='25年PDCA'!AW170 -> 0 | AH12: ='25年PDCA'!BO170 -> 75 | AJ12: ='25年PDCA'!AX170 -> 0 | AK12: ='25年PDCA'!BP170 -> 0
A13: 商談ステージ | B13: 社労士 | C13: 1 | D13: ='25年PDCA'!BE171 -> 0 | F13: 3 | G13: ='25年PDCA'!BF171 -> 0 | I13: 3 | J13: ='25年PDCA'!BG171 -> 0 | L13: 3 | M13: ='25年PDCA'!BH171 -> 0 | O13: 3 | P13: ='25年PDCA'!BI171 -> 34 | R13: 3 | S13: ='25年PDCA'!BJ171 -> 56 | U13: ='25年PDCA'!AS171 -> 4 | V13: ='25年PDCA'!BK171 -> 84 | X13: ='25年PDCA'!AT171 -> 0 | Y13: ='25年PDCA'!BL171 -> 117 | AA13: ='25年PDCA'!AU171 -> 0 | AB13: ='25年PDCA'!BM171 -> 137 | AD13: ='25年PDCA'!AV171 -> 0 | AE13: ='25年PDCA'!BN171 -> 160 | AG13: ='25年PDCA'!AW171 -> 0 | AH13: ='25年PDCA'!BO171 -> 150 | AJ13: ='25年PDCA'!AX171 -> 0 | AK13: ='25年PDCA'!BP171 -> 0
A14: 商談ステージ | B14: その他 | C14: 0 | D14: ='25年PDCA'!BE172 -> 0 | F14: 0 | G14: ='25年PDCA'!BF172 -> 0 | I14: 0 | J14: ='25年PDCA'!BG172 -> 0 | L14: 0 | M14: ='25年PDCA'!BH172 -> 0 | O14: 0 | P14: ='25年PDCA'!BI172 -> 18 | R14: 1 | S14: ='25年PDCA'!BJ172 -> 29 | U14: ='25年PDCA'!AS172 -> 1 | V14: ='25年PDCA'!BK172 -> 295 | X14: ='25年PDCA'!AT172 -> 0 | Y14: ='25年PDCA'!BL172 -> 410 | AA14: ='25年PDCA'!AU172 -> 0 | AB14: ='25年PDCA'!BM172 -> 479 | AD14: ='25年PDCA'!AV172 -> 0 | AE14: ='25年PDCA'!BN172 -> 559 | AG14: ='25年PDCA'!AW172 -> 0 | AH14: ='25年PDCA'!BO172 -> 525 | AJ14: ='25年PDCA'!AX172 -> 0 | AK14: ='25年PDCA'!BP172 -> 0
... A23: 締結ステージ | B23: その他 | C23: 0 | D23: ='25年PDCA'!BE181 -> 0 | F23: 0 | G23: ='25年PDCA'!BF181 -> 0 | I23: 0 | J23: ='25年PDCA'!BG181 -> 0 | L23: 0 | M23: ='25年PDCA'!BH181 -> 0 | O23: 1 | P23: ='25年PDCA'!BI181 -> 0 | R23: 1 | S23: ='25年PDCA'!BJ181 -> 1 | U23: ='25年PDCA'!AS181 -> 1 | V23: ='25年PDCA'!BK181 -> 2 | X23: ='25年PDCA'!AT181 -> 0 | Y23: ='25年PDCA'!BL181 -> 3 | AA23: ='25年PDCA'!AU181 -> 0 | AB23: ='25年PDCA'!BM181 -> 3 | AD23: ='25年PDCA'!AV181 -> 0 | AE23: ='25年PDCA'!BN181 -> 3 | AG23: ='25年PDCA'!AW181 -> 0 | AH23: ='25年PDCA'!BO181 -> 4 | AJ23: ='25年PDCA'!AX181 -> 0 | AK23: ='25年PDCA'!BP181 -> 0
C25: 1月 | F25: 2月 | I25: 3月 | L25: 4月 | O25: 5月 | R25: 6月 | U25: 7月 | X25: 8月 | AA25: 9月 | AD25: 10月 | AG25: 11月 | AJ25: 12月
C26: 実績 | D26: 計画 | F26: 実績 | G26: 計画 | I26: 実績 | J26: 計画 | L26: 実績 | M26: 計画 | O26: 実績 | P26: 計画 | R26: 実績 | S26: 計画 | U26: 実績 | V26: 計画 | X26: 実績 | Y26: 計画 | AA26: 実績 | AB26: 計画 | AD26: 実績 | AE26: 計画 | AG26: 実績 | AH26: 計画 | AJ26: 実績 | AK26: 計画
A27: 具体検討化率 | B27: ＴＪＫ | F27: =((F15++F18)-(C15+C18))/C12 -> #DIV/0! | G27: =((G15++G18)-(D15+D18))/D12 -> #DIV/0! | I27: =((I15++I18)-(F15+F18))/F12 -> #DIV/0! | J27: =((J15++J18)-(G15+G18))/G12 -> #DIV/0! | L27: =((L15++L18)-(I15+I18))/I12 -> #DIV/0! | M27: =((M15++M18)-(J15+J18))/J12 -> 0.3 | O27: =((O15++O18)-(L15+L18))/L12 -> 1 | P27: =((P15++P18)-(M15+M18))/M12 -> 0.11636364 | R27: =((R15++R18)-(O15+O18))/O12 -> 1 | S27: =((S15++S18)-(P15+P18))/P12 -> 0.091666667 | U27: =((U15++U18)-(R15+R18))/R12 -> 0 | V27: =((V15++V18)-(S15+S18))/S12 -> -0.11675127 | X27: =((X15++X18)-(U15+U18))/U12 -> -3 | Y27: =((Y15++Y18)-(V15+V18))/V12 -> 0 | AA27: =((AA15++AA18)-(X15+X18))/X12 -> #DIV/0! | AB27: =((AB15++AB18)-(Y15+Y18))/Y12 -> 0.017241379 | AD27: =((AD15++AD18)-(AA15+AA18))/AA12 -> #DIV/0! | AE27: =((AE15++AE18)-(AB15+AB18))/AB12 -> -0.014705882 | AG27: =((AG15++AG18)-(AD15+AD18))/AD12 -> #DIV/0! | AH27: =((AH15++AH18)-(AE15+AE18))/AE12 -> -0.025 | AJ27: =((AJ15++AJ18)-(AG15+AG18))/AG12 -> #DIV/0! | AK27: =((AK15++AK18)-(AH15+AH18))/AH12 -> -0.066666667
A28: 具体検討化率 | B28: 社労士 | F28: =((F16++F19)-(C16+C19))/C13 -> 0 | G28: =((G16++G19)-(D16+D19))/D13 -> #DIV/0! | I28: =((I16++I19)-(F16+F19))/F13 -> 0 | J28: =((J16++J19)-(G16+G19))/G13 -> #DIV/0! | L28: =((L16++L19)-(I16+I19))/I13 -> 0 | M28: =((M16++M19)-(J16+J19))/J13 -> #DIV/0! | O28: =((O16++O19)-(L16+L19))/L13 -> 0 | P28: =((P16++P19)-(M16+M19))/M13 -> #DIV/0! | R28: =((R16++R19)-(O16+O19))/O13 -> 0 | S28: =((S16++S19)-(P16+P19))/P13 -> 0.088235294 | U28: =((U16++U19)-(R16+R19))/R13 -> 0 | V28: =((V16++V19)-(S16+S19))/S13 -> 0.035714286 | X28: =((X16++X19)-(U16+U19))/U13 -> 0 | Y28: =((Y16++Y19)-(V16+V19))/V13 -> 0.047619048 | AA28: =((AA16++AA19)-(X16+X19))/X13 -> #DIV/0! | AB28: =((AB16++AB19)-(Y16+Y19))/Y13 -> 0.017094017 | AD28: =((AD16++AD19)-(AA16+AA19))/AA13 -> #DIV/0! | AE28: =((AE16++AE19)-(AB16+AB19))/AB13 -> -0.02189781 | AG28: =((AG16++AG19)-(AD16+AD19))/AD13 -> #DIV/0! | AH28: =((AH16++AH19)-(AE16+AE19))/AE13 -> -0.01875 | AJ28: =((AJ16++AJ19)-(AG16+AG19))/AG13 -> #DIV/0! | AK28: =((AK16++AK19)-(AH16+AH19))/AH13 -> -0.066666667
A29: 具体検討化率 | B29: その他 | F29: =((F17++F20)-(C17+C20))/C14 -> #DIV/0! | G29: =((G17++G20)-(D17+D20))/D14 -> #DIV/0! | I29: =((I17++I20)-(F17+F20))/F14 -> #DIV/0! | J29: =((J17++J20)-(G17+G20))/G14 -> #DIV/0! | L29: =((L17++L20)-(I17+I20))/I14 -> #DIV/0! | M29: =((M17++M20)-(J17+J20))/J14 -> #DIV/0! | O29: =((O17++O20)-(L17+L20))/L14 -> #DIV/0! | P29: =((P17++P20)-(M17+M20))/M14 -> #DIV/0! | R29: =((R17++R20)-(O17+O20))/O14 -> #DIV/0! | S29: =((S17++S20)-(P17+P20))/P14 -> 0.055555556 | U29: =((U17++U20)-(R17+R20))/R14 -> 0 | V29: =((V17++V20)-(S17+S20))/S14 -> 1.137931 | X29: =((X17++X20)-(U17+U20))/U14 -> 0 | Y29: =((Y17++Y20)-(V17+V20))/V14 -> 0.037288136 | AA29: =((AA17++AA20)-(X17+X20))/X14 -> #DIV/0! | AB29: =((AB17++AB20)-(Y17+Y20))/Y14 -> 0.02195122 | AD29: =((AD17++AD20)-(AA17+AA20))/AA14 -> #DIV/0! | AE29: =((AE17++AE20)-(AB17+AB20))/AB14 -> -0.025052192 | AG29: =((AG17++AG20)-(AD17+AD20))/AD14 -> #DIV/0! | AH29: =((AH17++AH20)-(AE17+AE20))/AE14 -> -0.019677996 | AJ29: =((AJ17++AJ20)-(AG17+AG20))/AG14 -> #DIV/0! | AK29: =((AK17++AK20)-(AH17+AH20))/AH14 -> -0.064761905
A30: 内諾率 | B30: ＴＪＫ | F30: =((F18++F21)-(C18+C21))/C15 -> #DIV/0! | G30: =((G18++G21)-(D18+D21))/D15 -> #DIV/0! | I30: =((I18++I21)-(F18+F21))/F15 -> #DIV/0! | J30: =((J18++J21)-(G18+G21))/G15 -> #DIV/0! | L30: =((L18++L21)-(I18+I21))/I15 -> #DIV/0! | M30: =((M18++M21)-(J18+J21))/J15 -> #DIV/0! | O30: =((O18++O21)-(L18+L21))/L15 -> #DIV/0! | P30: =((P18++P21)-(M18+M21))/M15 -> 0.48 | R30: =((R18++R21)-(O18+O21))/O15 -> 0 | S30: =((S18++S21)-(P18+P21))/P15 -> 0.4 | U30: =((U18++U21)-(R18+R21))/R15 -> 0 | V30: =((V18++V21)-(S18+S21))/S15 -> -0.31818182 | X30: =((X18++X21)-(U18+U21))/U15 -> 0 | Y30: =((Y18++Y21)-(V18+V21))/V15 -> 0 | AA30: =((AA18++AA21)-(X18+X21))/X15 -> #DIV/0! | AB30: =((AB18++AB21)-(Y18+Y21))/Y15 -> 0.16666667 | AD30: =((AD18++AD21)-(AA18+AA21))/AA15 -> #DIV/0! | AE30: =((AE18++AE21)-(AB18+AB21))/AB15 -> 0.16666667 | AG30: =((AG18++AG21)-(AD18+AD21))/AD15 -> #DIV/0! | AH30: =((AH18++AH21)-(AE18+AE21))/AE15 -> -0.2 | AJ30: =((AJ18++AJ21)-(AG18+AG21))/AG15 -> #DIV/0! | AK30: =((AK18++AK21)-(AH18+AH21))/AH15 -> -0.8
A31: 内諾率 | B31: 社労士 | F31: =((F19++F22)-(C19+C22))/C16 -> #DIV/0! | G31: =((G19++G22)-(D19+D22))/D16 -> #DIV/0! | I31: =((I19++I22)-(F19+F22))/F16 -> #DIV/0! | J31: =((J19++J22)-(G19+G22))/G16 -> #DIV/0! | L31: =((L19++L22)-(I19+I22))/I16 -> #DIV/0! | M31: =((M19++M22)-(J19+J22))/J16 -> #DIV/0! | O31: =((O19++O22)-(L19+L22))/L16 -> #DIV/0! | P31: =((P19++P22)-(M19+M22))/M16 -> #DIV/0! | R31: =((R19++R22)-(O19+O22))/O16 -> #DIV/0! | S31: =((S19++S22)-(P19+P22))/P16 -> 0.5 | U31: =((U19++U22)-(R19+R22))/R16 -> #DIV/0! | V31: =((V19++V22)-(S19+S22))/S16 -> 0 | X31: =((X19++X22)-(U19+U22))/U16 -> #DIV/0! | Y31: =((Y19++Y22)-(V19+V22))/V16 -> 0.125 | AA31: =((AA19++AA22)-(X19+X22))/X16 -> #DIV/0! | AB31: =((AB19++AB22)-(Y19+Y22))/Y16 -> 0.090909091 | AD31: =((AD19++AD22)-(AA19+AA22))/AA16 -> #DIV/0! | AE31: =((AE19++AE22)-(AB19+AB22))/AB16 -> 0.076923077 | AG31: =((AG19++AG22)-(AD19+AD22))/AD16 -> #DIV/0! | AH31: =((AH19++AH22)-(AE19+AE22))/AE16 -> -0.2 | AJ31: =((AJ19++AJ22)-(AG19+AG22))/AG16 -> #DIV/0! | AK31: =((AK19++AK22)-(AH19+AH22))/AH16 -> -0.4
A32: 内諾率 | B32: その他 | F32: =((F20++F23)-(C20+C23))/C17 -> #DIV/0! | G32: =((G20++G23)-(D20+D23))/D17 -> #DIV/0! | I32: =((I20++I23)-(F20+F23))/F17 -> #DIV/0! | J32: =((J20++J23)-(G20+G23))/G17 -> #DIV/0! | L32: =((L20++L23)-(I20+I23))/I17 -> #DIV/0! | M32: =((M20++M23)-(J20+J23))/J17 -> #DIV/0! | O32: =((O20++O23)-(L20+L23))/L17 -> #DIV/0! | P32: =((P20++P23)-(M20+M23))/M17 -> #DIV/0! | R32: =((R20++R23)-(O20+O23))/O17 -> #DIV/0! | S32: =((S20++S23)-(P20+P23))/P17 -> 0.66666667 | U32: =((U20++U23)-(R20+R23))/R17 -> #DIV/0! | V32: =((V20++V23)-(S20+S23))/S17 -> 2.6666667 | X32: =((X20++X23)-(U20+U23))/U17 -> #DIV/0! | Y32: =((Y20++Y23)-(V20+V23))/V17 -> 0.10344828 | AA32: =((AA20++AA23)-(X20+X23))/X17 -> #DIV/0! | AB32: =((AB20++AB23)-(Y20+Y23))/Y17 -> 0.026315789 | AD32: =((AD20++AD23)-(AA20+AA23))/AA17 -> #DIV/0! | AE32: =((AE20++AE23)-(AB20+AB23))/AB17 -> 0 | AG32: =((AG20++AG23)-(AD20+AD23))/AD17 -> #DIV/0! | AH32: =((AH20++AH23)-(AE20+AE23))/AE17 -> -0.29411765 | AJ32: =((AJ20++AJ23)-(AG20+AG23))/AG17 -> #DIV/0! | AK32: =((AK20++AK23)-(AH20+AH23))/AH17 -> -0.11764706
A34: ステージ
A55: 転換率
B96: 以下、濱西メモ
C100: 1月 | F100: 2月 | I100: 3月 | L100: 4月 | O100: 5月 | R100: 6月 | U100: 7月 | X100: 8月 | AA100: 9月 | AD100: 10月 | AG100: 11月 | AJ100: 12月
C101: 実績 | D101: 企業名 | F101: 実績 | G101: 企業名 | I101: 実績 | J101: 企業名 | L101: 実績 | M101: 企業名 | O101: 実績 | P101: 企業名 | R101: 実績 | S101: 企業名 | U101: 実績 | V101: 企業名 | X101: 実績 | Y101: 企業名 | AA101: 実績 | AB101: 企業名 | AD101: 実績 | AE101: 企業名 | AG101: 実績 | AH101: 企業名 | AJ101: 実績 | AK101: 企業名
A102: 新規リード | B102: ＴＪＫ | C102: 0 | F102: 0 | I102: 3 | J102: 株式会社ヒロケイ、SASクラウド株式会社、株式会社エフエム・スタッフ | L102: 2 | M102: 株式会社岩井システムクリエイティブ、株式会社アドバンテッジリスクマネジメント | O102: 6 | P102: 株式会社ＮＸワンビシアーカイブズ、株式会社総研システムズ、株式会社アドヴァンスト・インフォーメイション・デザイン、ＪＦＥコムサービス株式会社、株式会社ニッポンダイナミックシステムズ、ラバブルマーケティンググループ | R102: 2 | S102: 日本郵政インフォメーションテクノロジー株式会社、 株式会社ＮＸワンビシアーカイブズ | U102: 1 | V102: 平成医会 | X102: 0 | AA102: 0 | AD102: 0 | AG102: 0 | AJ102: 0
A103: 新規リード | B103: 社労士 | C103: 2 | D103: ベリーベスト弁護士、ベリーベスト税理士 | F103: 2 | G103: DADWAY、オオヨドコーポレーション | I103: 1 | J103: ネイル協会 | L103: 0 | O103: 0 | R103: 0 | U103: 0 | X103: 0 | AA103: 0 | AD103: 0 | AG103: 0 | AJ103: 0
A104: 新規リード | B104: その他 | C104: 0 | F104: 0 | I104: 0 | L104: 0 | O104: 1 | P104: 土岐市立病院 | R104: 1 | U104: 0 | X104: 0 | AA104: 0 | AD104: 0 | AG104: 0 | AJ104: 0
A105: 有効ステージ | B105: ＴＪＫ | C105: 0 | F105: 0 | I105: 3 | J105: 株式会社ヒロケイ、SASクラウド株式会社、株式会社エフエム・スタッフ | L105: 3 | M105: 株式会社ヒロケイ、SASクラウド株式会社、株式会社アドバンテッジリスクマネジメント | O105: 3 | P105: 株式会社ヒロケイ、SASクラウド株式会社、株式会社アドバンテッジリスクマネジメント | R105: 3 | S105: 株式会社ヒロケイ、SASクラウド株式会社、株式会社アドバンテッジリスクマネジメント | U105: 3 | V105: 株式会社ヒロケイ、SASクラウド株式会社、株式会社アドバンテッジリスクマネジメント | X105: 0 | AA105: 0 | AD105: 0 | AG105: 0 | AJ105: 0
A106: 有効ステージ | B106: 社労士 | C106: 1 | D106: ベリーベスト弁護士 | F106: 1 | G106: ベリーベスト弁護士 | I106: 0 | L106: 0 | O106: 0 | R106: 0 | U106: 0 | X106: 0 | AA106: 0 | AD106: 0 | AG106: 0 | AJ106: 0
A107: 有効ステージ | B107: その他 | C107: 0 | F107: 0 | I107: 0 | L107: 0 | O107: 1 | P107: 土岐市立病院 | R107: 0 | U107: 1 | V107: 平成医会 | X107: 0 | AA107: 0 | AD107: 0 | AG107: 0 | AJ107: 0
A108: 断念ステージ | B108: ＴＪＫ | C108: 0 | F108: 0 | I108: 0 | L108: 1 | M108: 株式会社エフエム・スタッフ | O108: 0 | R108: 0 | U108: 0 | X108: 0 | AA108: 0 | AD108: 0 | AG108: 0 | AJ108: 0
A109: 断念ステージ | B109: 社労士 | C109: 0 | F109: 0 | I109: 1 | J109: ベリーベスト弁護士 | L109: 1 | M109: ベリーベスト弁護士 | O109: 1 | P109: ベリーベスト弁護士 | R109: 1 | S109: ベリーベスト弁護士 | U109: 1 | V109: ベリーベスト弁護士 | X109: 0 | AA109: 0 | AD109: 0 | AG109: 0 | AJ109: 0
A110: 断念ステージ | B110: その他 | C110: 0 | F110: 0 | I110: 0 | L110: 0 | O110: 0 | R110: 0 | U110: 0 | X110: 0 | AA110: 0 | AD110: 0 | AG110: 0 | AJ110: 0
A111: 商談ステージ | B111: ＴＪＫ | C111: 0 | F111: 0 | I111: 0 | L111: 1 | M111: 株式会社岩井システムクリエイティブ | O111: 2 | P111: 株式会社岩井システムクリエイティブ、株式会社総研システムズ | R111: 1 | S111: 日本郵政インフォメーションテクノロジー株式会社 | U111: 1 | V111: 日本郵政インフォメーションテクノロジー株式会社 | X111: 0 | AA111: 0 | AD111: 0 | AG111: 0 | AJ111: 0
A112: 商談ステージ | B112: 社労士 | C112: 1 | D112: ベリーベスト弁護士 | F112: 3 | G112: DADWAY、オオヨドコーポレーション、ベリーベスト弁護士 | I112: 3 | J112: DADWAY、オオヨドコーポレーション、ベリーベスト弁護士 | L112: 3 | M112: DADWAY、オオヨドコーポレーション、ベリーベスト弁護士 | O112: 3 | P112: DADWAY、オオヨドコーポレーション、ベリーベスト弁護士 | R112: 3 | S112: DADWAY、オオヨドコーポレーション、ベリーベスト弁護士 | U112: 4 | V112: DADWAY、オオヨドコーポレーション、ベリーベスト弁護士、平成医会 | X112: 0 | AA112: 0 | AD112: 0 | AG112: 0 | AJ112: 0
A113: 商談ステージ | B113: その他 | C113: 0 | F113: 0 | I113: 0 | L113: 0 | O113: 0 | R113: 1 | S113: 土岐市立病院 | U113: 1 | V113: 土岐市立病院 | X113: 0 | AA113: 0 | AD113: 0 | AG113: 0 | AJ113: 0
A114: 具体検討ステージ | B114: ＴＪＫ | C114: 0 | F114: 0 | I114: 0 | L114: 0 | O114: 1 | P114: ラバブルマーケティンググループ | R114: 3 | S114: 株式会社岩井システムクリエイティブ、株式会社総研システムズ、ラバブルマーケティンググループ | U114: 3 | V114: 株式会社岩井システムクリエイティブ、株式会社総研システムズ、ラバブルマーケティンググループ | X114: 0 | AA114: 0 | AD114: 0 | AG114: 0 | AJ114: 0
A115: 具体検討ステージ | B115: 社労士 | C115: 0 | F115: 0 | I115: 0 | L115: 0 | O115: 0 | R115: 0 | U115: 0 | X115: 0 | AA115: 0 | AD115: 0 | AG115: 0 | AJ115: 0
A116: 具体検討ステージ | B116: その他 | C116: 0 | F116: 0 | I116: 0 | L116: 0 | O116: 0 | R116: 0 | U116: 0 | X116: 0 | AA116: 0 | AD116: 0 | AG116: 0 | AJ116: 0
A117: 内諾ステージ | B117: ＴＪＫ | C117: 0 | F117: 0 | I117: 0 | L117: 0 | O117: 0 | R117: 0 | U117: 0 | X117: 0 | AA117: 0 | AD117: 0 | AG117: 0 | AJ117: 0
A118: 内諾ステージ | B118: 社労士 | C118: 0 | F118: 0 | I118: 0 | L118: 0 | O118: 0 | R118: 0 | U118: 0 | X118: 0 | AA118: 0 | AD118: 0 | AG118: 0 | AJ118: 0
A119: 内諾ステージ | B119: その他 | C119: 0 | F119: 0 | I119: 0 | L119: 0 | O119: 0 | R119: 0 | U119: 0 | X119: 0 | AA119: 0 | AD119: 0 | AG119: 0 | AJ119: 0
A120: 締結ステージ | B120: ＴＪＫ | C120: 0 | F120: 0 | I120: 0 | L120: 0 | O120: 0 | R120: 0 | U120: 0 | X120: 0 | AA120: 0 | AD120: 0 | AG120: 0 | AJ120: 0
A121: 締結ステージ | B121: 社労士 | C121: 0 | F121: 0 | I121: 0 | L121: 0 | O121: 0 | R121: 0 | U121: 0 | X121: 0 | AA121: 0 | AD121: 0 | AG121: 0 | AJ121: 0
A122: 締結ステージ | B122: その他 | C122: 0 | F122: 0 | I122: 0 | L122: 0 | O122: 1 | P122: 東濃ハウジング | R122: 1 | S122: 東濃ハウジング | U122: 1 | V122: 東濃ハウジング | X122: 0 | AA122: 0 | AD122: 0 | AG122: 0 | AJ122: 0
A127: 代理店 | B127: ＴＪＫ | C127: 1 | D127: TJKベネフィット | F127: 1 | G127: TJKベネフィット | I127: 1 | J127: TJKベネフィット | L127: 1 | M127: TJKベネフィット | O127: 1 | P127: TJKベネフィット | R127: 1 | S127: TJKベネフィット | U127: 1 | V127: TJKベネフィット | X127: 1 | Y127: TJKベネフィット
A128: 代理店 | B128: 社労士 | C128: 0 | F128: 0 | I128: 0 | L128: 0 | O128: 0 | R128: 1 | S128: レアホア | U128: 1 | V128: レアホア | X128: 2 | Y128: レアホア、KS経営労務コンサルタントオフィス（元港区社労士支部長）
A129: 代理店 | B129: その他 | C129: 2 | D129: 八神製作所、三菱地所PM | F129: 2 | G129: 八神製作所、三菱地所PM | I129: 2 | J129: 八神製作所、三菱地所PM | L129: 2 | M129: 八神製作所、三菱地所PM | O129: 2 | P129: 八神製作所、三菱地所PM | R129: 3 | S129: 八神製作所、三菱地所PM、ジャパン介護ラボラトリー | U129: 4 | V129: 八神製作所、三菱地所PM、ジャパン介護ラボラトリー、三千和商工 | X129: 8 | Y129: 八神製作所、三菱地所PM、ジャパン介護ラボラトリー、三千和商工、ウィルオブワーク、プレミアリサーチ株式会社、HIS、平成医会
U132: 新規リード | V132: 127 | Y132: 153 | AB132: 115 | AE132: 115 | AH132: 0
U133: 商談ステージ | V133: 295 | Y133: 410 | AB133: 479 | AE133: 559 | AH133: 525
U134: 具体検討ステージ | V134: 29 | Y134: 38 | AB134: 46 | AE134: 34 | AH134: 34
A135: その他計画 | U135: 内諾ステージ | V135: 8 | Y135: 10 | AB135: 11 | AE135: 11 | AH135: 0
C137: 1月 | F137: 2月 | I137: 3月 | L137: 4月 | O137: 5月 | R137: 6月 | U137: 7月 | X137: 8月 | AA137: 9月 | AD137: 10月 | AG137: 11月 | AJ137: 12月
C138: 実績 | D138: 計画 | F138: 実績 | G138: 計画 | I138: 実績 | J138: 計画 | L138: 実績 | M138: 計画 | O138: 実績 | P138: 計画 | R138: 実績 | S138: 計画 | U138: 実績 | V138: 計画 | X138: 実績 | Y138: 計画 | AA138: 実績 | AB138: 計画 | AD138: 実績 | AE138: 計画 | AG138: 実績 | AH138: 計画 | AJ138: 実績 | AK138: 計画
A139: 新規リード | B139: 八神製作所 | C139: 0 | D139: 0 | F139: 0 | G139: 0 | I139: 0 | J139: 0 | L139: 0 | M139: 0 | O139: 0 | P139: 0 | R139: 1 | S139: 0 | V139: =V132/20 -> 6.35 | Y139: =Y132/20 -> 7.65 | AB139: =AB132/20 -> 5.75 | AE139: =AE132/20 -> 5.75 | AH139: 0 | AK139: 0
A140: 新規リード | B140: ジャパン介護ラボラトリー | C140: 0 | D140: 0 | F140: 0 | G140: 0 | I140: 0 | J140: 0 | L140: 0 | M140: 0 | O140: 0 | P140: 0 | R140: 0 | S140: 0 | V140: =127/20 -> 6.35 | Y140: =Y132/20 -> 7.65 | AB140: =AB132/20 -> 5.75 | AE140: =AE132/20 -> 5.75 | AH140: 0 | AK140: 0
A141: 新規リード | B141: 平成医会 | C141: 0 | D141: 0 | F141: 0 | G141: 0 | I141: 0 | J141: 0 | L141: 0 | M141: 0 | O141: 0 | P141: 0 | R141: 0 | S141: 0 | V141: =127/5 -> 25.4 | Y141: =Y132/5 -> 30.6 | AB141: =AB132/5 -> 23 | AE141: =AE132/5 -> 23
A142: 新規リード | B142: ココログループ | C142: 0 | D142: 0 | F142: 0 | G142: 0 | I142: 0 | J142: 0 | L142: 0 | M142: 0 | O142: 0 | P142: 0 | R142: 0 | S142: 0 | V142: =127/10 -> 12.7 | Y142: =Y132/10 -> 15.3 | AB142: =AB132/10 -> 11.5 | AE142: =AE132/10 -> 11.5
A143: 新規リード | B143: ウィルオブワーク | C143: 0 | D143: 0 | F143: 0 | G143: 0 | I143: 0 | J143: 0 | L143: 0 | M143: 0 | O143: 0 | P143: 0 | R143: 0 | S143: 0 | V143: =127*2/5 -> 50.8 | Y143: =Y132*2/5 -> 61.2 | AB143: =AB132*2/5 -> 46 | AE143: =AE132*2/5 -> 46
A144: 新規リード | B144: HIS | C144: 0 | D144: 0 | F144: 0 | G144: 0 | I144: 0 | J144: 0 | L144: 0 | M144: 0 | O144: 0 | P144: 0 | R144: 0 | S144: 0 | V144: =127/10 -> 12.7 | Y144: =Y132/10 -> 15.3 | AB144: =AB132/10 -> 11.5 | AE144: =AE132/10 -> 11.5
A145: 新規リード | B145: 三千和商工 | C145: 0 | D145: 0 | F145: 0 | G145: 0 | I145: 0 | J145: 0 | L145: 0 | M145: 0 | O145: 0 | P145: 0 | R145: 0 | S145: 0 | V145: =127/10 -> 12.7 | Y145: =Y132/10 -> 15.3 | AB145: =AB132/10 -> 11.5 | AE145: =AE132/10 -> 11.5 | AH145: 0 | AK145: 0
A146: 有効ステージ
A147: 有効ステージ
A148: 有効ステージ
A149: 断念ステージ
A150: 断念ステージ
A151: 断念ステージ
A152: 商談ステージ | B152: 八神製作所 | C152: 0 | D152: 0 | F152: 0 | G152: 0 | I152: 0 | J152: 0 | L152: 0 | M152: 0 | O152: 0 | P152: 0 | R152: 0 | S152: 0 | V152: =V133/20 -> 14.75 | Y152: =Y133/20 -> 20.5 | AB152: =AB133/20 -> 23.95 | AE152: =AE133/20 -> 27.95 | AH152: =AH133/20 -> 26.25 | AK152: 0
A153: 商談ステージ | B153: ジャパン介護ラボラトリー | C153: 0 | D153: 0 | F153: 0 | G153: 0 | I153: 0 | J153: 0 | L153: 0 | M153: 0 | O153: 0 | P153: 0 | R153: 0 | S153: 0 | V153: =V133/20 -> 14.75 | Y153: =Y133/20 -> 20.5 | AB153: =AB133/20 -> 23.95 | AE153: =AE133/20 -> 27.95 | AH153: =AH133/20 -> 26.25
A154: 商談ステージ | B154: 平成医会 | C154: 0 | D154: 0 | F154: 0 | G154: 0 | I154: 0 | J154: 0 | L154: 0 | M154: 0 | O154: 0 | P154: 0 | R154: 0 | S154: 0 | V154: =V133/5 -> 59 | Y154: =Y133/5 -> 82 | AB154: =AB133/5 -> 95.8 | AE154: =AE133/5 -> 111.8 | AH154: =AH133/5 -> 105
A155: 商談ステージ | B155: ココログループ | C155: 0 | D155: 0 | F155: 0 | G155: 0 | I155: 0 | J155: 0 | L155: 0 | M155: 0 | O155: 0 | P155: 0 | R155: 0 | S155: 0 | V155: =V133/10 -> 29.5 | Y155: =Y133/10 -> 41 | AB155: =AB133/10 -> 47.9 | AE155: =AE133/10 -> 55.9 | AH155: =AH133/10 -> 52.5
A156: 商談ステージ | B156: ウィルオブワーク | C156: 0 | D156: 0 | F156: 0 | G156: 0 | I156: 0 | J156: 0 | L156: 0 | M156: 0 | O156: 0 | P156: 0 | R156: 0 | S156: 0 | V156: =V133*2/5 -> 118 | Y156: =Y133*2/5 -> 164 | AB156: =AB133*2/5 -> 191.6 | AE156: =AE133*2/5 -> 223.6 | AH156: =AH133*2/5 -> 210 | AK156: 0
A157: 商談ステージ | B157: HIS | C157: 0 | D157: 0 | F157: 0 | G157: 0 | I157: 0 | J157: 0 | L157: 0 | M157: 0 | O157: 0 | P157: 0 | R157: 0 | S157: 0 | V157: =V133/10 -> 29.5 | Y157: =Y133/10 -> 41 | AB157: =AB133/10 -> 47.9 | AE157: =AE133/10 -> 55.9 | AH157: =AH133/10 -> 52.5
A158: 商談ステージ | B158: 三千和商工 | C158: 0 | D158: 0 | F158: 0 | G158: 0 | I158: 0 | J158: 0 | L158: 0 | M158: 0 | O158: 0 | P158: 0 | R158: 0 | S158: 0 | V158: =V133/10 -> 29.5 | Y158: =Y133/10 -> 41 | AB158: =AB133/10 -> 47.9 | AE158: =AE133/10 -> 55.9 | AH158: =AH133/10 -> 52.5 | AK158: 0
A159: 具体検討ステージ | B159: 八神製作所 | C159: 0 | D159: 0 | F159: 0 | G159: 0 | I159: 0 | J159: 0 | L159: 0 | M159: 0 | O159: 0 | P159: 0 | R159: 0 | S159: 0 | V159: =V134/20 -> 1.45 | Y159: =Y134/20 -> 1.9 | AB159: =AB134/20 -> 2.3 | AE159: =AE134/20 -> 1.7 | AH159: =AH134/20 -> 1.7 | AK159: 0
A160: 具体検討ステージ | B160: ジャパン介護ラボラトリー | C160: 0 | D160: 0 | F160: 0 | G160: 0 | I160: 0 | J160: 0 | L160: 0 | M160: 0 | O160: 0 | P160: 0 | R160: 0 | S160: 0 | V160: =V134/20 -> 1.45 | Y160: =Y134/20 -> 1.9 | AB160: =AB134/20 -> 2.3 | AE160: =AE134/20 -> 1.7 | AH160: =AH134/20 -> 1.7
A161: 具体検討ステージ | B161: 平成医会 | C161: 0 | D161: 0 | F161: 0 | G161: 0 | I161: 0 | J161: 0 | L161: 0 | M161: 0 | O161: 0 | P161: 0 | R161: 0 | S161: 0 | V161: =V134/5 -> 5.8 | Y161: =Y134/5 -> 7.6 | AB161: =AB134/5 -> 9.2 | AE161: =AE134/5 -> 6.8 | AH161: =AH134/5 -> 6.8
A162: 具体検討ステージ | B162: ココログループ | C162: 0 | D162: 0 | F162: 0 | G162: 0 | I162: 0 | J162: 0 | L162: 0 | M162: 0 | O162: 0 | P162: 0 | R162: 0 | S162: 0 | V162: =V134/10 -> 2.9 | Y162: =Y134/10 -> 3.8 | AB162: =AB134/10 -> 4.6 | AE162: =AE134/10 -> 3.4 | AH162: =AH134/10 -> 3.4
A163: 具体検討ステージ | B163: ウィルオブワーク | C163: 0 | D163: 0 | F163: 0 | G163: 0 | I163: 0 | J163: 0 | L163: 0 | M163: 0 | O163: 0 | P163: 0 | R163: 0 | S163: 0 | V163: =V134*2/5 -> 11.6 | Y163: =Y134*2/5 -> 15.2 | AB163: =AB134*2/5 -> 18.4 | AE163: =AE134*2/5 -> 13.6 | AH163: =AH134*2/5 -> 13.6
A164: 具体検討ステージ | B164: HIS | C164: 0 | D164: 0 | F164: 0 | G164: 0 | I164: 0 | J164: 0 | L164: 0 | M164: 0 | O164: 0 | P164: 0 | R164: 0 | S164: 0 | V164: =V134/10 -> 2.9 | Y164: =Y134/10 -> 3.8 | AB164: =AB134/10 -> 4.6 | AE164: =AE134/10 -> 3.4 | AH164: =AH134/10 -> 3.4
A165: 具体検討ステージ | B165: 三千和商工 | C165: 0 | D165: 0 | F165: 0 | G165: 0 | I165: 0 | J165: 0 | L165: 0 | M165: 0 | O165: 0 | P165: 0 | R165: 0 | S165: 0 | V165: =V134/10 -> 2.9 | Y165: =Y134/10 -> 3.8 | AB165: =AB134/10 -> 4.6 | AE165: =AE134/10 -> 3.4 | AH165: =AH134/10 -> 3.4 | AK165: 0
A166: 内諾ステージ | B166: 八神製作所 | C166: 0 | D166: 0 | F166: 0 | G166: 0 | I166: 0 | J166: 0 | L166: 0 | M166: 0 | O166: 0 | P166: 0 | R166: 0 | S166: 0 | V166: =V135/20 -> 0.4 | Y166: =Y135/20 -> 0.5 | AB166: =AB135/20 -> 0.55 | AE166: =AE135/20 -> 0.55 | AH166: =AH135/20 -> 0 | AJ166: =AK172/20 -> 0 | AK166: 0
A167: 内諾ステージ | B167: ジャパン介護ラボラトリー | C167: 0 | D167: 0 | F167: 0 | G167: 0 | I167: 0 | J167: 0 | L167: 0 | M167: 0 | O167: 0 | P167: 0 | R167: 0 | S167: 0 | V167: =V135/20 -> 0.4 | Y167: =Y135/20 -> 0.5 | AB167: =AB135/20 -> 0.55 | AE167: =AE135/20 -> 0.55 | AH167: =AH135/20 -> 0 | AJ167: =AK172/20 -> 0
A168: 内諾ステージ | B168: 平成医会 | C168: 0 | D168: 0 | F168: 0 | G168: 0 | I168: 0 | J168: 0 | L168: 0 | M168: 0 | O168: 0 | P168: 0 | R168: 0 | S168: 0 | V168: =V135/5 -> 1.6 | Y168: =Y135/5 -> 2 | AB168: =AB135/5 -> 2.2 | AE168: =AE135/5 -> 2.2 | AH168: =AH135/5 -> 0 | AJ168: =AK172/5 -> 0
A169: 内諾ステージ | B169: ココログループ | C169: 0 | D169: 0 | F169: 0 | G169: 0 | I169: 0 | J169: 0 | L169: 0 | M169: 0 | O169: 0 | P169: 0 | R169: 0 | S169: 0 | V169: =V135/10 -> 0.8 | Y169: =Y135/10 -> 1 | AB169: =AB135/10 -> 1.1 | AE169: =AE135/10 -> 1.1 | AH169: =AH135/10 -> 0 | AJ169: =AK172/10 -> 0
A170: 内諾ステージ | B170: ウィルオブワーク | C170: 0 | D170: 0 | F170: 0 | G170: 0 | I170: 0 | J170: 0 | L170: 0 | M170: 0 | O170: 0 | P170: 0 | R170: 0 | S170: 0 | V170: =V135*2/5 -> 3.2 | Y170: =Y135*2/5 -> 4 | AB170: =AB135*2/5 -> 4.4 | AE170: =AE135*2/5 -> 4.4 | AH170: =AH135*2/5 -> 0 | AJ170: =AK172*2/5 -> 0
A171: 内諾ステージ | B171: HIS | C171: 0 | D171: 0 | F171: 0 | G171: 0 | I171: 0 | J171: 0 | L171: 0 | M171: 0 | O171: 0 | P171: 0 | R171: 0 | S171: 0 | V171: =V135/10 -> 0.8 | Y171: =Y135/10 -> 1 | AB171: =AB135/10 -> 1.1 | AE171: =AE135/10 -> 1.1 | AH171: =AH135/10 -> 0 | AJ171: =AK172/10 -> 0 | AK171: 0
A172: 内諾ステージ | B172: 三千和商工 | C172: 0 | D172: 0 | F172: 0 | G172: 0 | I172: 0 | J172: 0 | L172: 0 | M172: 0 | O172: 0 | P172: 0 | R172: 0 | S172: 0 | V172: =V135/10 -> 0.8 | Y172: =Y135/10 -> 1 | AB172: =AB135/10 -> 1.1 | AE172: =AE135/10 -> 1.1 | AH172: =AH135/10 -> 0 | AJ172: =AK172/10 -> 0 | AK172: 0
A173: 締結ステージ
A174: 締結ステージ
A175: 締結ステージ
C177: 1月 | F177: 2月 | I177: 3月 | L177: 4月 | O177: 5月 | R177: 6月 | U177: 7月 | X177: 8月 | AA177: 9月 | AD177: 10月 | AG177: 11月 | AJ177: 12月
C178: 実績 | D178: 計画 | F178: 実績 | G178: 計画 | I178: 実績 | J178: 計画 | L178: 実績 | M178: 計画 | O178: 実績 | P178: 計画 | R178: 実績 | S178: 計画 | U178: 実績 | V178: 計画 | X178: 実績 | Y178: 計画 | AA178: 実績 | AB178: 計画 | AD178: 実績 | AE178: 計画 | AG178: 実績 | AH178: 計画 | AJ178: 実績 | AK178: 計画
A179: 具体検討化率 | B179: ＴＪＫ | F179: =((F159++F166)-(C159+C166))/C152 -> #DIV/0! | G179: =((G159++G166)-(D159+D166))/D152 -> #DIV/0! | I179: =((I159++I166)-(F159+F166))/F152 -> #DIV/0! | J179: =((J159++J166)-(G159+G166))/G152 -> #DIV/0! | L179: =((L159++L166)-(I159+I166))/I152 -> #DIV/0! | M179: =((M159++M166)-(J159+J166))/J152 -> #DIV/0! | O179: =((O159++O166)-(L159+L166))/L152 -> #DIV/0! | P179: =((P159++P166)-(M159+M166))/M152 -> #DIV/0! | R179: =((R159++R166)-(O159+O166))/O152 -> #DIV/0! | S179: =((S159++S166)-(P159+P166))/P152 -> #DIV/0! | U179: =((U159++U166)-(R159+R166))/R152 -> #DIV/0! | V179: =((V159++V166)-(S159+S166))/S152 -> #DIV/0! | X179: =((X159++X166)-(U159+U166))/U152 -> #DIV/0! | Y179: =((Y159++Y166)-(V159+V166))/V152 -> 0.037288136 | AA179: =((AA159++AA166)-(X159+X166))/X152 -> #DIV/0! | AB179: =((AB159++AB166)-(Y159+Y166))/Y152 -> 0.02195122 | AD179: =((AD159++AD166)-(AA159+AA166))/AA152 -> #DIV/0! | AE179: =((AE159++AE166)-(AB159+AB166))/AB152 -> -0.025052192 | AG179: =((AG159++AG166)-(AD159+AD166))/AD152 -> #DIV/0! | AH179: =((AH159++AH166)-(AE159+AE166))/AE152 -> -0.019677996 | AJ179: =((AJ159++AJ166)-(AG159+AG166))/AG152 -> #DIV/0! | AK179: =((AK159++AK166)-(AH159+AH166))/AH152 -> -0.064761905
A180: 具体検討化率 | B180: 社労士 | F180: =((F165++F171)-(C165+C171))/C156 -> #DIV/0! | G180: =((G165++G171)-(D165+D171))/D156 -> #DIV/0! | I180: =((I165++I171)-(F165+F171))/F156 -> #DIV/0! | J180: =((J165++J171)-(G165+G171))/G156 -> #DIV/0! | L180: =((L165++L171)-(I165+I171))/I156 -> #DIV/0! | M180: =((M165++M171)-(J165+J171))/J156 -> #DIV/0! | O180: =((O165++O171)-(L165+L171))/L156 -> #DIV/0! | P180: =((P165++P171)-(M165+M171))/M156 -> #DIV/0! | R180: =((R165++R171)-(O165+O171))/O156 -> #DIV/0! | S180: =((S165++S171)-(P165+P171))/P156 -> #DIV/0! | U180: =((U165++U171)-(R165+R171))/R156 -> #DIV/0! | V180: =((V165++V171)-(S165+S171))/S156 -> #DIV/0! | X180: =((X165++X171)-(U165+U171))/U156 -> #DIV/0! | Y180: =((Y165++Y171)-(V165+V171))/V156 -> 0.0093220339 | AA180: =((AA165++AA171)-(X165+X171))/X156 -> #DIV/0! | AB180: =((AB165++AB171)-(Y165+Y171))/Y156 -> 0.0054878049 | AD180: =((AD165++AD171)-(AA165+AA171))/AA156 -> #DIV/0! | AE180: =((AE165++AE171)-(AB165+AB171))/AB156 -> -0.006263048 | AG180: =((AG165++AG171)-(AD165+AD171))/AD156 -> #DIV/0! | AH180: =((AH165++AH171)-(AE165+AE171))/AE156 -> -0.0049194991 | AJ180: =((AJ165++AJ171)-(AG165+AG171))/AG156 -> #DIV/0! | AK180: =((AK165++AK171)-(AH165+AH171))/AH156 -> -0.016190476
A181: 具体検討化率 | B181: その他 | F181: =((#REF!++F172)-(#REF!+C172))/C158 -> #REF! | G181: =((#REF!++G172)-(#REF!+D172))/D158 -> #REF! | I181: =((#REF!++I172)-(#REF!+F172))/F158 -> #REF! | J181: =((#REF!++J172)-(#REF!+G172))/G158 -> #REF! | L181: =((#REF!++L172)-(#REF!+I172))/I158 -> #REF! | M181: =((#REF!++M172)-(#REF!+J172))/J158 -> #REF! | O181: =((#REF!++O172)-(#REF!+L172))/L158 -> #REF! | P181: =((#REF!++P172)-(#REF!+M172))/M158 -> #REF! | R181: =((#REF!++R172)-(#REF!+O172))/O158 -> #REF! | S181: =((#REF!++S172)-(#REF!+P172))/P158 -> #REF! | U181: =((#REF!++U172)-(#REF!+R172))/R158 -> #REF! | V181: =((#REF!++V172)-(#REF!+S172))/S158 -> #REF! | X181: =((#REF!++X172)-(#REF!+U172))/U158 -> #REF! | Y181: =((#REF!++Y172)-(#REF!+V172))/V158 -> #REF! | AA181: =((#REF!++AA172)-(#REF!+X172))/X158 -> #REF! | AB181: =((#REF!++AB172)-(#REF!+Y172))/Y158 -> #REF! | AD181: =((#REF!++AD172)-(#REF!+AA172))/AA158 -> #REF! | AE181: =((#REF!++AE172)-(#REF!+AB172))/AB158 -> #REF! | AG181: =((#REF!++AG172)-(#REF!+AD172))/AD158 -> #REF! | AH181: =((#REF!++AH172)-(#REF!+AE172))/AE158 -> #REF! | AJ181: =((#REF!++AJ172)-(#REF!+AG172))/AG158 -> #REF! | AK181: =((#REF!++AK172)-(#REF!+AH172))/AH158 -> #REF!
...

Sheet 25年PDCA
A1: 計画差 | B1: 計画差 | C1: 計画差 | D1: 計画差 | E1: 計画差 | F1: 計画差 | G1: 計画差 | H1: 計画差 | I1: 計画差 | J1: 計画差 | K1: 計画差 | L1: 計画差 | M1: 計画差 | N1: 計画差 | O1: 計画差 | S1: 計画比 | T1: 計画比 | U1: 計画比 | V1: 計画比 | W1: 計画比 | X1: 計画比 | Y1: 計画比 | Z1: 計画比 | AA1: 計画比 | AB1: 計画比 | AC1: 計画比 | AD1: 計画比 | AE1: 計画比 | AF1: 計画比 | AG1: 計画比 | AK1: 実績 | AL1: 実績 | AM1: 実績 | AN1: 実績 | AO1: 実績 | AP1: 実績 | AQ1: 実績 | AR1: 実績 | AS1: 実績 | AT1: 実績 | AU1: 実績 | AV1: 実績 | AW1: 実績 | AX1: 実績 | AY1: 実績 | BC1: 予算 | BD1: 予算 | BE1: 予算 | BF1: 予算 | BG1: 予算 | BH1: 予算 | BI1: 予算 | BJ1: 予算 | BK1: 予算 | BL1: 予算 | BM1: 予算 | BN1: 予算 | BO1: 予算 | BP1: 予算 | BQ1: 予算 | BZ1: 24実績 | CA1: 24実績 | CB1: 24実績 | CC1: 24実績 | CD1: 24実績 | CE1: 24実績 | CF1: 24実績 | CG1: 24実績 | CH1: 24実績 | CI1: 24実績 | CJ1: 24実績 | CK1: 24実績
C2: =IF(C4=$P4,1,0) -> 0 | D2: =IF(D4=$P4,1,0) -> 0 | E2: =IF(E4=$P4,1,0) -> 0 | F2: =IF(F4=$P4,1,0) -> 0 | G2: =IF(G4=$P4,1,0) -> 0 | H2: =IF(H4=$P4,1,0) -> 0 | I2: =IF(I4=$P4,1,0) -> 1 | J2: =IF(J4=$P4,1,0) -> 0 | ... N2: =IF(N4=$P4,1,0) -> 0 | U2: =IF(U4=$AH4,1,0) -> 0 | V2: =IF(V4=$AH4,1,0) -> 0 | W2: =IF(W4=$AH4,1,0) -> 0 | X2: =IF(X4=$AH4,1,0) -> 0 | Y2: =IF(Y4=$AH4,1,0) -> 0 | Z2: =IF(Z4=$AH4,1,0) -> 0 | AA2: =IF(AA4=$AH4,1,0) -> 1 | AB2: =IF(AB4=$AH4,1,0) -> 0 | ... AF2: =IF(AF4=$AH4,1,0) -> 0 | AM2: =IF(AM4=$AZ4,1,0) -> 0 | AN2: =IF(AN4=$AZ4,1,0) -> 0 | AO2: =IF(AO4=$AZ4,1,0) -> 0 | AP2: =IF(AP4=$AZ4,1,0) -> 0 | AQ2: =IF(AQ4=$AZ4,1,0) -> 0 | AR2: =IF(AR4=$AZ4,1,0) -> 0 | AS2: =IF(AS4=$AZ4,1,0) -> 1 | AT2: =IF(AT4=$AZ4,1,0) -> 0 | ... AX2: =IF(AX4=$AZ4,1,0) -> 0 | BE2: =IF(BE4=$BR4,1,0) -> 0 | BF2: =IF(BF4=$BR4,1,0) -> 0 | BG2: =IF(BG4=$BR4,1,0) -> 0 | BH2: =IF(BH4=$BR4,1,0) -> 0 | BI2: =IF(BI4=$BR4,1,0) -> 0 | BJ2: =IF(BJ4=$BR4,1,0) -> 0 | BK2: =IF(BK4=$BR4,1,0) -> 1 | BL2: =IF(BL4=$BR4,1,0) -> 0 | ... BQ2: =IF(BQ4=$BR4,1,0) -> 0 | BZ2: =IF(BZ4=$AZ4,1,0) -> 0 | CA2: =IF(CA4=$AZ4,1,0) -> 0 | CB2: =IF(CB4=$AZ4,1,0) -> 0 | CC2: =IF(CC4=$AZ4,1,0) -> 0 | CD2: =IF(CD4=$AZ4,1,0) -> 0 | CE2: 1 | CF2: 0 | CG2: =IF(CG4=$AZ4,1,0) -> 0 | CH2: =IF(CH4=$AZ4,1,0) -> 0 | CI2: =IF(CI4=$AZ4,1,0) -> 0 | CJ2: =IF(CJ4=$AZ4,1,0) -> 0 | CK2: =IF(CK4=$AZ4,1,0) -> 0
C3: =IF(C4<=$P4,1,0) -> 1 | D3: =IF(D4<=$P4,1,0) -> 1 | E3: =IF(E4<=$P4,1,0) -> 1 | F3: =IF(F4<=$P4,1,0) -> 1 | G3: =IF(G4<=$P4,1,0) -> 1 | H3: =IF(H4<=$P4,1,0) -> 1 | I3: =IF(I4<=$P4,1,0) -> 1 | J3: =IF(J4<=$P4,1,0) -> 0 | ... N3: =IF(N4<=$P4,1,0) -> 0 | U3: =IF(U4<=$AH4,1,0) -> 1 | V3: =IF(V4<=$AH4,1,0) -> 1 | W3: =IF(W4<=$AH4,1,0) -> 1 | X3: =IF(X4<=$AH4,1,0) -> 1 | Y3: =IF(Y4<=$AH4,1,0) -> 1 | Z3: =IF(Z4<=$AH4,1,0) -> 1 | AA3: =IF(AA4<=$AH4,1,0) -> 1 | AB3: =IF(AB4<=$AH4,1,0) -> 0 | ... AF3: =IF(AF4<=$AH4,1,0) -> 0 | AM3: =IF(AM4<=$AZ4,1,0) -> 1 | AN3: =IF(AN4<=$AZ4,1,0) -> 1 | AO3: =IF(AO4<=$AZ4,1,0) -> 1 | AP3: =IF(AP4<=$AZ4,1,0) -> 1 | AQ3: =IF(AQ4<=$AZ4,1,0) -> 1 | AR3: =IF(AR4<=$AZ4,1,0) -> 1 | AS3: =IF(AS4<=$AZ4,1,0) -> 1 | AT3: =IF(AT4<=$AZ4,1,0) -> 0 | ... AX3: =IF(AX4<=$AZ4,1,0) -> 0 | BE3: =IF(BE4<=$BR4,1,0) -> 1 | BF3: =IF(BF4<=$BR4,1,0) -> 1 | BG3: =IF(BG4<=$BR4,1,0) -> 1 | BH3: =IF(BH4<=$BR4,1,0) -> 1 | BI3: =IF(BI4<=$BR4,1,0) -> 1 | BJ3: =IF(BJ4<=$BR4,1,0) -> 1 | BK3: =IF(BK4<=$BR4,1,0) -> 1 | BL3: =IF(BL4<=$BR4,1,0) -> 0 | ... BQ3: =IF(BQ4<=$BR4,1,0) -> 0 | BZ3: =IF(BZ4<=$AZ4,1,0) -> 1 | CA3: =IF(CA4<=$AZ4,1,0) -> 1 | CB3: =IF(CB4<=$AZ4,1,0) -> 1 | CC3: =IF(CC4<=$AZ4,1,0) -> 1 | CD3: =IF(CD4<=$AZ4,1,0) -> 1 | CE3: =IF(CE4<=$AZ4,1,0) -> 1 | CF3: 0 | CG3: =IF(CG4<=$AZ4,1,0) -> 0 | CH3: =IF(CH4<=$AZ4,1,0) -> 0 | CI3: =IF(CI4<=$AZ4,1,0) -> 0 | CJ3: =IF(CJ4<=$AZ4,1,0) -> 0 | CK3: =IF(CK4<=$AZ4,1,0) -> 0
A4: 売上高 | C4: 1 | D4: 2 | E4: 3 | F4: 4 | G4: 5 | H4: 6 | I4: 7 | J4: 8 | K4: 9 | L4: 10 | M4: 11 | N4: 12 | O4: 合計 | P4: =サマリ!$A$1 -> 7 | Q4: =サマリ!$A$1 -> 7 | S4: 売上高 | U4: 1 | V4: 2 | W4: 3 | X4: 4 | Y4: 5 | Z4: 6 | AA4: 7 | AB4: 8 | AC4: 9 | AD4: 10 | AE4: 11 | AF4: 12 | AG4: 合計 | AH4: =サマリ!$A$1 -> 7 | AI4: =サマリ!$A$1 -> 7 | AK4: 売上高 | AM4: 1 | AN4: 2 | AO4: 3 | AP4: 4 | AQ4: 5 | AR4: 6 | AS4: 7 | AT4: 8 | AU4: 9 | AV4: 10 | AW4: 11 | AX4: 12 | AY4: 合計 | AZ4: =サマリ!$A$1 -> 7 | BA4: =サマリ!$A$1 -> 7 | BC4: 売上高 | BE4: 1 | BF4: 2 | BG4: 3 | BH4: 4 | BI4: 5 | BJ4: 6 | BK4: 7 | BL4: 8 | BM4: 9 | BN4: 10 | BO4: 11 | BP4: 12 | BQ4: 合計 | BR4: =サマリ!$A$1 -> 7 | BS4: =サマリ!$A$1 -> 7 | BT4: 24年実績 | BU4: ２５-24年差分 | BV4: 25年販売構成比 | BX4: 24年 | BZ4: 1 | CA4: 2 | CB4: 3 | CC4: 4 | CD4: 5 | CE4: 6 | CF4: 7 | CG4: 8 | CH4: 9 | CI4: 10 | CJ4: 11 | CK4: 12 | CL4: 合計 | CM4: =サマリ!$A$1 -> 7 | CN4: =サマリ!$A$1 -> 7 | CP4: 累月前年比 | CQ4: 単月前年比
A5: 新規（WEB） | B5: アプリ | C5: =AM5-BE5 -> 0 | D5: =AN5-BF5 -> 0 | E5: =AO5-BG5 -> 0 | F5: =AP5-BH5 -> 0 | G5: =AQ5-BI5 -> 0 | H5: =AR5-BJ5 -> 0 | I5: =AS5-BK5 -> -1995 | J5: =AT5-BL5 -> -3420 | ... O5: =AY5-BQ5 -> -36480 | S5: 新規（WEB） | T5: アプリ | U5: =AM5/BE5 -> #DIV/0! | V5: =AN5/BF5 -> #DIV/0! | W5: =AO5/BG5 -> #DIV/0! | X5: =AP5/BH5 -> #DIV/0! | Y5: =AQ5/BI5 -> #DIV/0! | Z5: =AR5/BJ5 -> #DIV/0! | AA5: =AS5/BK5 -> 0 | AB5: =AT5/BL5 -> 0 | ... AG5: =AY5/BQ5 -> 0 | AK5: 新規（WEB） | AL5: アプリ | AM5: 0 | AN5: 0 | AO5: 0 | AP5: 0 | AQ5: 0 | AR5: 0 | AS5: 0 | AY5: =SUM(AM5:AX5) -> 0 | AZ5: =SUMIF(AM$3:AX$3,1,AM5:AX5) -> 0 | BA5: =SUMIF(AN$2:AY$2,1,AN5:AY5) -> 0 | BC5: 新規（WEB） | BD5: アプリ | BE5: =BE38*BE66 -> 0 | BF5: =BF38*BF66 -> 0 | BG5: =BG38*BG66 -> 0 | BH5: =BH38*BH66 -> 0 | BI5: =BI38*BI66 -> 0 | BJ5: =BJ38*BJ66 -> 0 | BK5: =BK38*BK66 -> 1995 | BL5: =BL38*BL66 -> 3420 | ... BP5: =BP38*BP66 -> 10830 | BQ5: =SUM(BE5:BP5) -> 36480 | BR5: =SUMIF(BE$3:BP$3,1,BE5:BP5) -> 1995 | BS5: =SUMIF(BF$2:BQ$2,1,BF5:BQ5) -> 1995 | BX5: 新規（WEB） | BY5: アプリ | BZ5: 0 | CA5: 0 | CB5: 0 | CC5: 0 | CD5: 0 | CE5: 0 | CF5: 0 | CG5: 0 | CH5: 0 | CI5: 0 | CJ5: 0 | CK5: 0 | CL5: =SUM(BZ5:CK5) -> 0 | CM5: =SUMIF(BZ$3:CK$3,1,BZ5:CK5) -> 0 | CN5: =SUMIF(BZ$2:CK$2,1,BZ5:CK5) -> 0 | CP5: =AZ5/CM5 -> #DIV/0! | CQ5: =BA5/CN5 -> #DIV/0!
A6: 新規（WEB） | B6: スタンド（宅急便） | C6: =AM6-BE6 -> 96.167 | D6: =AN6-BF6 -> -19.739 | E6: =AO6-BG6 -> -64.954 | F6: =AP6-BH6 -> -38.961 | G6: =AQ6-BI6 -> -181.893 | H6: =AR6-BJ6 -> -397.581 | I6: =AS6-BK6 -> -701.633 | J6: =AT6-BL6 -> -1075.86 | ... O6: =AY6-BQ6 -> -9520.992 | S6: 新規（WEB） | T6: スタンド（宅急便） | U6: =AM6/BE6 -> 2.3407925 | V6: =AN6/BF6 -> 0.86239613 | W6: =AO6/BG6 -> 0.69812987 | X6: =AP6/BH6 -> 0.84479792 | Y6: =AQ6/BI6 -> 0.49279739 | Z6: =AR6/BJ6 -> 0.34785797 | AA6: =AS6/BK6 -> 0.18479983 | AB6: =AT6/BL6 -> 0 | ... AG6: =AY6/BQ6 -> 0.11207455 | AK6: 新規（WEB） | AL6: スタンド（宅急便） ※電子M除く | AM6: 167.891 | AN6: 123.709 | AO6: 150.218 | AP6: 212.073 | AQ6: 176.727 | AR6: 212.073 | AS6: 159.055 | AY6: =SUM(AM6:AX6) -> 1201.746 | AZ6: =SUMIF(AM$3:AX$3,1,AM6:AX6) -> 1201.746 | BA6: =SUMIF(AN$2:AY$2,1,AN6:AY6) -> 159.055 | BC6: 新規（WEB） | BD6: スタンド（宅急便） | BE6: =BE39*BE67 -> 71.724 | BF6: =BF39*BF67 -> 143.448 | BG6: =BG39*BG67 -> 215.172 | BH6: =BH39*BH67 -> 251.034 | BI6: =BI39*BI67 -> 358.62 | BJ6: =BJ39*BJ67 -> 609.654 | BK6: =BK39*BK67 -> 860.688 | BL6: =BL39*BL67 -> 1075.86 | ... BP6: =BP39*BP67 -> 2331.03 | BQ6: =SUM(BE6:BP6) -> 10722.738 | BR6: =SUMIF(BE$3:BP$3,1,BE6:BP6) -> 2510.34 | BS6: =SUMIF(BF$2:BQ$2,1,BF6:BQ6) -> 860.688 | BX6: 新規（WEB） | BY6: スタンド（宅急便） | BZ6: 2236.0282 | CA6: 2091.7473 | CB6: 2086.44 | CC6: 2278.4482 | CD6: 1900.1536 | CE6: 1904.6718 | CF6: 2065.1564 | CG6: 2199.8945 | CH6: 2223.42 | CI6: 2375.8636 | CJ6: 2111.1545 | CK6: 1999.3 | CL6: =SUM(BZ6:CK6) -> 25472.278 | CM6: =SUMIF(BZ$3:CK$3,1,BZ6:CK6) -> 12497.489 | CN6: =SUMIF(BZ$2:CK$2,1,BZ6:CK6) -> 1904.6718 | CP6: =AZ6/CM6 -> 0.096158996 | CQ6: =BA6/CN6 -> 0.083507825
A7: 新規（WEB） | B7: スタンド（ＦＳ） | C7: =AM7-BE7 -> 8.6 | D7: =AN7-BF7 -> 14.2 | E7: =AO7-BG7 -> -14.862 | F7: =AP7-BH7 -> -13.462 | G7: =AQ7-BI7 -> -1.862 | H7: =AR7-BJ7 -> 0.138 | I7: =AS7-BK7 -> -752 | J7: =AT7-BL7 -> -1300 | ... O7: =AY7-BQ7 -> -13603.248 | S7: 新規（WEB） | T7: スタンド（ＦＳ） | U7: =AM7/BE7 -> #DIV/0! | V7: =AN7/BF7 -> #DIV/0! | W7: =AO7/BG7 -> 0.58557805 | X7: =AP7/BH7 -> 0.62461659 | Y7: =AQ7/BI7 -> 0.94807875 | Z7: =AR7/BJ7 -> 1.0038481 | AA7: =AS7/BK7 -> 0.035897436 | AB7: =AT7/BL7 -> 0 | ... AG7: =AY7/BQ7 -> 0.011926684 | AK7: 新規（WEB） | AL7: スタンド（ＦＳ） ※elepay除く | AM7: 8.6 | AN7: 14.2 | AO7: 21 | AP7: 22.4 | AQ7: 34 | AR7: 36 | AS7: 28 | AY7: =SUM(AM7:AX7) -> 164.2 | AZ7: =SUMIF(AM$3:AX$3,1,AM7:AX7) -> 164.2 | BA7: =SUMIF(AN$2:AY$2,1,AN7:AY7) -> 28 | BC7: 新規（WEB） | BD7: スタンド（ＦＳ） | BE7: =BE40*BE68 -> 0 | BF7: =BF40*BF68 -> 0 | BG7: =BG40*BG68 -> 35.862 | BH7: =BH40*BH68 -> 35.862 | BI7: =BI40*BI68 -> 35.862 | BJ7: =BJ40*BJ68 -> 35.862 | BK7: =BK40*BK68 -> 780 | BL7: =BL40*BL68 -> 1300 | ... BP7: =BP40*BP68 -> 4004 | BQ7: =SUM(BE7:BP7) -> 13767.448 | BR7: =SUMIF(BE$3:BP$3,1,BE7:BP7) -> 923.448 | BS7: =SUMIF(BF$2:BQ$2,1,BF7:BQ7) -> 780 | BX7: 新規（WEB） | BY7: スタンド（ＦＳ） | BZ7: 0 | CA7: 0 | CB7: 0 | CC7: 0 | CD7: 0 | CE7: 0 | CF7: 12.8 | CG7: 47.6 | CH7: 147 | CI7: 137.136 | CJ7: 151.809 | CK7: 128.482 | CL7: =SUM(CF7:CK7) -> 624.827 | CM7: =SUMIF(BZ$3:CK$3,1,BZ7:CK7) -> 0 | CN7: =SUMIF(BZ$2:CK$2,1,BZ7:CK7) -> 0 | CP7: =AZ7/CM7 -> #DIV/0! | CQ7: =BA7/CN7 -> #DIV/0!
A8: 新規（WEB） | B8: スタンド（社外） | C8: =AM8-BE8 -> 0 | D8: =AN8-BF8 -> 0 | E8: =AO8-BG8 -> 0 | F8: =AP8-BH8 -> 0 | G8: =AQ8-BI8 -> 0 | H8: =AR8-BJ8 -> 0 | I8: =AS8-BK8 -> -415.4475 | J8: =AT8-BL8 -> -692.4125 | ... O8: =AY8-BQ8 -> -7256.483 | S8: 新規（WEB） | T8: スタンド（社外） | U8: =AM8/BE8 -> #DIV/0! | V8: =AN8/BF8 -> #DIV/0! | W8: =AO8/BG8 -> #DIV/0! | X8: =AP8/BH8 -> #DIV/0! | Y8: =AQ8/BI8 -> #DIV/0! | Z8: =AR8/BJ8 -> #DIV/0! | AA8: =AS8/BK8 -> 0 | AB8: =AT8/BL8 -> 0 | ... AG8: =AY8/BQ8 -> 0 | AK8: 新規（WEB） | AL8: スタンド（社外） | AM8: 0 | AN8: 0 | AO8: 0 | AP8: 0 | AQ8: 0 | AR8: 0 | AS8: 0 | AY8: =SUM(AM8:AX8) -> 0 | AZ8: =SUMIF(AM$3:AX$3,1,AM8:AX8) -> 0 | BA8: =SUMIF(AN$2:AY$2,1,AN8:AY8) -> 0 | BC8: 新規（WEB） | BD8: スタンド（社外） | BE8: =BE41*BE69 -> 0 | BF8: =BF41*BF69 -> 0 | BG8: =BG41*BG69 -> 0 | BH8: =BH41*BH69 -> 0 | BI8: =BI41*BI69 -> 0 | BJ8: =BJ41*BJ69 -> 0 | BK8: =BK41*BK69 -> 415.4475 | BL8: =BL41*BL69 -> 692.4125 | ... BP8: =BP41*BP69 -> 2132.6305 | BQ8: =SUM(BE8:BP8) -> 7256.483 | BR8: =SUMIF(BE$3:BP$3,1,BE8:BP8) -> 415.4475 | BS8: =SUMIF(BF$2:BQ$2,1,BF8:BQ8) -> 415.4475 | BX8: 新規（WEB） | BY8: スタンド（社外） | BZ8: 243.30182 | CA8: 175.93091 | CB8: 284.00545 | CC8: 245.91818 | CD8: 207.20364 | CE8: 269.38182 | CF8: 235.96545 | CG8: 221.64182 | CH8: 229.62727 | CI8: 223.74727 | CJ8: 193.82182 | CK8: 229.57091 | CL8: =SUM(BZ8:CK8) -> 2760.1164 | CM8: =SUMIF(BZ$3:CK$3,1,BZ8:CK8) -> 1425.7418 | CN8: =SUMIF(BZ$2:CK$2,1,BZ8:CK8) -> 269.38182 | CP8: =AZ8/CM8 -> 0 | CQ8: =BA8/CN8 -> 0
A9: 新規（WEB） | B9: 計 | C9: =AM9-BE9 -> 104.767 | D9: =AN9-BF9 -> -5.539 | E9: =AO9-BG9 -> -79.816 | F9: =AP9-BH9 -> -52.423 | G9: =AQ9-BI9 -> -183.755 | H9: =AR9-BJ9 -> -397.443 | I9: =AS9-BK9 -> -3864.0805 | J9: =AT9-BL9 -> -6488.2725 | ... O9: =AY9-BQ9 -> -66860.723 | S9: 新規（WEB） | T9: 計 | U9: =AM9/BE9 -> 2.4606966 | V9: =AN9/BF9 -> 0.9613867 | W9: =AO9/BG9 -> 0.68205104 | X9: =AP9/BH9 -> 0.81727525 | Y9: =AQ9/BI9 -> 0.5341866 | Z9: =AR9/BJ9 -> 0.38430186 | AA9: =AS9/BK9 -> 0.046173474 | AB9: =AT9/BL9 -> 0 | ... AG9: =AY9/BQ9 -> 0.020020705 | AK9: 新規（WEB） | AL9: 計 | AM9: =SUM(AM5:AM8) -> 176.491 | AN9: =SUM(AN5:AN8) -> 137.909 | AO9: =SUM(AO5:AO8) -> 171.218 | AP9: =SUM(AP5:AP8) -> 234.473 | AQ9: =SUM(AQ5:AQ8) -> 210.727 | AR9: =SUM(AR5:AR8) -> 248.073 | AS9: =SUM(AS5:AS8) -> 187.055 | AT9: =SUM(AT5:AT8) -> 0 | ... AX9: =SUM(AX5:AX8) -> 0 | AY9: =SUM(AM9:AX9) -> 1365.946 | AZ9: =SUMIF(AM$3:AX$3,1,AM9:AX9) -> 1365.946 | BA9: =SUMIF(AN$2:AY$2,1,AN9:AY9) -> 187.055 | BC9: 新規（WEB） | BD9: 計 | BE9: =SUM(BE5:BE8) -> 71.724 | BF9: =SUM(BF5:BF8) -> 143.448 | BG9: =SUM(BG5:BG8) -> 251.034 | BH9: =SUM(BH5:BH8) -> 286.896 | BI9: =SUM(BI5:BI8) -> 394.482 | BJ9: =SUM(BJ5:BJ8) -> 645.516 | BK9: =SUM(BK5:BK8) -> 4051.1355 | BL9: =SUM(BL5:BL8) -> 6488.2725 | ... BP9: =SUM(BP5:BP8) -> 19297.66 | BQ9: =SUM(BE9:BP9) -> 68226.669 | BR9: =SUMIF(BE$3:BP$3,1,BE9:BP9) -> 5844.2355 | BS9: =SUMIF(BF$2:BQ$2,1,BF9:BQ9) -> 4051.1355 | BV9: =BQ9/$BQ$34 -> 0.20067069 | BX9: 新規（WEB） | BY9: 計 | BZ9: =SUM(BZ5:BZ8) -> 2479.33 | CA9: =SUM(CA5:CA8) -> 2267.6782 | CB9: =SUM(CB5:CB8) -> 2370.4455 | CC9: =SUM(CC5:CC8) -> 2524.3664 | CD9: =SUM(CD5:CD8) -> 2107.3573 | CE9: =SUM(CE5:CE8) -> 2174.0536 | CF9: =SUM(CF5:CF8) -> 2313.9218 | CG9: =SUM(CG5:CG8) -> 2469.1364 | ... CK9: =SUM(CK5:CK8) -> 2357.3529 | CL9: =SUM(BZ9:CK9) -> 28857.222 | CM9: =SUMIF(BZ$3:CK$3,1,BZ9:CK9) -> 13923.231 | CN9: =SUMIF(BZ$2:CK$2,1,BZ9:CK9) -> 2174.0536 | CP9: =AZ9/CM9 -> 0.098105534 | CQ9: =BA9/CN9 -> 0.086039736
A10: 新規（法人） | B10: アプリ | C10: =AM10-BE10 -> 0 | D10: =AN10-BF10 -> 0 | E10: =AO10-BG10 -> 0 | F10: =AP10-BH10 -> 0 | G10: =AQ10-BI10 -> 0 | H10: =AR10-BJ10 -> 0 | I10: =AS10-BK10 -> -420 | J10: =AT10-BL10 -> -1260 | ... O10: =AY10-BQ10 -> -14700 | S10: 新規（法人） | T10: アプリ | U10: =AM10/BE10 -> #DIV/0! | V10: =AN10/BF10 -> #DIV/0! | W10: =AO10/BG10 -> #DIV/0! | X10: =AP10/BH10 -> #DIV/0! | Y10: =AQ10/BI10 -> #DIV/0! | Z10: =AR10/BJ10 -> #DIV/0! | AA10: =AS10/BK10 -> 0 | AB10: =AT10/BL10 -> 0 | ... AG10: =AY10/BQ10 -> 0 | AK10: 新規（法人） | AL10: アプリ | AM10: 0 | AN10: 0 | AO10: 0 | AP10: 0 | AQ10: 0 | AR10: 0 | AS10: 0 | AY10: =SUM(AM10:AX10) -> 0 | AZ10: =SUMIF(AM$3:AX$3,1,AM10:AX10) -> 0 | BA10: =SUMIF(AN$2:AY$2,1,AN10:AY10) -> 0 | BC10: 新規（法人） | BD10: アプリ | BE10: =BE43*BE71 -> 0 | BF10: =BF43*BF71 -> 0 | BG10: =BG43*BG71 -> 0 | BH10: =BH43*BH71 -> 0 | BI10: =BI43*BI71 -> 0 | BJ10: =BJ43*BJ71 -> 0 | BK10: =BK43*BK71 -> 420 | BL10: =BL43*BL71 -> 1260 | ... BP10: =BP43*BP71 -> 4200 | BQ10: =SUM(BE10:BP10) -> 14700 | BR10: =SUMIF(BE$3:BP$3,1,BE10:BP10) -> 420 | BS10: =SUMIF(BF$2:BQ$2,1,BF10:BQ10) -> 420 | BX10: 新規（法人） | BY10: アプリ | BZ10: 0 | CA10: 0 | CB10: 0 | CC10: 0 | CD10: 0 | CE10: 0 | CF10: 0 | CG10: 0 | CH10: 0 | CI10: 0 | CJ10: 0 | CK10: 0 | CL10: =SUM(BZ10:CK10) -> 0 | CM10: =SUMIF(BZ$3:CK$3,1,BZ10:CK10) -> 0 | CN10: =SUMIF(BZ$2:CK$2,1,BZ10:CK10) -> 0 | CP10: =AZ10/CM10 -> #DIV/0! | CQ10: =BA10/CN10 -> #DIV/0!
A11: 新規（法人） | B11: スタンド（宅急便） | C11: =AM11-BE11 -> 0 | D11: =AN11-BF11 -> -35.862 | E11: =AO11-BG11 -> -72.240545 | F11: =AP11-BH11 -> -143.448 | G11: =AQ11-BI11 -> -143.96455 | H11: =AR11-BJ11 -> -179.82655 | I11: =AS11-BK11 -> -251.034 | J11: =AT11-BL11 -> -322.758 | ... O11: =AY11-BQ11 -> -3085.6816 | S11: 新規（法人） | T11: スタンド（宅急便） | U11: =AM11/BE11 -> #DIV/0! | V11: =AN11/BF11 -> 0 | W11: =AO11/BG11 -> 0.3285321 | X11: =AP11/BH11 -> 0 | Y11: =AQ11/BI11 -> 0.19711926 | Z11: =AR11/BJ11 -> 0.16426605 | AA11: =AS11/BK11 -> 0 | AB11: =AT11/BL11 -> 0 | ... AG11: =AY11/BQ11 -> 0.033222347 | AK11: 新規（法人） | AL11: スタンド（宅急便） ※電子M除く | AM11: 0 | AN11: 0 | AO11: 35.345455 | AP11: 0 | AQ11: 35.345455 | AR11: 35.345455 | AS11: 0 | AY11: =SUM(AM11:AX11) -> 106.03636 | AZ11: =SUMIF(AM$3:AX$3,1,AM11:AX11) -> 106.03636 | BA11: =SUMIF(AN$2:AY$2,1,AN11:AY11) -> 0 | BC11: 新規（法人） | BD11: スタンド（宅急便） | BE11: =BE44*BE72 -> 0 | BF11: =BF44*BF72 -> 35.862 | BG11: =BG44*BG72 -> 107.586 | BH11: =BH44*BH72 -> 143.448 | BI11: =BI44*BI72 -> 179.31 | BJ11: =BJ44*BJ72 -> 215.172 | BK11: =BK44*BK72 -> 251.034 | BL11: =BL44*BL72 -> 322.758 | ... BP11: =BP44*BP72 -> 537.93 | BQ11: =SUM(BE11:BP11) -> 3191.718 | BR11: =SUMIF(BE$3:BP$3,1,BE11:BP11) -> 932.412 | BS11: =SUMIF(BF$2:BQ$2,1,BF11:BQ11) -> 251.034 | BX11: 新規（法人） | BY11: スタンド（宅急便） | BZ11: 297.55636 | CA11: 359.05727 | CB11: 351.31818 | CC11: 512.75909 | CD11: 463.13818 | CE11: 761.54545 | CF11: 469.56091 | CG11: 417.02273 | CH11: 674.05091 | CI11: 494.61364 | CJ11: 494.64 | CK11: 338.94545 | CL11: =SUM(BZ11:CK11) -> 5634.2082 | CM11: =SUMIF(BZ$3:CK$3,1,BZ11:CK11) -> 2745.3745 | CN11: =SUMIF(BZ$2:CK$2,1,BZ11:CK11) -> 761.54545 | CP11: =AZ11/CM11 -> 0.038623642 | CQ11: =BA11/CN11 -> 0
A12: 新規（法人） | B12: スタンド（ＦＳ） | C12: =AM12-BE12 -> 0 | D12: =AN12-BF12 -> 239.12727 | E12: =AO12-BG12 -> 311.27273 | F12: =AP12-BH12 -> 393.01818 | G12: =AQ12-BI12 -> 252.50909 | H12: =AR12-BJ12 -> 379.745 | I12: =AS12-BK12 -> 271.727 | J12: =AT12-BL12 -> -156 | ... O12: =AY12-BQ12 -> 79.399273 | S12: 新規（法人） | T12: スタンド（ＦＳ） | U12: =AM12/BE12 -> #DIV/0! | V12: =AN12/BF12 -> #DIV/0! | W12: =AO12/BG12 -> #DIV/0! | X12: =AP12/BH12 -> #DIV/0! | Y12: =AQ12/BI12 -> #DIV/0! | Z12: =AR12/BJ12 -> #DIV/0! | AA12: =AS12/BK12 -> 6.2255192 | AB12: =AT12/BL12 -> 0 | ... AG12: =AY12/BQ12 -> 1.043626 | AK12: 新規（法人） | AL12: スタンド（ＦＳ） ※elepay除く | AM12: 0 | AN12: 239.12727 | AO12: 311.27273 | AP12: 393.01818 | AQ12: 252.50909 | AR12: 379.745 | AS12: 323.727 | AY12: =SUM(AM12:AX12) -> 1899.3993 | AZ12: =SUMIF(AM$3:AX$3,1,AM12:AX12) -> 1899.3993 | BA12: =SUMIF(AN$2:AY$2,1,AN12:AY12) -> 323.727 | BC12: 新規（法人） | BD12: スタンド（ＦＳ） | BE12: =BE45*BE73 -> 0 | BF12: =BF45*BF73 -> 0 | BG12: =BG45*BG73 -> 0 | BH12: =BH45*BH73 -> 0 | BI12: =BI45*BI73 -> 0 | BJ12: =BJ45*BJ73 -> 0 | BK12: =BK45*BK73 -> 52 | BL12: =BL45*BL73 -> 156 | ... BP12: =BP45*BP73 -> 520 | BQ12: =SUM(BE12:BP12) -> 1820 | BR12: =SUMIF(BE$3:BP$3,1,BE12:BP12) -> 52 | BS12: =SUMIF(BF$2:BQ$2,1,BF12:BQ12) -> 52 | BX12: 新規（法人） | BY12: スタンド（ＦＳ） | BZ12: 0 | CA12: 0 | CB12: 0 | CC12: 0 | CD12: 0 | CE12: 0 | CF12: 0 | CG12: 0 | CH12: 0 | CI12: 49.2 | CJ12: 106.8 | CK12: 53 | CL12: =SUM(CI12:CK12) -> 209 | CM12: =SUMIF(BZ$3:CK$3,1,BZ12:CK12) -> 0 | CN12: =SUMIF(BZ$2:CK$2,1,BZ12:CK12) -> 0 | CP12: =AZ12/CM12 -> #DIV/0! | CQ12: =BA12/CN12 -> #DIV/0!
